{
"type": "FeatureCollection",
"name": "KINUP_62_toilets",
"crs": { "type": "name", "properties": { "name": "urn:ogc:def:crs:OGC:1.3:CRS84" } },
"features": [
{ "type": "Feature", "properties": { "name": "Next", "payment_info": "Free", "accessible": "True", "radar": "Unknown", "women": "True", "men": "True", "baby_change": "Unknown", "Mon": "Unknown", "Tue": "Unknown", "Wed": "Unknown", "Thu": "Unknown", "Fri": "Unknown", "Sat": "Unknown", "Sun": "Unknown", "index_right": 82, "park_offical_id": "KINUP_62" }, "geometry": { "type": "Point", "coordinates": [ -0.351428469, 53.794783416 ] } },
{ "type": "Feature", "properties": { "name": "Marks  Spencer ", "payment_info": "Free", "accessible": "True", "radar": "Unknown", "women": "True", "men": "True", "baby_change": "Unknown", "Mon": "Unknown", "Tue": "Unknown", "Wed": "Unknown", "Thu": "Unknown", "Fri": "Unknown", "Sat": "Unknown", "Sun": "Unknown", "index_right": 82, "park_offical_id": "KINUP_62" }, "geometry": { "type": "Point", "coordinates": [ -0.349430576, 53.795124549 ] } },
{ "type": "Feature", "properties": { "name": "ASDA Kingswood", "payment_info": "Free", "accessible": "True", "radar": "Unknown", "women": "True", "men": "True", "baby_change": "True", "Mon": "00:00-00:00", "Tue": "00:00-00:00", "Wed": "00:00-00:00", "Thu": "00:00-00:00", "Fri": "00:00-00:00", "Sat": "00:00-00:00", "Sun": "00:00-00:00", "index_right": 82, "park_offical_id": "KINUP_62" }, "geometry": { "type": "Point", "coordinates": [ -0.345747471, 53.79439632 ] } }
]
}
