{
"type": "FeatureCollection",
"name": "KINUP_57_toilets",
"crs": { "type": "name", "properties": { "name": "urn:ogc:def:crs:OGC:1.3:CRS84" } },
"features": [
{ "type": "Feature", "properties": { "name": "Cheryls Cafe", "payment_info": "Cost unknown", "accessible": "True", "radar": "False", "women": "Unknown", "men": "Unknown", "baby_change": "True", "Mon": "09:00-17:00", "Tue": "09:00-17:00", "Wed": "09:00-17:00", "Thu": "09:00-17:00", "Fri": "09:00-17:00", "Sat": "09:00-17:00", "Sun": "09:00-17:00", "index_right": 76, "park_offical_id": "KINUP_57" }, "geometry": { "type": "Point", "coordinates": [ -0.369545948, 53.734427545 ] } }
]
}
