{
"type": "FeatureCollection",
"name": "NORLI_37_toilets",
"crs": { "type": "name", "properties": { "name": "urn:ogc:def:crs:OGC:1.3:CRS84" } },
"features": [
{ "type": "Feature", "properties": { "name": "Sillica Lodge Garden centre", "payment_info": "Free", "accessible": "Unknown", "radar": "False", "women": "True", "men": "True", "baby_change": "Unknown", "Mon": "Unknown", "Tue": "Unknown", "Wed": "Unknown", "Thu": "Unknown", "Fri": "Unknown", "Sat": "Unknown", "Sun": "Unknown", "index_right": 91, "park_offical_id": "NORLI_37" }, "geometry": { "type": "Point", "coordinates": [ -0.683188116, 53.559158141 ] } },
{ "type": "Feature", "properties": { "name": "Asda", "payment_info": "Free", "accessible": "Unknown", "radar": "False", "women": "True", "men": "True", "baby_change": "Unknown", "Mon": "Unknown", "Tue": "Unknown", "Wed": "Unknown", "Thu": "Unknown", "Fri": "Unknown", "Sat": "Unknown", "Sun": "Unknown", "index_right": 91, "park_offical_id": "NORLI_37" }, "geometry": { "type": "Point", "coordinates": [ -0.684617601, 53.56539451 ] } }
]
}
