{
"type": "FeatureCollection",
"name": "YORK__77",
"crs": { "type": "name", "properties": { "name": "urn:ogc:def:crs:OGC:1.3:CRS84" } },
"features": [
{ "type": "Feature", "properties": { "osm_id": 12012859916, "name": null, "amenity": null, "man_made": null, "leisure": "picnic_table", "playground": null, "memorial": null }, "geometry": { "type": "Point", "coordinates": [ -1.1287089, 53.99915 ] } },
{ "type": "Feature", "properties": { "osm_id": 12012859915, "name": null, "amenity": "bench", "man_made": null, "leisure": null, "playground": null, "memorial": null }, "geometry": { "type": "Point", "coordinates": [ -1.1287293, 53.9991671 ] } }
]
}
