{
"type": "FeatureCollection",
"name": "YORK__26",
"crs": { "type": "name", "properties": { "name": "urn:ogc:def:crs:OGC:1.3:CRS84" } },
"features": [
{ "type": "Feature", "properties": { "osm_id": 10899974949, "name": null, "amenity": null, "man_made": null, "leisure": "picnic_table", "playground": null, "memorial": null }, "geometry": { "type": "Point", "coordinates": [ -1.0878968, 53.939668 ] } },
{ "type": "Feature", "properties": { "osm_id": 10899974948, "name": null, "amenity": "bench", "man_made": null, "leisure": null, "playground": null, "memorial": null }, "geometry": { "type": "Point", "coordinates": [ -1.0884081, 53.9399658 ] } },
{ "type": "Feature", "properties": { "osm_id": 10899974947, "name": null, "amenity": "bench", "man_made": null, "leisure": null, "playground": null, "memorial": null }, "geometry": { "type": "Point", "coordinates": [ -1.0878215, 53.940201 ] } },
{ "type": "Feature", "properties": { "osm_id": 10899974946, "name": null, "amenity": "bench", "man_made": null, "leisure": null, "playground": null, "memorial": null }, "geometry": { "type": "Point", "coordinates": [ -1.0878575, 53.9404766 ] } },
{ "type": "Feature", "properties": { "osm_id": 10899974944, "name": null, "amenity": "bench", "man_made": null, "leisure": null, "playground": null, "memorial": null }, "geometry": { "type": "Point", "coordinates": [ -1.0881186, 53.9405464 ] } },
{ "type": "Feature", "properties": { "osm_id": 10899974943, "name": null, "amenity": "bench", "man_made": null, "leisure": null, "playground": null, "memorial": null }, "geometry": { "type": "Point", "coordinates": [ -1.088029, 53.9406308 ] } }
]
}
