{
"type": "FeatureCollection",
"name": "YORK__97",
"crs": { "type": "name", "properties": { "name": "urn:ogc:def:crs:OGC:1.3:CRS84" } },
"features": [
{ "type": "Feature", "properties": { "osm_id": 11898535332, "name": null, "amenity": "bench", "man_made": null, "leisure": null, "playground": null, "memorial": null }, "geometry": { "type": "Point", "coordinates": [ -1.085627, 53.9587685 ] } },
{ "type": "Feature", "properties": { "osm_id": 1533603977, "name": null, "amenity": "bench", "man_made": null, "leisure": null, "playground": null, "memorial": null }, "geometry": { "type": "Point", "coordinates": [ -1.0859691, 53.9587781 ] } },
{ "type": "Feature", "properties": { "osm_id": 1533604117, "name": null, "amenity": "bench", "man_made": null, "leisure": null, "playground": null, "memorial": null }, "geometry": { "type": "Point", "coordinates": [ -1.0860143, 53.9590128 ] } },
{ "type": "Feature", "properties": { "osm_id": 1533603975, "name": null, "amenity": "bench", "man_made": null, "leisure": null, "playground": null, "memorial": null }, "geometry": { "type": "Point", "coordinates": [ -1.0864301, 53.9592312 ] } },
{ "type": "Feature", "properties": { "osm_id": 1533603974, "name": null, "amenity": "bench", "man_made": null, "leisure": null, "playground": null, "memorial": null }, "geometry": { "type": "Point", "coordinates": [ -1.0866031, 53.9593287 ] } },
{ "type": "Feature", "properties": { "osm_id": 1533603972, "name": null, "amenity": "bench", "man_made": null, "leisure": null, "playground": null, "memorial": null }, "geometry": { "type": "Point", "coordinates": [ -1.0868197, 53.9594478 ] } },
{ "type": "Feature", "properties": { "osm_id": 1533603978, "name": null, "amenity": "bench", "man_made": null, "leisure": null, "playground": null, "memorial": null }, "geometry": { "type": "Point", "coordinates": [ -1.0870356, 53.9595449 ] } }
]
}
