{
"type": "FeatureCollection",
"name": "0b326b4f6dff_visibility",
"crs": { "type": "name", "properties": { "name": "urn:ogc:def:crs:OGC:1.3:CRS84" } },
"features": [
{ "type": "Feature", "properties": { "visible_points": 1, "total_points": 46, "visibility_pct": 2.1739130434782608 }, "geometry": { "type": "Point", "coordinates": [ -1.224744170538813, 53.478844625717102 ] } },
{ "type": "Feature", "properties": { "visible_points": 4, "total_points": 46, "visibility_pct": 8.695652173913043 }, "geometry": { "type": "Point", "coordinates": [ -1.224535408619629, 53.478843272539507 ] } },
{ "type": "Feature", "properties": { "visible_points": 0, "total_points": 43, "visibility_pct": 0.0 }, "geometry": { "type": "Point", "coordinates": [ -1.224326646717383, 53.478841918997219 ] } },
{ "type": "Feature", "properties": { "visible_points": 3, "total_points": 47, "visibility_pct": 6.3829787234042552 }, "geometry": { "type": "Point", "coordinates": [ -1.224846588395957, 53.478953153136928 ] } },
{ "type": "Feature", "properties": { "visible_points": 0, "total_points": 47, "visibility_pct": 0.0 }, "geometry": { "type": "Point", "coordinates": [ -1.224637825939664, 53.478951800136464 ] } },
{ "type": "Feature", "properties": { "visible_points": 0, "total_points": 47, "visibility_pct": 0.0 }, "geometry": { "type": "Point", "coordinates": [ -1.224429063500321, 53.478950446771336 ] } },
{ "type": "Feature", "properties": { "visible_points": 3, "total_points": 47, "visibility_pct": 6.3829787234042552 }, "geometry": { "type": "Point", "coordinates": [ -1.224949006773234, 53.479061680468796 ] } },
{ "type": "Feature", "properties": { "visible_points": 1, "total_points": 47, "visibility_pct": 2.1276595744680851 }, "geometry": { "type": "Point", "coordinates": [ -1.224740243779844, 53.479060327645477 ] } },
{ "type": "Feature", "properties": { "visible_points": 0, "total_points": 47, "visibility_pct": 0.0 }, "geometry": { "type": "Point", "coordinates": [ -1.224531480803392, 53.479058974457466 ] } },
{ "type": "Feature", "properties": { "visible_points": 0, "total_points": 47, "visibility_pct": 0.0 }, "geometry": { "type": "Point", "coordinates": [ -1.224322717843896, 53.479057620904776 ] } },
{ "type": "Feature", "properties": { "visible_points": 1, "total_points": 47, "visibility_pct": 2.1276595744680851 }, "geometry": { "type": "Point", "coordinates": [ -1.225051425670662, 53.479170207712713 ] } },
{ "type": "Feature", "properties": { "visible_points": 1, "total_points": 47, "visibility_pct": 2.1276595744680851 }, "geometry": { "type": "Point", "coordinates": [ -1.224842662140164, 53.479168855066511 ] } },
{ "type": "Feature", "properties": { "visible_points": 1, "total_points": 47, "visibility_pct": 2.1276595744680851 }, "geometry": { "type": "Point", "coordinates": [ -1.224633898626609, 53.479167502055638 ] } },
{ "type": "Feature", "properties": { "visible_points": 0, "total_points": 47, "visibility_pct": 0.0 }, "geometry": { "type": "Point", "coordinates": [ -1.22442513513, 53.4791661486801 ] } },
{ "type": "Feature", "properties": { "visible_points": 2, "total_points": 43, "visibility_pct": 4.6511627906976747 }, "geometry": { "type": "Point", "coordinates": [ -1.225153845088244, 53.479278734868636 ] } },
{ "type": "Feature", "properties": { "visible_points": 2, "total_points": 46, "visibility_pct": 4.3478260869565215 }, "geometry": { "type": "Point", "coordinates": [ -1.224945081020637, 53.47927738239958 ] } },
{ "type": "Feature", "properties": { "visible_points": 1, "total_points": 47, "visibility_pct": 2.1276595744680851 }, "geometry": { "type": "Point", "coordinates": [ -1.224736316969965, 53.47927602956586 ] } },
{ "type": "Feature", "properties": { "visible_points": 0, "total_points": 47, "visibility_pct": 0.0 }, "geometry": { "type": "Point", "coordinates": [ -1.224527552936246, 53.479274676367424 ] } },
{ "type": "Feature", "properties": { "visible_points": 0, "total_points": 47, "visibility_pct": 0.0 }, "geometry": { "type": "Point", "coordinates": [ -1.224318788919475, 53.479273322804332 ] } },
{ "type": "Feature", "properties": { "visible_points": 1, "total_points": 41, "visibility_pct": 2.4390243902439024 }, "geometry": { "type": "Point", "coordinates": [ -1.225047500421259, 53.479385909644684 ] } },
{ "type": "Feature", "properties": { "visible_points": 0, "total_points": 44, "visibility_pct": 0.0 }, "geometry": { "type": "Point", "coordinates": [ -1.224629971262642, 53.479383203966812 ] } },
{ "type": "Feature", "properties": { "visible_points": 0, "total_points": 44, "visibility_pct": 0.0 }, "geometry": { "type": "Point", "coordinates": [ -1.224421206708751, 53.479381850580843 ] } }
]
}
