{
"type": "FeatureCollection",
"name": "9dca28751fbf_visibility",
"crs": { "type": "name", "properties": { "name": "urn:ogc:def:crs:OGC:1.3:CRS84" } },
"features": [
{ "type": "Feature", "properties": { "visible_points": 0, "total_points": 47, "visibility_pct": 0.0 }, "geometry": { "type": "Point", "coordinates": [ -1.12968003315393, 53.491838389683473 ] } },
{ "type": "Feature", "properties": { "visible_points": 1, "total_points": 47, "visibility_pct": 2.1276595744680851 }, "geometry": { "type": "Point", "coordinates": [ -1.129471205662494, 53.491836870556142 ] } },
{ "type": "Feature", "properties": { "visible_points": 0, "total_points": 52, "visibility_pct": 0.0 }, "geometry": { "type": "Point", "coordinates": [ -1.12978224170806, 53.491946999595037 ] } },
{ "type": "Feature", "properties": { "visible_points": 0, "total_points": 53, "visibility_pct": 0.0 }, "geometry": { "type": "Point", "coordinates": [ -1.129573413679663, 53.491945480657748 ] } },
{ "type": "Feature", "properties": { "visible_points": 0, "total_points": 57, "visibility_pct": 0.0 }, "geometry": { "type": "Point", "coordinates": [ -1.129884450772969, 53.492055609216777 ] } },
{ "type": "Feature", "properties": { "visible_points": 0, "total_points": 57, "visibility_pct": 0.0 }, "geometry": { "type": "Point", "coordinates": [ -1.129675622233937, 53.492054090478916 ] } },
{ "type": "Feature", "properties": { "visible_points": 0, "total_points": 56, "visibility_pct": 0.0 }, "geometry": { "type": "Point", "coordinates": [ -1.129466793712926, 53.492052571375517 ] } },
{ "type": "Feature", "properties": { "visible_points": 0, "total_points": 57, "visibility_pct": 0.0 }, "geometry": { "type": "Point", "coordinates": [ -1.129986660324443, 53.492164218622293 ] } },
{ "type": "Feature", "properties": { "visible_points": 2, "total_points": 57, "visibility_pct": 3.5087719298245612 }, "geometry": { "type": "Point", "coordinates": [ -1.129777831283375, 53.492162700086617 ] } },
{ "type": "Feature", "properties": { "visible_points": 0, "total_points": 57, "visibility_pct": 0.0 }, "geometry": { "type": "Point", "coordinates": [ -1.12956900226032, 53.492161181185416 ] } },
{ "type": "Feature", "properties": { "visible_points": 0, "total_points": 56, "visibility_pct": 0.0 }, "geometry": { "type": "Point", "coordinates": [ -1.130088870359928, 53.492272827915521 ] } },
{ "type": "Feature", "properties": { "visible_points": 0, "total_points": 57, "visibility_pct": 0.0 }, "geometry": { "type": "Point", "coordinates": [ -1.129880040816818, 53.492271309582058 ] } },
{ "type": "Feature", "properties": { "visible_points": 0, "total_points": 57, "visibility_pct": 0.0 }, "geometry": { "type": "Point", "coordinates": [ -1.129671211291716, 53.492269790883036 ] } },
{ "type": "Feature", "properties": { "visible_points": 0, "total_points": 57, "visibility_pct": 0.0 }, "geometry": { "type": "Point", "coordinates": [ -1.129462381784647, 53.492268271818446 ] } },
{ "type": "Feature", "properties": { "visible_points": 0, "total_points": 53, "visibility_pct": 0.0 }, "geometry": { "type": "Point", "coordinates": [ -1.129982250834271, 53.492379918965199 ] } },
{ "type": "Feature", "properties": { "visible_points": 0, "total_points": 54, "visibility_pct": 0.0 }, "geometry": { "type": "Point", "coordinates": [ -1.129773420807132, 53.492378400468368 ] } },
{ "type": "Feature", "properties": { "visible_points": 0, "total_points": 54, "visibility_pct": 0.0 }, "geometry": { "type": "Point", "coordinates": [ -1.129564590798005, 53.492376881605992 ] } },
{ "type": "Feature", "properties": { "visible_points": 0, "total_points": 53, "visibility_pct": 0.0 }, "geometry": { "type": "Point", "coordinates": [ -1.129355760806905, 53.492375362378041 ] } },
{ "type": "Feature", "properties": { "visible_points": 0, "total_points": 49, "visibility_pct": 0.0 }, "geometry": { "type": "Point", "coordinates": [ -1.129875630806553, 53.492487009941442 ] } },
{ "type": "Feature", "properties": { "visible_points": 3, "total_points": 50, "visibility_pct": 6.0 }, "geometry": { "type": "Point", "coordinates": [ -1.129666800295381, 53.492485491281222 ] } },
{ "type": "Feature", "properties": { "visible_points": 3, "total_points": 49, "visibility_pct": 6.1224489795918364 }, "geometry": { "type": "Point", "coordinates": [ -1.129457969802228, 53.492483972255485 ] } },
{ "type": "Feature", "properties": { "visible_points": 3, "total_points": 46, "visibility_pct": 6.5217391304347823 }, "geometry": { "type": "Point", "coordinates": [ -1.129249139327091, 53.492482452864159 ] } },
{ "type": "Feature", "properties": { "visible_points": 3, "total_points": 44, "visibility_pct": 6.8181818181818175 }, "geometry": { "type": "Point", "coordinates": [ -1.129769010276769, 53.492594100844201 ] } }
]
}
