{
"type": "FeatureCollection",
"name": "BRADF_378_lighting",
"crs": { "type": "name", "properties": { "name": "urn:ogc:def:crs:OGC:1.3:CRS84" } },
"features": [
{"type":"Feature","properties":{"Park Feature":"Street Light"},"geometry":{"type":"Point","coordinates":[-1.711972212529191,53.804131235450726]}},
{"type":"Feature","properties":{"Park Feature":"Street Light"},"geometry":{"type":"Point","coordinates":[-1.711972212529191,53.804131235450726]}},
{"type":"Feature","properties":{"Park Feature":"Street Light"},"geometry":{"type":"Point","coordinates":[-1.712460801125889,53.804402941473661]}},
{"type":"Feature","properties":{"Park Feature":"Street Light"},"geometry":{"type":"Point","coordinates":[-1.712460801125889,53.804402941473661]}},
{"type":"Feature","properties":{"Park Feature":"Street Light"},"geometry":{"type":"Point","coordinates":[-1.710302682000161,53.803365947987828]}},
{"type":"Feature","properties":{"Park Feature":"Street Light"},"geometry":{"type":"Point","coordinates":[-1.710624485673744,53.803600409300756]}},
{"type":"Feature","properties":{"Park Feature":"Street Light"},"geometry":{"type":"Point","coordinates":[-1.711180070697646,53.80362061822369]}},
{"type":"Feature","properties":{"Park Feature":"Street Light"},"geometry":{"type":"Point","coordinates":[-1.711180070697646,53.80362061822369]}},
{"type":"Feature","properties":{"Park Feature":"Street Light"},"geometry":{"type":"Point","coordinates":[-1.711442610046363,53.803863024335804]}},
{"type":"Feature","properties":{"Park Feature":"Street Light"},"geometry":{"type":"Point","coordinates":[-1.711442610046363,53.803863024335804]}},
{"type":"Feature","properties":{"Park Feature":"Street Light"},"geometry":{"type":"Point","coordinates":[-1.710766924007549,53.803864099273632]}},
{"type":"Feature","properties":{"Park Feature":"Street Light"},"geometry":{"type":"Point","coordinates":[-1.710313011176543,53.804073326482062]}},
{"type":"Feature","properties":{"Park Feature":"Street Light"},"geometry":{"type":"Point","coordinates":[-1.709964311338159,53.804438297430529]}},
{"type":"Feature","properties":{"Park Feature":"Street Light"},"geometry":{"type":"Point","coordinates":[-1.710199542559985,53.80467704523933]}},
{"type":"Feature","properties":{"Park Feature":"Street Light"},"geometry":{"type":"Point","coordinates":[-1.711058006102308,53.80481662477014]}},
{"type":"Feature","properties":{"Park Feature":"Street Light"},"geometry":{"type":"Point","coordinates":[-1.711397830086238,53.804860582202188]}},
{"type":"Feature","properties":{"Park Feature":"Street Light"},"geometry":{"type":"Point","coordinates":[-1.709177831543627,53.80354928698555]}},
{"type":"Feature","properties":{"Park Feature":"Street Light"},"geometry":{"type":"Point","coordinates":[-1.709575600224255,53.803555640024783]}},
{"type":"Feature","properties":{"Park Feature":"Street Light"},"geometry":{"type":"Point","coordinates":[-1.708950421102215,53.803719508912387]}},
{"type":"Feature","properties":{"Park Feature":"Street Light"},"geometry":{"type":"Point","coordinates":[-1.70927385593853,53.803936900613593]}},
{"type":"Feature","properties":{"Park Feature":"Street Light"},"geometry":{"type":"Point","coordinates":[-1.70901794852045,53.804276027730481]}},
{"type":"Feature","properties":{"Park Feature":"Street Light"},"geometry":{"type":"Point","coordinates":[-1.709327425466557,53.804536527813703]}},
{"type":"Feature","properties":{"Park Feature":"Street Light"},"geometry":{"type":"Point","coordinates":[-1.709704036664053,53.804750451549573]}},
{"type":"Feature","properties":{"Park Feature":"Street Light"},"geometry":{"type":"Point","coordinates":[-1.710577862672358,53.804864006437207]}}
]
}
