{
"type": "FeatureCollection",
"name": "NORYO_495",
"crs": { "type": "name", "properties": { "name": "urn:ogc:def:crs:OGC:1.3:CRS84" } },
"features": [
{ "type": "Feature", "properties": { "osm_id": 7419821268, "name": null, "amenity": "bench", "man_made": null, "leisure": null, "playground": null, "memorial": null }, "geometry": { "type": "Point", "coordinates": [ -0.4049306, 54.2810318 ] } },
{ "type": "Feature", "properties": { "osm_id": 7419821265, "name": null, "amenity": "bench", "man_made": null, "leisure": null, "playground": null, "memorial": null }, "geometry": { "type": "Point", "coordinates": [ -0.4048287, 54.2810851 ] } },
{ "type": "Feature", "properties": { "osm_id": 7419821281, "name": null, "amenity": "bench", "man_made": null, "leisure": null, "playground": null, "memorial": null }, "geometry": { "type": "Point", "coordinates": [ -0.4049601, 54.2811853 ] } },
{ "type": "Feature", "properties": { "osm_id": 7419821259, "name": null, "amenity": "bench", "man_made": null, "leisure": null, "playground": null, "memorial": null }, "geometry": { "type": "Point", "coordinates": [ -0.4052875, 54.2812486 ] } }
]
}
