{
"type": "FeatureCollection",
"name": "NORYO_75",
"crs": { "type": "name", "properties": { "name": "urn:ogc:def:crs:OGC:1.3:CRS84" } },
"features": [
{ "type": "Feature", "properties": { "osm_id": 10916064640, "name": null, "amenity": "bench", "man_made": null, "leisure": null, "playground": null, "memorial": null }, "geometry": { "type": "Point", "coordinates": [ -1.0883807, 53.7675771 ] } },
{ "type": "Feature", "properties": { "osm_id": 10916177905, "name": null, "amenity": "bench", "man_made": null, "leisure": null, "playground": null, "memorial": null }, "geometry": { "type": "Point", "coordinates": [ -1.0889237, 53.7675821 ] } },
{ "type": "Feature", "properties": { "osm_id": 10916176622, "name": null, "amenity": "bench", "man_made": null, "leisure": null, "playground": null, "memorial": null }, "geometry": { "type": "Point", "coordinates": [ -1.0884486, 53.7675932 ] } },
{ "type": "Feature", "properties": { "osm_id": 10916177383, "name": null, "amenity": "bench", "man_made": null, "leisure": null, "playground": null, "memorial": null }, "geometry": { "type": "Point", "coordinates": [ -1.0890567, 53.7676074 ] } },
{ "type": "Feature", "properties": { "osm_id": 10916086876, "name": null, "amenity": "bench", "man_made": null, "leisure": null, "playground": null, "memorial": null }, "geometry": { "type": "Point", "coordinates": [ -1.0895093, 53.767704 ] } }
]
}
