{
"type": "FeatureCollection",
"name": "NORYO_567",
"crs": { "type": "name", "properties": { "name": "urn:ogc:def:crs:OGC:1.3:CRS84" } },
"features": [
{ "type": "Feature", "properties": { "osm_id": 1400317756, "name": null, "amenity": "bench", "man_made": null, "leisure": null, "playground": null, "memorial": null }, "geometry": { "type": "Point", "coordinates": [ -0.7754427, 54.2447703 ] } },
{ "type": "Feature", "properties": { "osm_id": 1400317814, "name": null, "amenity": "bench", "man_made": null, "leisure": null, "playground": null, "memorial": null }, "geometry": { "type": "Point", "coordinates": [ -0.7753918, 54.244775 ] } },
{ "type": "Feature", "properties": { "osm_id": 1400317744, "name": null, "amenity": "bench", "man_made": null, "leisure": null, "playground": null, "memorial": null }, "geometry": { "type": "Point", "coordinates": [ -0.7753421, 54.2447867 ] } },
{ "type": "Feature", "properties": { "osm_id": 1400317761, "name": null, "amenity": "bench", "man_made": null, "leisure": null, "playground": null, "memorial": null }, "geometry": { "type": "Point", "coordinates": [ -0.7752778, 54.2448118 ] } },
{ "type": "Feature", "properties": { "osm_id": 1400317820, "name": null, "amenity": "bench", "man_made": null, "leisure": null, "playground": null, "memorial": null }, "geometry": { "type": "Point", "coordinates": [ -0.7752335, 54.2448557 ] } },
{ "type": "Feature", "properties": { "osm_id": 1400348901, "name": null, "amenity": "bench", "man_made": null, "leisure": null, "playground": null, "memorial": null }, "geometry": { "type": "Point", "coordinates": [ -0.7752375, 54.2449066 ] } },
{ "type": "Feature", "properties": { "osm_id": 1400317816, "name": null, "amenity": "bench", "man_made": null, "leisure": null, "playground": null, "memorial": null }, "geometry": { "type": "Point", "coordinates": [ -0.7755296, 54.2449589 ] } },
{ "type": "Feature", "properties": { "osm_id": 1400317850, "name": null, "amenity": "bench", "man_made": null, "leisure": null, "playground": null, "memorial": null }, "geometry": { "type": "Point", "coordinates": [ -0.7754983, 54.2449725 ] } },
{ "type": "Feature", "properties": { "osm_id": 1400317760, "name": null, "amenity": "bench", "man_made": null, "leisure": null, "playground": null, "memorial": null }, "geometry": { "type": "Point", "coordinates": [ -0.7754727, 54.2449784 ] } },
{ "type": "Feature", "properties": { "osm_id": 1400317804, "name": null, "amenity": "bench", "man_made": null, "leisure": null, "playground": null, "memorial": null }, "geometry": { "type": "Point", "coordinates": [ -0.7754327, 54.2449891 ] } }
]
}
