{
"type": "FeatureCollection",
"name": "NORYO_52",
"crs": { "type": "name", "properties": { "name": "urn:ogc:def:crs:OGC:1.3:CRS84" } },
"features": [
{ "type": "Feature", "properties": { "osm_id": 4356817812, "name": null, "amenity": "bench", "man_made": null, "leisure": null, "playground": null, "memorial": null }, "geometry": { "type": "Point", "coordinates": [ -1.2764317, 54.0957157 ] } },
{ "type": "Feature", "properties": { "osm_id": 4356817817, "name": null, "amenity": "bench", "man_made": null, "leisure": null, "playground": null, "memorial": null }, "geometry": { "type": "Point", "coordinates": [ -1.2767991, 54.0958936 ] } },
{ "type": "Feature", "properties": { "osm_id": 4356817808, "name": null, "amenity": "bench", "man_made": null, "leisure": null, "playground": null, "memorial": null }, "geometry": { "type": "Point", "coordinates": [ -1.2760588, 54.095958 ] } }
]
}
