{
"type": "FeatureCollection",
"name": "NORYO_854",
"crs": { "type": "name", "properties": { "name": "urn:ogc:def:crs:OGC:1.3:CRS84" } },
"features": [
{ "type": "Feature", "properties": { "osm_id": 8837675794, "name": null, "amenity": "bench", "man_made": null, "leisure": null, "playground": null, "memorial": null }, "geometry": { "type": "Point", "coordinates": [ -1.4278783, 54.3429411 ] } },
{ "type": "Feature", "properties": { "osm_id": 8837677080, "name": null, "amenity": "bench", "man_made": null, "leisure": null, "playground": null, "memorial": null }, "geometry": { "type": "Point", "coordinates": [ -1.4280931, 54.3436471 ] } },
{ "type": "Feature", "properties": { "osm_id": 8837732228, "name": null, "amenity": "bench", "man_made": null, "leisure": null, "playground": null, "memorial": null }, "geometry": { "type": "Point", "coordinates": [ -1.4290432, 54.3413787 ] } },
{ "type": "Feature", "properties": { "osm_id": 8837732230, "name": null, "amenity": "bench", "man_made": null, "leisure": null, "playground": null, "memorial": null }, "geometry": { "type": "Point", "coordinates": [ -1.4291439, 54.3413856 ] } },
{ "type": "Feature", "properties": { "osm_id": 8837732229, "name": null, "amenity": "bench", "man_made": null, "leisure": null, "playground": null, "memorial": null }, "geometry": { "type": "Point", "coordinates": [ -1.4291806, 54.341431 ] } },
{ "type": "Feature", "properties": { "osm_id": 8837677590, "name": null, "amenity": "bench", "man_made": null, "leisure": null, "playground": null, "memorial": null }, "geometry": { "type": "Point", "coordinates": [ -1.4285483, 54.3423268 ] } },
{ "type": "Feature", "properties": { "osm_id": 8837687703, "name": null, "amenity": "bench", "man_made": null, "leisure": null, "playground": null, "memorial": null }, "geometry": { "type": "Point", "coordinates": [ -1.4283045, 54.3425901 ] } }
]
}
