{
"type": "FeatureCollection",
"name": "NORYO_1011",
"crs": { "type": "name", "properties": { "name": "urn:ogc:def:crs:OGC:1.3:CRS84" } },
"features": [
{ "type": "Feature", "properties": { "osm_id": 8986727457, "name": null, "amenity": "bench", "man_made": null, "leisure": null, "playground": null, "memorial": null }, "geometry": { "type": "Point", "coordinates": [ -2.0259743, 53.9486024 ] } },
{ "type": "Feature", "properties": { "osm_id": 8986727459, "name": null, "amenity": "bench", "man_made": null, "leisure": null, "playground": null, "memorial": null }, "geometry": { "type": "Point", "coordinates": [ -2.0292307, 53.9502437 ] } },
{ "type": "Feature", "properties": { "osm_id": 8986727461, "name": null, "amenity": null, "man_made": null, "leisure": "picnic_table", "playground": null, "memorial": null }, "geometry": { "type": "Point", "coordinates": [ -2.0306252, 53.9508538 ] } },
{ "type": "Feature", "properties": { "osm_id": 8986727462, "name": null, "amenity": null, "man_made": null, "leisure": "picnic_table", "playground": null, "memorial": null }, "geometry": { "type": "Point", "coordinates": [ -2.030617, 53.950971 ] } },
{ "type": "Feature", "properties": { "osm_id": 8986727460, "name": null, "amenity": "bench", "man_made": null, "leisure": null, "playground": null, "memorial": null }, "geometry": { "type": "Point", "coordinates": [ -2.0293446, 53.9510715 ] } }
]
}
