{
"type": "FeatureCollection",
"name": "BRADF_75_toilets",
"crs": { "type": "name", "properties": { "name": "urn:ogc:def:crs:OGC:1.3:CRS84" } },
"features": [
{ "type": "Feature", "properties": { "name": "Caroline Street Toilets", "payment_info": "Free", "accessible": "True", "radar": "Unknown", "women": "True", "men": "True", "baby_change": "Unknown", "Mon": "Unknown", "Tue": "Unknown", "Wed": "Unknown", "Thu": "Unknown", "Fri": "Unknown", "Sat": "Unknown", "Sun": "Unknown", "index_right": 221, "park_offical_id": "BRADF_75" }, "geometry": { "type": "Point", "coordinates": [ -1.788977087, 53.837707635 ] } },
{ "type": "Feature", "properties": { "name": "Asda Shipley", "payment_info": "Free", "accessible": "True", "radar": "Unknown", "women": "True", "men": "True", "baby_change": "True", "Mon": "06:00-00:00", "Tue": "06:00-00:00", "Wed": "06:00-00:00", "Thu": "06:00-00:00", "Fri": "06:00-00:00", "Sat": "06:00-22:00", "Sun": "10:00-16:00", "index_right": 221, "park_offical_id": "BRADF_75" }, "geometry": { "type": "Point", "coordinates": [ -1.7799188, 53.8323808 ] } },
{ "type": "Feature", "properties": { "name": "Salts Mill", "payment_info": "Free", "accessible": "False", "radar": "Unknown", "women": "True", "men": "True", "baby_change": "True", "Mon": "Closed", "Tue": "Closed", "Wed": "10:00-17:00", "Thu": "10:00-17:00", "Fri": "10:00-17:00", "Sat": "09:30-17:00", "Sun": "09:30-17:00", "index_right": 221, "park_offical_id": "BRADF_75" }, "geometry": { "type": "Point", "coordinates": [ -1.787252426, 53.838759622 ] } }
]
}
