{
"type": "FeatureCollection",
"name": "BRADF_115_toilets",
"crs": { "type": "name", "properties": { "name": "urn:ogc:def:crs:OGC:1.3:CRS84" } },
"features": [
{ "type": "Feature", "properties": { "name": "Half Moon Cafe Toilets", "payment_info": "Free", "accessible": "True", "radar": "False", "women": "True", "men": "True", "baby_change": "True", "Mon": "09:00-15:00", "Tue": "09:00-15:00", "Wed": "09:00-15:00", "Thu": "09:00-15:00", "Fri": "09:00-15:00", "Sat": "09:00-15:00", "Sun": "09:00-16:00", "index_right": 19, "park_offical_id": "BRADF_115" }, "geometry": { "type": "Point", "coordinates": [ -1.791729033, 53.841129282 ] } },
{ "type": "Feature", "properties": { "name": "Caroline Street Toilets", "payment_info": "Free", "accessible": "True", "radar": "Unknown", "women": "True", "men": "True", "baby_change": "Unknown", "Mon": "Unknown", "Tue": "Unknown", "Wed": "Unknown", "Thu": "Unknown", "Fri": "Unknown", "Sat": "Unknown", "Sun": "Unknown", "index_right": 19, "park_offical_id": "BRADF_115" }, "geometry": { "type": "Point", "coordinates": [ -1.788977087, 53.837707635 ] } },
{ "type": "Feature", "properties": { "name": "Salts Mill", "payment_info": "Free", "accessible": "False", "radar": "Unknown", "women": "True", "men": "True", "baby_change": "True", "Mon": "Closed", "Tue": "Closed", "Wed": "10:00-17:00", "Thu": "10:00-17:00", "Fri": "10:00-17:00", "Sat": "09:30-17:00", "Sun": "09:30-17:00", "index_right": 19, "park_offical_id": "BRADF_115" }, "geometry": { "type": "Point", "coordinates": [ -1.787252426, 53.838759622 ] } }
]
}
