{
"type": "FeatureCollection",
"name": "CALDE_91",
"crs": { "type": "name", "properties": { "name": "urn:ogc:def:crs:OGC:1.3:CRS84" } },
"features": [
{ "type": "Feature", "properties": { "osm_id": 4593011925, "name": null, "amenity": "bench", "man_made": null, "leisure": null, "playground": null, "memorial": null }, "geometry": { "type": "Point", "coordinates": [ -1.884009, 53.6723484 ] } },
{ "type": "Feature", "properties": { "osm_id": 4593011926, "name": null, "amenity": "bench", "man_made": null, "leisure": null, "playground": null, "memorial": null }, "geometry": { "type": "Point", "coordinates": [ -1.8830086, 53.6724962 ] } },
{ "type": "Feature", "properties": { "osm_id": 4593011927, "name": null, "amenity": "bench", "man_made": null, "leisure": null, "playground": null, "memorial": null }, "geometry": { "type": "Point", "coordinates": [ -1.8833854, 53.6728735 ] } },
{ "type": "Feature", "properties": { "osm_id": 7857618706, "name": null, "amenity": null, "man_made": null, "leisure": "picnic_table", "playground": null, "memorial": null }, "geometry": { "type": "Point", "coordinates": [ -1.8830225, 53.6729338 ] } },
{ "type": "Feature", "properties": { "osm_id": 4593011928, "name": null, "amenity": "bench", "man_made": null, "leisure": null, "playground": null, "memorial": null }, "geometry": { "type": "Point", "coordinates": [ -1.8825459, 53.6729736 ] } },
{ "type": "Feature", "properties": { "osm_id": 7857618711, "name": null, "amenity": "bench", "man_made": null, "leisure": null, "playground": null, "memorial": null }, "geometry": { "type": "Point", "coordinates": [ -1.8820952, 53.6735761 ] } },
{ "type": "Feature", "properties": { "osm_id": 7857618778, "name": null, "amenity": "bench", "man_made": null, "leisure": null, "playground": null, "memorial": null }, "geometry": { "type": "Point", "coordinates": [ -1.8835402, 53.6735936 ] } },
{ "type": "Feature", "properties": { "osm_id": 7857618712, "name": null, "amenity": "bench", "man_made": null, "leisure": null, "playground": null, "memorial": null }, "geometry": { "type": "Point", "coordinates": [ -1.8820992, 53.6736977 ] } },
{ "type": "Feature", "properties": { "osm_id": 7857618713, "name": null, "amenity": "bench", "man_made": null, "leisure": null, "playground": null, "memorial": null }, "geometry": { "type": "Point", "coordinates": [ -1.8821273, 53.6738907 ] } },
{ "type": "Feature", "properties": { "osm_id": 7857618714, "name": null, "amenity": "bench", "man_made": null, "leisure": null, "playground": null, "memorial": null }, "geometry": { "type": "Point", "coordinates": [ -1.8821501, 53.6740782 ] } },
{ "type": "Feature", "properties": { "osm_id": 7857618715, "name": null, "amenity": "bench", "man_made": null, "leisure": null, "playground": null, "memorial": null }, "geometry": { "type": "Point", "coordinates": [ -1.8822517, 53.6743102 ] } },
{ "type": "Feature", "properties": { "osm_id": 7857618707, "name": null, "amenity": null, "man_made": null, "leisure": "picnic_table", "playground": null, "memorial": null }, "geometry": { "type": "Point", "coordinates": [ -1.8840391, 53.6745052 ] } },
{ "type": "Feature", "properties": { "osm_id": 7857618710, "name": null, "amenity": "bench", "man_made": null, "leisure": null, "playground": null, "memorial": null }, "geometry": { "type": "Point", "coordinates": [ -1.8823412, 53.6745307 ] } },
{ "type": "Feature", "properties": { "osm_id": 7857618708, "name": null, "amenity": null, "man_made": null, "leisure": "picnic_table", "playground": null, "memorial": null }, "geometry": { "type": "Point", "coordinates": [ -1.8825961, 53.6752933 ] } },
{ "type": "Feature", "properties": { "osm_id": 7857618709, "name": null, "amenity": null, "man_made": null, "leisure": "picnic_table", "playground": null, "memorial": null }, "geometry": { "type": "Point", "coordinates": [ -1.8852058, 53.6759177 ] } },
{ "type": "Feature", "properties": { "osm_id": 4593011929, "name": null, "amenity": "bench", "man_made": null, "leisure": null, "playground": null, "memorial": null }, "geometry": { "type": "Point", "coordinates": [ -1.8829402, 53.6765529 ] } }
]
}
