{
"type": "FeatureCollection",
"name": "SHEFF_17",
"crs": { "type": "name", "properties": { "name": "urn:ogc:def:crs:OGC:1.3:CRS84" } },
"features": [
{ "type": "Feature", "properties": { "osm_id": 11368893991, "name": null, "amenity": "bench", "man_made": null, "leisure": null, "playground": null, "memorial": null }, "geometry": { "type": "Point", "coordinates": [ -1.4564409, 53.3636002 ] } },
{ "type": "Feature", "properties": { "osm_id": 11368893990, "name": null, "amenity": "bench", "man_made": null, "leisure": null, "playground": null, "memorial": null }, "geometry": { "type": "Point", "coordinates": [ -1.4547023, 53.3639109 ] } },
{ "type": "Feature", "properties": { "osm_id": 11368893995, "name": null, "amenity": null, "man_made": null, "leisure": "picnic_table", "playground": null, "memorial": null }, "geometry": { "type": "Point", "coordinates": [ -1.4551643, 53.3639906 ] } },
{ "type": "Feature", "properties": { "osm_id": 11368893987, "name": null, "amenity": null, "man_made": null, "leisure": "picnic_table", "playground": null, "memorial": null }, "geometry": { "type": "Point", "coordinates": [ -1.4563335, 53.3640032 ] } }
]
}
