{
"type": "FeatureCollection",
"name": "SHEFF_24",
"crs": { "type": "name", "properties": { "name": "urn:ogc:def:crs:OGC:1.3:CRS84" } },
"features": [
{ "type": "Feature", "properties": { "osm_id": 8095106645, "name": null, "amenity": "bench", "man_made": null, "leisure": null, "playground": null, "memorial": null }, "geometry": { "type": "Point", "coordinates": [ -1.4607672, 53.3790742 ] } },
{ "type": "Feature", "properties": { "osm_id": 8095106646, "name": null, "amenity": "bench", "man_made": null, "leisure": null, "playground": null, "memorial": null }, "geometry": { "type": "Point", "coordinates": [ -1.4603215, 53.3798599 ] } },
{ "type": "Feature", "properties": { "osm_id": 8095106647, "name": null, "amenity": "bench", "man_made": null, "leisure": null, "playground": null, "memorial": null }, "geometry": { "type": "Point", "coordinates": [ -1.4602088, 53.3802909 ] } }
]
}
