{
"type": "FeatureCollection",
"name": "LEEDS_35",
"crs": { "type": "name", "properties": { "name": "urn:ogc:def:crs:OGC:1.3:CRS84" } },
"features": [
{ "type": "Feature", "properties": { "osm_id": 4209816023, "name": null, "amenity": "bench", "man_made": null, "leisure": null, "playground": null, "memorial": null }, "geometry": { "type": "Point", "coordinates": [ -1.5739062, 53.8307428 ] } },
{ "type": "Feature", "properties": { "osm_id": 4209816022, "name": null, "amenity": "bench", "man_made": null, "leisure": null, "playground": null, "memorial": null }, "geometry": { "type": "Point", "coordinates": [ -1.5737641, 53.830875 ] } },
{ "type": "Feature", "properties": { "osm_id": 4209816021, "name": null, "amenity": "bench", "man_made": null, "leisure": null, "playground": null, "memorial": null }, "geometry": { "type": "Point", "coordinates": [ -1.5739492, 53.8310427 ] } },
{ "type": "Feature", "properties": { "osm_id": 4209816020, "name": null, "amenity": "bench", "man_made": null, "leisure": null, "playground": null, "memorial": null }, "geometry": { "type": "Point", "coordinates": [ -1.5741872, 53.8310921 ] } },
{ "type": "Feature", "properties": { "osm_id": 4209816018, "name": null, "amenity": "bench", "man_made": null, "leisure": null, "playground": null, "memorial": null }, "geometry": { "type": "Point", "coordinates": [ -1.5744393, 53.8312805 ] } },
{ "type": "Feature", "properties": { "osm_id": 4214304901, "name": null, "amenity": "bench", "man_made": null, "leisure": null, "playground": null, "memorial": null }, "geometry": { "type": "Point", "coordinates": [ -1.5748839, 53.8314855 ] } },
{ "type": "Feature", "properties": { "osm_id": 4214420534, "name": null, "amenity": "bench", "man_made": null, "leisure": null, "playground": null, "memorial": null }, "geometry": { "type": "Point", "coordinates": [ -1.5756574, 53.8316452 ] } },
{ "type": "Feature", "properties": { "osm_id": 4214420535, "name": null, "amenity": "bench", "man_made": null, "leisure": null, "playground": null, "memorial": null }, "geometry": { "type": "Point", "coordinates": [ -1.5744021, 53.8317932 ] } },
{ "type": "Feature", "properties": { "osm_id": 4214304899, "name": null, "amenity": "bench", "man_made": null, "leisure": null, "playground": null, "memorial": null }, "geometry": { "type": "Point", "coordinates": [ -1.5760158, 53.8321408 ] } },
{ "type": "Feature", "properties": { "osm_id": 4214420538, "name": null, "amenity": "bench", "man_made": null, "leisure": null, "playground": null, "memorial": null }, "geometry": { "type": "Point", "coordinates": [ -1.5743713, 53.8322784 ] } },
{ "type": "Feature", "properties": { "osm_id": 2801129863, "name": null, "amenity": "bench", "man_made": null, "leisure": null, "playground": null, "memorial": null }, "geometry": { "type": "Point", "coordinates": [ -1.5735651, 53.8325035 ] } },
{ "type": "Feature", "properties": { "osm_id": 2801129862, "name": null, "amenity": "bench", "man_made": null, "leisure": null, "playground": null, "memorial": null }, "geometry": { "type": "Point", "coordinates": [ -1.573515, 53.8330162 ] } },
{ "type": "Feature", "properties": { "osm_id": 4209816016, "name": null, "amenity": "bench", "man_made": null, "leisure": null, "playground": null, "memorial": null }, "geometry": { "type": "Point", "coordinates": [ -1.5752594, 53.8331024 ] } },
{ "type": "Feature", "properties": { "osm_id": 2801129861, "name": null, "amenity": "bench", "man_made": null, "leisure": null, "playground": null, "memorial": null }, "geometry": { "type": "Point", "coordinates": [ -1.5735372, 53.8334862 ] } },
{ "type": "Feature", "properties": { "osm_id": 4214304891, "name": null, "amenity": "bench", "man_made": null, "leisure": null, "playground": null, "memorial": null }, "geometry": { "type": "Point", "coordinates": [ -1.5757816, 53.8335525 ] } },
{ "type": "Feature", "properties": { "osm_id": 4214304892, "name": null, "amenity": "bench", "man_made": null, "leisure": null, "playground": null, "memorial": null }, "geometry": { "type": "Point", "coordinates": [ -1.5759479, 53.833729 ] } },
{ "type": "Feature", "properties": { "osm_id": 4214304895, "name": null, "amenity": "bench", "man_made": null, "leisure": null, "playground": null, "memorial": null }, "geometry": { "type": "Point", "coordinates": [ -1.5756877, 53.8341738 ] } }
]
}
