{
"type": "FeatureCollection",
"name": "316921bf38ed_visibility",
"crs": { "type": "name", "properties": { "name": "urn:ogc:def:crs:OGC:1.3:CRS84" } },
"features": [
{ "type": "Feature", "properties": { "visible_points": 0, "total_points": 49, "visibility_pct": 0.0 }, "geometry": { "type": "Point", "coordinates": [ -1.48951866209975, 53.672880826741213 ] } },
{ "type": "Feature", "properties": { "visible_points": 7, "total_points": 53, "visibility_pct": 13.20754716981132 }, "geometry": { "type": "Point", "coordinates": [ -1.489308926499483, 53.672879930146905 ] } },
{ "type": "Feature", "properties": { "visible_points": 4, "total_points": 54, "visibility_pct": 7.4074074074074066 }, "geometry": { "type": "Point", "coordinates": [ -1.4890991909103, 53.672879033184451 ] } },
{ "type": "Feature", "properties": { "visible_points": 0, "total_points": 48, "visibility_pct": 0.0 }, "geometry": { "type": "Point", "coordinates": [ -1.489622227952375, 53.672989120934261 ] } },
{ "type": "Feature", "properties": { "visible_points": 7, "total_points": 53, "visibility_pct": 13.20754716981132 }, "geometry": { "type": "Point", "coordinates": [ -1.489412491824534, 53.672988224572876 ] } },
{ "type": "Feature", "properties": { "visible_points": 7, "total_points": 54, "visibility_pct": 12.962962962962962 }, "geometry": { "type": "Point", "coordinates": [ -1.489202755707775, 53.67298732784333 ] } },
{ "type": "Feature", "properties": { "visible_points": 7, "total_points": 54, "visibility_pct": 12.962962962962962 }, "geometry": { "type": "Point", "coordinates": [ -1.488993019602096, 53.672986430745638 ] } },
{ "type": "Feature", "properties": { "visible_points": 0, "total_points": 54, "visibility_pct": 0.0 }, "geometry": { "type": "Point", "coordinates": [ -1.488783283507506, 53.672985533279785 ] } },
{ "type": "Feature", "properties": { "visible_points": 2, "total_points": 47, "visibility_pct": 4.2553191489361701 }, "geometry": { "type": "Point", "coordinates": [ -1.489725794321482, 53.673097414985108 ] } },
{ "type": "Feature", "properties": { "visible_points": 5, "total_points": 52, "visibility_pct": 9.6153846153846168 }, "geometry": { "type": "Point", "coordinates": [ -1.48951605766607, 53.673096518856646 ] } },
{ "type": "Feature", "properties": { "visible_points": 6, "total_points": 54, "visibility_pct": 11.111111111111111 }, "geometry": { "type": "Point", "coordinates": [ -1.48930632102173, 53.67309562236003 ] } },
{ "type": "Feature", "properties": { "visible_points": 5, "total_points": 54, "visibility_pct": 9.2592592592592595 }, "geometry": { "type": "Point", "coordinates": [ -1.48909658438847, 53.673094725495254 ] } },
{ "type": "Feature", "properties": { "visible_points": 5, "total_points": 54, "visibility_pct": 9.2592592592592595 }, "geometry": { "type": "Point", "coordinates": [ -1.4888868477663, 53.67309382826231 ] } },
{ "type": "Feature", "properties": { "visible_points": 0, "total_points": 50, "visibility_pct": 0.0 }, "geometry": { "type": "Point", "coordinates": [ -1.488677111155214, 53.673092930661234 ] } },
{ "type": "Feature", "properties": { "visible_points": 0, "total_points": 54, "visibility_pct": 0.0 }, "geometry": { "type": "Point", "coordinates": [ -1.489409886852173, 53.673203916734522 ] } },
{ "type": "Feature", "properties": { "visible_points": 0, "total_points": 54, "visibility_pct": 0.0 }, "geometry": { "type": "Point", "coordinates": [ -1.48920014969133, 53.673203020102662 ] } },
{ "type": "Feature", "properties": { "visible_points": 3, "total_points": 54, "visibility_pct": 5.5555555555555554 }, "geometry": { "type": "Point", "coordinates": [ -1.488990412541575, 53.673202123102641 ] } },
{ "type": "Feature", "properties": { "visible_points": 5, "total_points": 51, "visibility_pct": 9.8039215686274517 }, "geometry": { "type": "Point", "coordinates": [ -1.488780675402904, 53.673201225734466 ] } },
{ "type": "Feature", "properties": { "visible_points": 4, "total_points": 45, "visibility_pct": 8.8888888888888893 }, "geometry": { "type": "Point", "coordinates": [ -1.488570938275322, 53.673200327998138 ] } },
{ "type": "Feature", "properties": { "visible_points": 1, "total_points": 53, "visibility_pct": 1.8867924528301887 }, "geometry": { "type": "Point", "coordinates": [ -1.48909397783333, 53.673310417800785 ] } },
{ "type": "Feature", "properties": { "visible_points": 0, "total_points": 50, "visibility_pct": 0.0 }, "geometry": { "type": "Point", "coordinates": [ -1.488884240167074, 53.673309520665512 ] } }
]
}
