{
"type": "FeatureCollection",
"name": "4b666d231c4c_visibility",
"crs": { "type": "name", "properties": { "name": "urn:ogc:def:crs:OGC:1.3:CRS84" } },
"features": [
{ "type": "Feature", "properties": { "visible_points": 0, "total_points": 48, "visibility_pct": 0.0 }, "geometry": { "type": "Point", "coordinates": [ -1.315228525573483, 53.598186787339621 ] } },
{ "type": "Feature", "properties": { "visible_points": 4, "total_points": 48, "visibility_pct": 8.3333333333333321 }, "geometry": { "type": "Point", "coordinates": [ -1.315019174145638, 53.598185590686533 ] } },
{ "type": "Feature", "properties": { "visible_points": 0, "total_points": 47, "visibility_pct": 0.0 }, "geometry": { "type": "Point", "coordinates": [ -1.314809822732843, 53.598184393667182 ] } },
{ "type": "Feature", "properties": { "visible_points": 0, "total_points": 49, "visibility_pct": 0.0 }, "geometry": { "type": "Point", "coordinates": [ -1.315331454862894, 53.59829523404138 ] } },
{ "type": "Feature", "properties": { "visible_points": 7, "total_points": 49, "visibility_pct": 14.285714285714285 }, "geometry": { "type": "Point", "coordinates": [ -1.315122102896766, 53.598294037566696 ] } },
{ "type": "Feature", "properties": { "visible_points": 10, "total_points": 49, "visibility_pct": 20.408163265306122 }, "geometry": { "type": "Point", "coordinates": [ -1.314912750945689, 53.59829284072574 ] } },
{ "type": "Feature", "properties": { "visible_points": 2, "total_points": 48, "visibility_pct": 4.1666666666666661 }, "geometry": { "type": "Point", "coordinates": [ -1.314703399009669, 53.598291643518529 ] } },
{ "type": "Feature", "properties": { "visible_points": 7, "total_points": 49, "visibility_pct": 14.285714285714285 }, "geometry": { "type": "Point", "coordinates": [ -1.315434384675536, 53.598403680654314 ] } },
{ "type": "Feature", "properties": { "visible_points": 10, "total_points": 49, "visibility_pct": 20.408163265306122 }, "geometry": { "type": "Point", "coordinates": [ -1.315225032171125, 53.598402484358047 ] } },
{ "type": "Feature", "properties": { "visible_points": 10, "total_points": 49, "visibility_pct": 20.408163265306122 }, "geometry": { "type": "Point", "coordinates": [ -1.315015679681756, 53.598401287695488 ] } },
{ "type": "Feature", "properties": { "visible_points": 8, "total_points": 49, "visibility_pct": 16.326530612244898 }, "geometry": { "type": "Point", "coordinates": [ -1.314806327207452, 53.598400090666665 ] } },
{ "type": "Feature", "properties": { "visible_points": 5, "total_points": 49, "visibility_pct": 10.204081632653061 }, "geometry": { "type": "Point", "coordinates": [ -1.315327961968712, 53.598510931060559 ] } },
{ "type": "Feature", "properties": { "visible_points": 9, "total_points": 49, "visibility_pct": 18.367346938775512 }, "geometry": { "type": "Point", "coordinates": [ -1.31511860894106, 53.59850973457641 ] } },
{ "type": "Feature", "properties": { "visible_points": 9, "total_points": 49, "visibility_pct": 18.367346938775512 }, "geometry": { "type": "Point", "coordinates": [ -1.314909255928461, 53.598508537725969 ] } },
{ "type": "Feature", "properties": { "visible_points": 0, "total_points": 49, "visibility_pct": 0.0 }, "geometry": { "type": "Point", "coordinates": [ -1.314699902930919, 53.598507340509272 ] } },
{ "type": "Feature", "properties": { "visible_points": 8, "total_points": 49, "visibility_pct": 16.326530612244898 }, "geometry": { "type": "Point", "coordinates": [ -1.315221538723595, 53.598618181368508 ] } },
{ "type": "Feature", "properties": { "visible_points": 9, "total_points": 49, "visibility_pct": 18.367346938775512 }, "geometry": { "type": "Point", "coordinates": [ -1.315012185172698, 53.598616984696484 ] } },
{ "type": "Feature", "properties": { "visible_points": 9, "total_points": 49, "visibility_pct": 18.367346938775512 }, "geometry": { "type": "Point", "coordinates": [ -1.314802831636863, 53.598615787658176 ] } },
{ "type": "Feature", "properties": { "visible_points": 4, "total_points": 44, "visibility_pct": 9.0909090909090917 }, "geometry": { "type": "Point", "coordinates": [ -1.315324469029368, 53.598726628071766 ] } },
{ "type": "Feature", "properties": { "visible_points": 2, "total_points": 45, "visibility_pct": 4.4444444444444446 }, "geometry": { "type": "Point", "coordinates": [ -1.315115114940182, 53.598725431578146 ] } },
{ "type": "Feature", "properties": { "visible_points": 2, "total_points": 46, "visibility_pct": 4.3478260869565215 }, "geometry": { "type": "Point", "coordinates": [ -1.314905760866043, 53.598724234718254 ] } },
{ "type": "Feature", "properties": { "visible_points": 0, "total_points": 44, "visibility_pct": 0.0 }, "geometry": { "type": "Point", "coordinates": [ -1.314696406806966, 53.598723037492078 ] } }
]
}
