{
"type": "FeatureCollection",
"name": "9de5a2a6877e_visibility",
"crs": { "type": "name", "properties": { "name": "urn:ogc:def:crs:OGC:1.3:CRS84" } },
"features": [
{ "type": "Feature", "properties": { "visible_points": 1, "total_points": 55, "visibility_pct": 1.8181818181818181 }, "geometry": { "type": "Point", "coordinates": [ -1.230097199581657, 53.708776719976662 ] } },
{ "type": "Feature", "properties": { "visible_points": 0, "total_points": 50, "visibility_pct": 0.0 }, "geometry": { "type": "Point", "coordinates": [ -1.229887300674763, 53.708775373937527 ] } },
{ "type": "Feature", "properties": { "visible_points": 5, "total_points": 59, "visibility_pct": 8.4745762711864394 }, "geometry": { "type": "Point", "coordinates": [ -1.230619980704438, 53.708887929124707 ] } },
{ "type": "Feature", "properties": { "visible_points": 4, "total_points": 59, "visibility_pct": 6.7796610169491522 }, "geometry": { "type": "Point", "coordinates": [ -1.230200181742091, 53.708885238500876 ] } },
{ "type": "Feature", "properties": { "visible_points": 4, "total_points": 56, "visibility_pct": 7.1428571428571423 }, "geometry": { "type": "Point", "coordinates": [ -1.229990282286646, 53.708883892637481 ] } },
{ "type": "Feature", "properties": { "visible_points": 8, "total_points": 58, "visibility_pct": 13.793103448275861 }, "geometry": { "type": "Point", "coordinates": [ -1.230722964493336, 53.708996447211554 ] } },
{ "type": "Feature", "properties": { "visible_points": 13, "total_points": 59, "visibility_pct": 22.033898305084744 }, "geometry": { "type": "Point", "coordinates": [ -1.230513064455044, 53.708995102259216 ] } },
{ "type": "Feature", "properties": { "visible_points": 1, "total_points": 59, "visibility_pct": 1.6949152542372881 }, "geometry": { "type": "Point", "coordinates": [ -1.230303164433903, 53.708993756939215 ] } },
{ "type": "Feature", "properties": { "visible_points": 6, "total_points": 59, "visibility_pct": 10.16949152542373 }, "geometry": { "type": "Point", "coordinates": [ -1.230093264429907, 53.708992411251565 ] } },
{ "type": "Feature", "properties": { "visible_points": 0, "total_points": 55, "visibility_pct": 0.0 }, "geometry": { "type": "Point", "coordinates": [ -1.229883364443073, 53.708991065196237 ] } },
{ "type": "Feature", "properties": { "visible_points": 13, "total_points": 53, "visibility_pct": 24.528301886792452 }, "geometry": { "type": "Point", "coordinates": [ -1.230825948813627, 53.709104965212539 ] } },
{ "type": "Feature", "properties": { "visible_points": 12, "total_points": 58, "visibility_pct": 20.689655172413794 }, "geometry": { "type": "Point", "coordinates": [ -1.230616048226791, 53.70910362043594 ] } },
{ "type": "Feature", "properties": { "visible_points": 10, "total_points": 59, "visibility_pct": 16.949152542372879 }, "geometry": { "type": "Point", "coordinates": [ -1.230406147657097, 53.709102275291691 ] } },
{ "type": "Feature", "properties": { "visible_points": 10, "total_points": 59, "visibility_pct": 16.949152542372879 }, "geometry": { "type": "Point", "coordinates": [ -1.230196247104553, 53.709100929779758 ] } },
{ "type": "Feature", "properties": { "visible_points": 8, "total_points": 59, "visibility_pct": 13.559322033898304 }, "geometry": { "type": "Point", "coordinates": [ -1.229986346569166, 53.709099583900176 ] } },
{ "type": "Feature", "properties": { "visible_points": 15, "total_points": 53, "visibility_pct": 28.30188679245283 }, "geometry": { "type": "Point", "coordinates": [ -1.230719032529926, 53.70921213852678 ] } },
{ "type": "Feature", "properties": { "visible_points": 15, "total_points": 57, "visibility_pct": 26.315789473684209 }, "geometry": { "type": "Point", "coordinates": [ -1.230509131411683, 53.709210793558277 ] } },
{ "type": "Feature", "properties": { "visible_points": 14, "total_points": 59, "visibility_pct": 23.728813559322035 }, "geometry": { "type": "Point", "coordinates": [ -1.230299230310585, 53.709209448222111 ] } },
{ "type": "Feature", "properties": { "visible_points": 12, "total_points": 59, "visibility_pct": 20.33898305084746 }, "geometry": { "type": "Point", "coordinates": [ -1.23008932922664, 53.709208102518254 ] } },
{ "type": "Feature", "properties": { "visible_points": 12, "total_points": 52, "visibility_pct": 23.076923076923077 }, "geometry": { "type": "Point", "coordinates": [ -1.230612115697666, 53.709319311738994 ] } }
]
}
