{
"type": "FeatureCollection",
"name": "SHEFF_205_toilets",
"crs": { "type": "name", "properties": { "name": "urn:ogc:def:crs:OGC:1.3:CRS84" } },
"features": [
{ "type": "Feature", "properties": { "name": "Norfolk Park Toilets", "payment_info": "Free", "accessible": "True", "radar": "False", "women": "True", "men": "True", "baby_change": "True", "Mon": "Unknown", "Tue": "Unknown", "Wed": "Unknown", "Thu": "Unknown", "Fri": "Unknown", "Sat": "Unknown", "Sun": "Unknown", "index_right": 160, "park_offical_id": "SHEFF_205" }, "geometry": { "type": "Point", "coordinates": [ -1.447971761, 53.368135385 ] } }
]
}
