{
"type": "FeatureCollection",
"name": "SHEFF_98_toilets",
"crs": { "type": "name", "properties": { "name": "urn:ogc:def:crs:OGC:1.3:CRS84" } },
"features": [
{ "type": "Feature", "properties": { "name": "Chapel town Park Toilets", "payment_info": "Free", "accessible": "True", "radar": "Unknown", "women": "Unknown", "men": "Unknown", "baby_change": "True", "Mon": "09:00-18:00", "Tue": "09:00-18:00", "Wed": "09:00-18:00", "Thu": "09:00-18:00", "Fri": "09:00-18:00", "Sat": "09:00-18:00", "Sun": "09:00-18:00", "index_right": 394, "park_offical_id": "SHEFF_98" }, "geometry": { "type": "Point", "coordinates": [ -1.4642393, 53.4609435 ] } },
{ "type": "Feature", "properties": { "name": "Asda Chapeltown", "payment_info": "Cost unknown", "accessible": "True", "radar": "Unknown", "women": "True", "men": "True", "baby_change": "Unknown", "Mon": "09:00-17:00", "Tue": "09:00-17:00", "Wed": "09:00-17:00", "Thu": "09:00-17:00", "Fri": "09:00-17:00", "Sat": "09:00-17:00", "Sun": "09:00-17:00", "index_right": 394, "park_offical_id": "SHEFF_98" }, "geometry": { "type": "Point", "coordinates": [ -1.4658916, 53.462519596 ] } }
]
}
