{
"type": "FeatureCollection",
"name": "SHEFF_109_toilets",
"crs": { "type": "name", "properties": { "name": "urn:ogc:def:crs:OGC:1.3:CRS84" } },
"features": [
{ "type": "Feature", "properties": { "name": "Whirlow Brook Park", "payment_info": "Free", "accessible": "True", "radar": "False", "women": "True", "men": "True", "baby_change": "True", "Mon": "09:00-16:00", "Tue": "09:00-16:00", "Wed": "09:00-16:00", "Thu": "09:00-16:00", "Fri": "09:00-16:30", "Sat": "09:00-16:30", "Sun": "09:00-16:30", "index_right": 29, "park_offical_id": "SHEFF_109" }, "geometry": { "type": "Point", "coordinates": [ -1.538240609, 53.341081975 ] } }
]
}
