{
"type": "FeatureCollection",
"name": "SHEFF_152_toilets",
"crs": { "type": "name", "properties": { "name": "urn:ogc:def:crs:OGC:1.3:CRS84" } },
"features": [
{ "type": "Feature", "properties": { "name": "Burton Street Cafe", "payment_info": "Free", "accessible": "True", "radar": "Unknown", "women": "True", "men": "True", "baby_change": "True", "Mon": "09:00-16:00", "Tue": "09:00-16:00", "Wed": "09:00-16:00", "Thu": "09:00-16:00", "Fri": "09:00-16:00", "Sat": "Closed", "Sun": "Closed", "index_right": 112, "park_offical_id": "SHEFF_152" }, "geometry": { "type": "Point", "coordinates": [ -1.49305433, 53.400348804 ] } },
{ "type": "Feature", "properties": { "name": "Tesco Infirmary Road", "payment_info": "Cost unknown", "accessible": "True", "radar": "Unknown", "women": "True", "men": "True", "baby_change": "Unknown", "Mon": "09:00-17:00", "Tue": "09:00-17:00", "Wed": "09:00-17:00", "Thu": "09:00-17:00", "Fri": "09:00-17:00", "Sat": "09:00-17:00", "Sun": "09:00-17:00", "index_right": 112, "park_offical_id": "SHEFF_152" }, "geometry": { "type": "Point", "coordinates": [ -1.48266077, 53.389362484 ] } }
]
}
