{
"type": "FeatureCollection",
"name": "SHEFF_45_toilets",
"crs": { "type": "name", "properties": { "name": "urn:ogc:def:crs:OGC:1.3:CRS84" } },
"features": [
{ "type": "Feature", "properties": { "name": "Morrisons Halfway Sheffield", "payment_info": "Free", "accessible": "True", "radar": "False", "women": "True", "men": "True", "baby_change": "True", "Mon": "07:00-23:00", "Tue": "07:00-23:00", "Wed": "07:00-23:00", "Thu": "07:00-23:00", "Fri": "07:00-23:00", "Sat": "07:00-23:00", "Sun": "10:00-16:00", "index_right": 256, "park_offical_id": "SHEFF_45" }, "geometry": { "type": "Point", "coordinates": [ -1.343502402, 53.325090098 ] } }
]
}
