{
"type": "FeatureCollection",
"name": "SHEFF_18_toilets",
"crs": { "type": "name", "properties": { "name": "urn:ogc:def:crs:OGC:1.3:CRS84" } },
"features": [
{ "type": "Feature", "properties": { "name": "Surestart", "payment_info": "Free", "accessible": "False", "radar": "Unknown", "women": "True", "men": "True", "baby_change": "True", "Mon": "09:00-17:00", "Tue": "09:00-17:00", "Wed": "09:00-17:00", "Thu": "09:00-17:00", "Fri": "09:00-17:00", "Sat": "09:00-17:00", "Sun": "09:00-17:00", "index_right": 141, "park_offical_id": "SHEFF_18" }, "geometry": { "type": "Point", "coordinates": [ -1.447856426, 53.41755728 ] } },
{ "type": "Feature", "properties": { "name": "Shiregreen Cemetery", "payment_info": "Free", "accessible": "False", "radar": "Unknown", "women": "Unknown", "men": "Unknown", "baby_change": "Unknown", "Mon": "Unknown", "Tue": "Unknown", "Wed": "Unknown", "Thu": "Unknown", "Fri": "Unknown", "Sat": "Unknown", "Sun": "Unknown", "index_right": 141, "park_offical_id": "SHEFF_18" }, "geometry": { "type": "Point", "coordinates": [ -1.4356468, 53.4212512 ] } }
]
}
