{
"type": "FeatureCollection",
"name": "SHEFF_888_toilets",
"crs": { "type": "name", "properties": { "name": "urn:ogc:def:crs:OGC:1.3:CRS84" } },
"features": [
{ "type": "Feature", "properties": { "name": "Bankers Draft", "payment_info": "Free", "accessible": "True", "radar": "True", "women": "True", "men": "True", "baby_change": "Unknown", "Mon": "09:00-17:00", "Tue": "09:00-17:00", "Wed": "09:00-17:00", "Thu": "09:00-17:00", "Fri": "09:00-17:00", "Sat": "09:00-17:00", "Sun": "09:00-17:00", "index_right": 368, "park_offical_id": "SHEFF_888" }, "geometry": { "type": "Point", "coordinates": [ -1.466513872, 53.383264374 ] } },
{ "type": "Feature", "properties": { "name": "Sheffield Bus Interchange", "payment_info": "Free", "accessible": "True", "radar": "Unknown", "women": "True", "men": "True", "baby_change": "True", "Mon": "07:00-19:00", "Tue": "07:00-19:00", "Wed": "07:00-19:00", "Thu": "07:00-19:00", "Fri": "07:00-19:00", "Sat": "07:00-19:00", "Sun": "Closed", "index_right": 368, "park_offical_id": "SHEFF_888" }, "geometry": { "type": "Point", "coordinates": [ -1.463850439, 53.380930284 ] } }
]
}
