{
"type": "FeatureCollection",
"name": "SHEFF_139_toilets",
"crs": { "type": "name", "properties": { "name": "urn:ogc:def:crs:OGC:1.3:CRS84" } },
"features": [
{ "type": "Feature", "properties": { "name": "Forge Dam Park", "payment_info": "Free", "accessible": "True", "radar": "True", "women": "True", "men": "True", "baby_change": "True", "Mon": "09:00-17:00", "Tue": "09:00-17:00", "Wed": "09:00-17:00", "Thu": "09:00-17:00", "Fri": "09:00-17:00", "Sat": "09:00-17:00", "Sun": "09:00-17:00", "index_right": 88, "park_offical_id": "SHEFF_139" }, "geometry": { "type": "Point", "coordinates": [ -1.54582606, 53.36073066 ] } }
]
}
