{
"type": "FeatureCollection",
"name": "SHEFF_597_toilets",
"crs": { "type": "name", "properties": { "name": "urn:ogc:def:crs:OGC:1.3:CRS84" } },
"features": [
{ "type": "Feature", "properties": { "name": "The Rawson Spring", "payment_info": "Cost unknown", "accessible": "True", "radar": "Unknown", "women": "True", "men": "True", "baby_change": "Unknown", "Mon": "09:00-17:00", "Tue": "09:00-17:00", "Wed": "09:00-17:00", "Thu": "09:00-17:00", "Fri": "09:00-17:00", "Sat": "09:00-17:00", "Sun": "09:00-17:00", "index_right": 278, "park_offical_id": "SHEFF_597" }, "geometry": { "type": "Point", "coordinates": [ -1.500357985, 53.401906295 ] } },
{ "type": "Feature", "properties": { "name": "Hillsborough Interchange Enquiries Office ", "payment_info": "Free", "accessible": "True", "radar": "False", "women": "True", "men": "True", "baby_change": "Unknown", "Mon": "09:00-18:00", "Tue": "09:00-18:00", "Wed": "09:00-18:00", "Thu": "09:00-18:00", "Fri": "09:00-18:00", "Sat": "09:00-18:00", "Sun": "Closed", "index_right": 278, "park_offical_id": "SHEFF_597" }, "geometry": { "type": "Point", "coordinates": [ -1.49936676, 53.401886427 ] } }
]
}
