{
"type": "FeatureCollection",
"name": "WAKEF_73_toilets",
"crs": { "type": "name", "properties": { "name": "urn:ogc:def:crs:OGC:1.3:CRS84" } },
"features": [
{ "type": "Feature", "properties": { "name": "Pugneys Country Park", "payment_info": "Free", "accessible": "Unknown", "radar": "Unknown", "women": "True", "men": "True", "baby_change": "Unknown", "Mon": "Unknown", "Tue": "Unknown", "Wed": "Unknown", "Thu": "Unknown", "Fri": "Unknown", "Sat": "Unknown", "Sun": "Unknown", "index_right": 204, "park_offical_id": "WAKEF_73" }, "geometry": { "type": "Point", "coordinates": [ -1.510723692, 53.657388072 ] } }
]
}
