{
"type": "FeatureCollection",
"name": "WAKEF_19_toilets",
"crs": { "type": "name", "properties": { "name": "urn:ogc:def:crs:OGC:1.3:CRS84" } },
"features": [
{ "type": "Feature", "properties": { "name": "Tesco Hemsworth", "payment_info": "Free", "accessible": "True", "radar": "Unknown", "women": "True", "men": "True", "baby_change": "True", "Mon": "Unknown", "Tue": "Unknown", "Wed": "Unknown", "Thu": "Unknown", "Fri": "Unknown", "Sat": "Unknown", "Sun": "Unknown", "index_right": 79, "park_offical_id": "WAKEF_19" }, "geometry": { "type": "Point", "coordinates": [ -1.352457311, 53.612891782 ] } }
]
}
