{
"type": "FeatureCollection",
"name": "WAKEF_274_toilets",
"crs": { "type": "name", "properties": { "name": "urn:ogc:def:crs:OGC:1.3:CRS84" } },
"features": [
{ "type": "Feature", "properties": { "name": "Shoemarket Toilets", "payment_info": "20", "accessible": "False", "radar": "False", "women": "True", "men": "True", "baby_change": "True", "Mon": "Unknown", "Tue": "Unknown", "Wed": "Unknown", "Thu": "Unknown", "Fri": "Unknown", "Sat": "Unknown", "Sun": "Unknown", "index_right": 120, "park_offical_id": "WAKEF_274" }, "geometry": { "type": "Point", "coordinates": [ -1.312844753, 53.691905595 ] } },
{ "type": "Feature", "properties": { "name": "Baghill House Health and Wellbeing Centre", "payment_info": "Free", "accessible": "True", "radar": "Unknown", "women": "True", "men": "True", "baby_change": "Unknown", "Mon": "08:30-16:30", "Tue": "08:30-16:30", "Wed": "08:30-16:30", "Thu": "08:30-16:30", "Fri": "08:30-16:30", "Sat": "Closed", "Sun": "Closed", "index_right": 120, "park_offical_id": "WAKEF_274" }, "geometry": { "type": "Point", "coordinates": [ -1.303094923, 53.693926446 ] } },
{ "type": "Feature", "properties": { "name": "Pontefract Castle", "payment_info": "Free", "accessible": "True", "radar": "Unknown", "women": "True", "men": "True", "baby_change": "True", "Mon": "Unknown", "Tue": "Unknown", "Wed": "Unknown", "Thu": "Unknown", "Fri": "Unknown", "Sat": "Unknown", "Sun": "Unknown", "index_right": 120, "park_offical_id": "WAKEF_274" }, "geometry": { "type": "Point", "coordinates": [ -1.303698421, 53.695230427 ] } }
]
}
