{
"type": "FeatureCollection",
"name": "WAKEF_103_toilets",
"crs": { "type": "name", "properties": { "name": "urn:ogc:def:crs:OGC:1.3:CRS84" } },
"features": [
{ "type": "Feature", "properties": { "name": "Wakefield One Council Offices and Library", "payment_info": "Free", "accessible": "Unknown", "radar": "Unknown", "women": "True", "men": "True", "baby_change": "Unknown", "Mon": "Unknown", "Tue": "Unknown", "Wed": "Unknown", "Thu": "Unknown", "Fri": "Unknown", "Sat": "Unknown", "Sun": "Unknown", "index_right": 6, "park_offical_id": "WAKEF_103" }, "geometry": { "type": "Point", "coordinates": [ -1.503680741, 53.684283775 ] } },
{ "type": "Feature", "properties": { "name": "Drury Lane Health and Wellbeing Centre", "payment_info": "Free", "accessible": "True", "radar": "True", "women": "True", "men": "True", "baby_change": "Unknown", "Mon": "08:30-17:00", "Tue": "08:30-17:00", "Wed": "08:30-17:00", "Thu": "08:30-17:00", "Fri": "08:30-17:00", "Sat": "Closed", "Sun": "Closed", "index_right": 6, "park_offical_id": "WAKEF_103" }, "geometry": { "type": "Point", "coordinates": [ -1.503144801, 53.682989013 ] } },
{ "type": "Feature", "properties": { "name": "Wakefield Westgate Platform 1", "payment_info": "Free", "accessible": "Unknown", "radar": "Unknown", "women": "True", "men": "True", "baby_change": "Unknown", "Mon": "Unknown", "Tue": "Unknown", "Wed": "Unknown", "Thu": "Unknown", "Fri": "Unknown", "Sat": "Unknown", "Sun": "Unknown", "index_right": 6, "park_offical_id": "WAKEF_103" }, "geometry": { "type": "Point", "coordinates": [ -1.505773096, 53.682878317 ] } }
]
}
