{
"type": "FeatureCollection",
"name": "066b74219d9b_visibility",
"crs": { "type": "name", "properties": { "name": "urn:ogc:def:crs:OGC:1.3:CRS84" } },
"features": [
{ "type": "Feature", "properties": { "visible_points": 6, "total_points": 47, "visibility_pct": 12.76595744680851 }, "geometry": { "type": "Point", "coordinates": [ -1.639609689691142, 53.672485785801662 ] } },
{ "type": "Feature", "properties": { "visible_points": 11, "total_points": 49, "visibility_pct": 22.448979591836736 }, "geometry": { "type": "Point", "coordinates": [ -1.639399954905602, 53.672485158154949 ] } },
{ "type": "Feature", "properties": { "visible_points": 10, "total_points": 50, "visibility_pct": 20.0 }, "geometry": { "type": "Point", "coordinates": [ -1.639190220128128, 53.672484530140807 ] } },
{ "type": "Feature", "properties": { "visible_points": 5, "total_points": 49, "visibility_pct": 10.204081632653061 }, "geometry": { "type": "Point", "coordinates": [ -1.638980485358758, 53.672483901759271 ] } },
{ "type": "Feature", "properties": { "visible_points": 4, "total_points": 50, "visibility_pct": 8.0 }, "geometry": { "type": "Point", "coordinates": [ -1.639503902669274, 53.672593326300699 ] } },
{ "type": "Feature", "properties": { "visible_points": 7, "total_points": 50, "visibility_pct": 14.000000000000002 }, "geometry": { "type": "Point", "coordinates": [ -1.639294167344083, 53.672592698475853 ] } },
{ "type": "Feature", "properties": { "visible_points": 6, "total_points": 50, "visibility_pct": 12.0 }, "geometry": { "type": "Point", "coordinates": [ -1.639084432026975, 53.672592070283606 ] } },
{ "type": "Feature", "properties": { "visible_points": 1, "total_points": 50, "visibility_pct": 2.0 }, "geometry": { "type": "Point", "coordinates": [ -1.638874696717959, 53.672591441723952 ] } },
{ "type": "Feature", "properties": { "visible_points": 10, "total_points": 50, "visibility_pct": 20.0 }, "geometry": { "type": "Point", "coordinates": [ -1.639398115099662, 53.672700866711573 ] } },
{ "type": "Feature", "properties": { "visible_points": 8, "total_points": 50, "visibility_pct": 16.0 }, "geometry": { "type": "Point", "coordinates": [ -1.639188379234826, 53.672700238708622 ] } },
{ "type": "Feature", "properties": { "visible_points": 7, "total_points": 50, "visibility_pct": 14.000000000000002 }, "geometry": { "type": "Point", "coordinates": [ -1.63897864337807, 53.672699610338256 ] } },
{ "type": "Feature", "properties": { "visible_points": 0, "total_points": 50, "visibility_pct": 0.0 }, "geometry": { "type": "Point", "coordinates": [ -1.639502063394884, 53.672809034847958 ] } },
{ "type": "Feature", "properties": { "visible_points": 10, "total_points": 50, "visibility_pct": 20.0 }, "geometry": { "type": "Point", "coordinates": [ -1.63929232698231, 53.67280840703431 ] } },
{ "type": "Feature", "properties": { "visible_points": 8, "total_points": 50, "visibility_pct": 16.0 }, "geometry": { "type": "Point", "coordinates": [ -1.639082590577813, 53.672807778853247 ] } },
{ "type": "Feature", "properties": { "visible_points": 4, "total_points": 50, "visibility_pct": 8.0 }, "geometry": { "type": "Point", "coordinates": [ -1.638872854181418, 53.672807150304742 ] } },
{ "type": "Feature", "properties": { "visible_points": 0, "total_points": 50, "visibility_pct": 0.0 }, "geometry": { "type": "Point", "coordinates": [ -1.639396275269432, 53.672916575260665 ] } },
{ "type": "Feature", "properties": { "visible_points": 9, "total_points": 50, "visibility_pct": 18.0 }, "geometry": { "type": "Point", "coordinates": [ -1.639186538317197, 53.672915947268883 ] } },
{ "type": "Feature", "properties": { "visible_points": 5, "total_points": 49, "visibility_pct": 10.204081632653061 }, "geometry": { "type": "Point", "coordinates": [ -1.638976801373052, 53.672915318909702 ] } },
{ "type": "Feature", "properties": { "visible_points": 1, "total_points": 44, "visibility_pct": 2.2727272727272729 }, "geometry": { "type": "Point", "coordinates": [ -1.639500224096195, 53.673024743387678 ] } },
{ "type": "Feature", "properties": { "visible_points": 1, "total_points": 45, "visibility_pct": 2.2222222222222223 }, "geometry": { "type": "Point", "coordinates": [ -1.639290486596221, 53.6730241155852 ] } },
{ "type": "Feature", "properties": { "visible_points": 8, "total_points": 45, "visibility_pct": 17.777777777777779 }, "geometry": { "type": "Point", "coordinates": [ -1.639080749104333, 53.673023487415321 ] } },
{ "type": "Feature", "properties": { "visible_points": 1, "total_points": 43, "visibility_pct": 2.3255813953488373 }, "geometry": { "type": "Point", "coordinates": [ -1.638871011620531, 53.673022858877992 ] } }
]
}
