{
"type": "FeatureCollection",
"name": "0eddb6f44f3e_visibility",
"crs": { "type": "name", "properties": { "name": "urn:ogc:def:crs:OGC:1.3:CRS84" } },
"features": [
{ "type": "Feature", "properties": { "visible_points": 2, "total_points": 43, "visibility_pct": 4.6511627906976747 }, "geometry": { "type": "Point", "coordinates": [ -1.683197988007969, 53.590424968486538 ] } },
{ "type": "Feature", "properties": { "visible_points": 2, "total_points": 44, "visibility_pct": 4.5454545454545459 }, "geometry": { "type": "Point", "coordinates": [ -1.682988662344744, 53.590424415421502 ] } },
{ "type": "Feature", "properties": { "visible_points": 6, "total_points": 45, "visibility_pct": 13.333333333333334 }, "geometry": { "type": "Point", "coordinates": [ -1.68277933668851, 53.590423861990274 ] } },
{ "type": "Feature", "properties": { "visible_points": 2, "total_points": 49, "visibility_pct": 4.0816326530612246 }, "geometry": { "type": "Point", "coordinates": [ -1.683092520335876, 53.590532549049392 ] } },
{ "type": "Feature", "properties": { "visible_points": 6, "total_points": 50, "visibility_pct": 12.0 }, "geometry": { "type": "Point", "coordinates": [ -1.68288319414311, 53.590531995798266 ] } },
{ "type": "Feature", "properties": { "visible_points": 9, "total_points": 49, "visibility_pct": 18.367346938775512 }, "geometry": { "type": "Point", "coordinates": [ -1.682673867957335, 53.590531442180925 ] } },
{ "type": "Feature", "properties": { "visible_points": 4, "total_points": 54, "visibility_pct": 7.4074074074074066 }, "geometry": { "type": "Point", "coordinates": [ -1.682987052127236, 53.590640129515741 ] } },
{ "type": "Feature", "properties": { "visible_points": 6, "total_points": 55, "visibility_pct": 10.909090909090908 }, "geometry": { "type": "Point", "coordinates": [ -1.682777725404923, 53.590639576078516 ] } },
{ "type": "Feature", "properties": { "visible_points": 5, "total_points": 55, "visibility_pct": 9.0909090909090917 }, "geometry": { "type": "Point", "coordinates": [ -1.683090910640896, 53.590748263142693 ] } },
{ "type": "Feature", "properties": { "visible_points": 10, "total_points": 55, "visibility_pct": 18.181818181818183 }, "geometry": { "type": "Point", "coordinates": [ -1.682881583382044, 53.590747709885584 ] } },
{ "type": "Feature", "properties": { "visible_points": 10, "total_points": 55, "visibility_pct": 18.181818181818183 }, "geometry": { "type": "Point", "coordinates": [ -1.682672256130186, 53.59074715626226 ] } },
{ "type": "Feature", "properties": { "visible_points": 11, "total_points": 55, "visibility_pct": 20.0 }, "geometry": { "type": "Point", "coordinates": [ -1.682985441888698, 53.590855843602121 ] } },
{ "type": "Feature", "properties": { "visible_points": 10, "total_points": 55, "visibility_pct": 18.181818181818183 }, "geometry": { "type": "Point", "coordinates": [ -1.682776114100298, 53.590855290158913 ] } },
{ "type": "Feature", "properties": { "visible_points": 9, "total_points": 51, "visibility_pct": 17.647058823529413 }, "geometry": { "type": "Point", "coordinates": [ -1.682879972599945, 53.590963423965036 ] } },
{ "type": "Feature", "properties": { "visible_points": 11, "total_points": 50, "visibility_pct": 22.0 }, "geometry": { "type": "Point", "coordinates": [ -1.68267064428199, 53.59096287033573 ] } },
{ "type": "Feature", "properties": { "visible_points": 8, "total_points": 46, "visibility_pct": 17.391304347826086 }, "geometry": { "type": "Point", "coordinates": [ -1.682983831629131, 53.591071557680635 ] } },
{ "type": "Feature", "properties": { "visible_points": 10, "total_points": 45, "visibility_pct": 22.222222222222221 }, "geometry": { "type": "Point", "coordinates": [ -1.682774502774629, 53.591071004231438 ] } },
{ "type": "Feature", "properties": { "visible_points": 9, "total_points": 44, "visibility_pct": 20.454545454545457 }, "geometry": { "type": "Point", "coordinates": [ -1.682565173927118, 53.591070450416019 ] } },
{ "type": "Feature", "properties": { "visible_points": 7, "total_points": 41, "visibility_pct": 17.073170731707318 }, "geometry": { "type": "Point", "coordinates": [ -1.682878361796808, 53.591179138036644 ] } },
{ "type": "Feature", "properties": { "visible_points": 9, "total_points": 40, "visibility_pct": 22.5 }, "geometry": { "type": "Point", "coordinates": [ -1.682669032412742, 53.591178584401341 ] } }
]
}
