{
"type": "FeatureCollection",
"name": "224a4d25eb2f_visibility",
"crs": { "type": "name", "properties": { "name": "urn:ogc:def:crs:OGC:1.3:CRS84" } },
"features": [
{ "type": "Feature", "properties": { "visible_points": 9, "total_points": 46, "visibility_pct": 19.565217391304348 }, "geometry": { "type": "Point", "coordinates": [ -1.664849654863456, 53.677476865221458 ] } },
{ "type": "Feature", "properties": { "visible_points": 4, "total_points": 44, "visibility_pct": 9.0909090909090917 }, "geometry": { "type": "Point", "coordinates": [ -1.664639898536681, 53.677476278222059 ] } },
{ "type": "Feature", "properties": { "visible_points": 9, "total_points": 52, "visibility_pct": 17.307692307692307 }, "geometry": { "type": "Point", "coordinates": [ -1.664953675496706, 53.677585014512125 ] } },
{ "type": "Feature", "properties": { "visible_points": 9, "total_points": 50, "visibility_pct": 18.0 }, "geometry": { "type": "Point", "coordinates": [ -1.664743918679606, 53.677584427666957 ] } },
{ "type": "Feature", "properties": { "visible_points": 0, "total_points": 47, "visibility_pct": 0.0 }, "geometry": { "type": "Point", "coordinates": [ -1.664534161869407, 53.67758384045468 ] } },
{ "type": "Feature", "properties": { "visible_points": 10, "total_points": 57, "visibility_pct": 17.543859649122805 }, "geometry": { "type": "Point", "coordinates": [ -1.665057696613379, 53.677693163738169 ] } },
{ "type": "Feature", "properties": { "visible_points": 12, "total_points": 56, "visibility_pct": 21.428571428571427 }, "geometry": { "type": "Point", "coordinates": [ -1.664847939305947, 53.677692577047225 ] } },
{ "type": "Feature", "properties": { "visible_points": 0, "total_points": 53, "visibility_pct": 0.0 }, "geometry": { "type": "Point", "coordinates": [ -1.664638182005417, 53.677691989989164 ] } },
{ "type": "Feature", "properties": { "visible_points": 9, "total_points": 57, "visibility_pct": 15.789473684210526 }, "geometry": { "type": "Point", "coordinates": [ -1.665161718213478, 53.677801312899575 ] } },
{ "type": "Feature", "properties": { "visible_points": 11, "total_points": 57, "visibility_pct": 19.298245614035086 }, "geometry": { "type": "Point", "coordinates": [ -1.664951960415717, 53.677800726362861 ] } },
{ "type": "Feature", "properties": { "visible_points": 2, "total_points": 57, "visibility_pct": 3.5087719298245612 }, "geometry": { "type": "Point", "coordinates": [ -1.664742202624852, 53.677800139459038 ] } },
{ "type": "Feature", "properties": { "visible_points": 8, "total_points": 55, "visibility_pct": 14.545454545454545 }, "geometry": { "type": "Point", "coordinates": [ -1.665265740297005, 53.677909461996364 ] } },
{ "type": "Feature", "properties": { "visible_points": 11, "total_points": 57, "visibility_pct": 19.298245614035086 }, "geometry": { "type": "Point", "coordinates": [ -1.665055982008909, 53.677908875613866 ] } },
{ "type": "Feature", "properties": { "visible_points": 0, "total_points": 57, "visibility_pct": 0.0 }, "geometry": { "type": "Point", "coordinates": [ -1.664846223727711, 53.677908288864266 ] } },
{ "type": "Feature", "properties": { "visible_points": 6, "total_points": 49, "visibility_pct": 12.244897959183673 }, "geometry": { "type": "Point", "coordinates": [ -1.66536976286397, 53.678017611028508 ] } },
{ "type": "Feature", "properties": { "visible_points": 10, "total_points": 52, "visibility_pct": 19.230769230769234 }, "geometry": { "type": "Point", "coordinates": [ -1.665160004085534, 53.678017024800241 ] } },
{ "type": "Feature", "properties": { "visible_points": 1, "total_points": 53, "visibility_pct": 1.8867924528301887 }, "geometry": { "type": "Point", "coordinates": [ -1.664950245314001, 53.678016438204864 ] } },
{ "type": "Feature", "properties": { "visible_points": 9, "total_points": 43, "visibility_pct": 20.930232558139537 }, "geometry": { "type": "Point", "coordinates": [ -1.66547378591437, 53.678125759996028 ] } },
{ "type": "Feature", "properties": { "visible_points": 10, "total_points": 46, "visibility_pct": 21.739130434782609 }, "geometry": { "type": "Point", "coordinates": [ -1.665264026645598, 53.678125173921984 ] } },
{ "type": "Feature", "properties": { "visible_points": 6, "total_points": 48, "visibility_pct": 12.5 }, "geometry": { "type": "Point", "coordinates": [ -1.665054267383718, 53.678124587480852 ] } },
{ "type": "Feature", "properties": { "visible_points": 3, "total_points": 42, "visibility_pct": 7.1428571428571423 }, "geometry": { "type": "Point", "coordinates": [ -1.665158289936881, 53.678232736692195 ] } }
]
}
