{
"type": "FeatureCollection",
"name": "5e3b80925ac1_visibility",
"crs": { "type": "name", "properties": { "name": "urn:ogc:def:crs:OGC:1.3:CRS84" } },
"features": [
{ "type": "Feature", "properties": { "visible_points": 1, "total_points": 42, "visibility_pct": 2.3809523809523809 }, "geometry": { "type": "Point", "coordinates": [ -1.751703154649944, 53.729943500582294 ] } },
{ "type": "Feature", "properties": { "visible_points": 2, "total_points": 45, "visibility_pct": 4.4444444444444446 }, "geometry": { "type": "Point", "coordinates": [ -1.751493131594419, 53.729943067798303 ] } },
{ "type": "Feature", "properties": { "visible_points": 1, "total_points": 46, "visibility_pct": 2.1739130434782608 }, "geometry": { "type": "Point", "coordinates": [ -1.751283109021572, 53.7299426339912 ] } },
{ "type": "Feature", "properties": { "visible_points": 0, "total_points": 49, "visibility_pct": 0.0 }, "geometry": { "type": "Point", "coordinates": [ -1.751597510791047, 53.730051139168943 ] } },
{ "type": "Feature", "properties": { "visible_points": 0, "total_points": 51, "visibility_pct": 0.0 }, "geometry": { "type": "Point", "coordinates": [ -1.751387487436528, 53.730050705858254 ] } },
{ "type": "Feature", "properties": { "visible_points": 1, "total_points": 52, "visibility_pct": 1.9230769230769231 }, "geometry": { "type": "Point", "coordinates": [ -1.751177464480096, 53.730050271792436 ] } },
{ "type": "Feature", "properties": { "visible_points": 0, "total_points": 55, "visibility_pct": 0.0 }, "geometry": { "type": "Point", "coordinates": [ -1.751491866552028, 53.73015877754225 ] } },
{ "type": "Feature", "properties": { "visible_points": 0, "total_points": 56, "visibility_pct": 0.0 }, "geometry": { "type": "Point", "coordinates": [ -1.751281842889438, 53.73015834374965 ] } },
{ "type": "Feature", "properties": { "visible_points": 0, "total_points": 56, "visibility_pct": 0.0 }, "geometry": { "type": "Point", "coordinates": [ -1.75107181938973, 53.730157909507327 ] } },
{ "type": "Feature", "properties": { "visible_points": 2, "total_points": 56, "visibility_pct": 3.5714285714285712 }, "geometry": { "type": "Point", "coordinates": [ -1.75138622184204, 53.730266415605321 ] } },
{ "type": "Feature", "properties": { "visible_points": 2, "total_points": 56, "visibility_pct": 3.5714285714285712 }, "geometry": { "type": "Point", "coordinates": [ -1.751176197793455, 53.730265981554687 ] } },
{ "type": "Feature", "properties": { "visible_points": 1, "total_points": 56, "visibility_pct": 1.7857142857142856 }, "geometry": { "type": "Point", "coordinates": [ -1.751280576740444, 53.730374053500512 ] } },
{ "type": "Feature", "properties": { "visible_points": 5, "total_points": 55, "visibility_pct": 9.0909090909090917 }, "geometry": { "type": "Point", "coordinates": [ -1.751070552148579, 53.730373619273365 ] } },
{ "type": "Feature", "properties": { "visible_points": 0, "total_points": 52, "visibility_pct": 0.0 }, "geometry": { "type": "Point", "coordinates": [ -1.751384956230692, 53.730482125344807 ] } },
{ "type": "Feature", "properties": { "visible_points": 0, "total_points": 51, "visibility_pct": 0.0 }, "geometry": { "type": "Point", "coordinates": [ -1.751174931089948, 53.730481691309343 ] } },
{ "type": "Feature", "properties": { "visible_points": 3, "total_points": 49, "visibility_pct": 6.1224489795918364 }, "geometry": { "type": "Point", "coordinates": [ -1.750964905954803, 53.730481256905691 ] } },
{ "type": "Feature", "properties": { "visible_points": 0, "total_points": 46, "visibility_pct": 0.0 }, "geometry": { "type": "Point", "coordinates": [ -1.751279310574585, 53.730589763243813 ] } },
{ "type": "Feature", "properties": { "visible_points": 3, "total_points": 45, "visibility_pct": 6.666666666666667 }, "geometry": { "type": "Point", "coordinates": [ -1.751069284890554, 53.730589329031815 ] } },
{ "type": "Feature", "properties": { "visible_points": 2, "total_points": 42, "visibility_pct": 4.7619047619047619 }, "geometry": { "type": "Point", "coordinates": [ -1.750859259212118, 53.730588894451657 ] } },
{ "type": "Feature", "properties": { "visible_points": 2, "total_points": 40, "visibility_pct": 5.0 }, "geometry": { "type": "Point", "coordinates": [ -1.751173664369572, 53.730697401056432 ] } }
]
}
