{
"type": "FeatureCollection",
"name": "69b0f26f80ae_visibility",
"crs": { "type": "name", "properties": { "name": "urn:ogc:def:crs:OGC:1.3:CRS84" } },
"features": [
{ "type": "Feature", "properties": { "visible_points": 0, "total_points": 49, "visibility_pct": 0.0 }, "geometry": { "type": "Point", "coordinates": [ -1.899744197625164, 53.607024222584435 ] } },
{ "type": "Feature", "properties": { "visible_points": 1, "total_points": 45, "visibility_pct": 2.2222222222222223 }, "geometry": { "type": "Point", "coordinates": [ -1.899534785796664, 53.607024048991704 ] } },
{ "type": "Feature", "properties": { "visible_points": 3, "total_points": 40, "visibility_pct": 7.5 }, "geometry": { "type": "Point", "coordinates": [ -1.899325373970395, 53.607023875032489 ] } },
{ "type": "Feature", "properties": { "visible_points": 0, "total_points": 56, "visibility_pct": 0.0 }, "geometry": { "type": "Point", "coordinates": [ -1.899848650448879, 53.607132167441783 ] } },
{ "type": "Feature", "properties": { "visible_points": 5, "total_points": 52, "visibility_pct": 9.6153846153846168 }, "geometry": { "type": "Point", "coordinates": [ -1.899639238085551, 53.607131994031761 ] } },
{ "type": "Feature", "properties": { "visible_points": 5, "total_points": 47, "visibility_pct": 10.638297872340425 }, "geometry": { "type": "Point", "coordinates": [ -1.899429825724447, 53.607131820255283 ] } },
{ "type": "Feature", "properties": { "visible_points": 0, "total_points": 59, "visibility_pct": 0.0 }, "geometry": { "type": "Point", "coordinates": [ -1.89995310380519, 53.60724011220605 ] } },
{ "type": "Feature", "properties": { "visible_points": 3, "total_points": 57, "visibility_pct": 5.2631578947368416 }, "geometry": { "type": "Point", "coordinates": [ -1.899743690907029, 53.607239938978765 ] } },
{ "type": "Feature", "properties": { "visible_points": 0, "total_points": 50, "visibility_pct": 0.0 }, "geometry": { "type": "Point", "coordinates": [ -1.90047638456674, 53.607348401866915 ] } },
{ "type": "Feature", "properties": { "visible_points": 0, "total_points": 55, "visibility_pct": 0.0 }, "geometry": { "type": "Point", "coordinates": [ -1.900266971129318, 53.607348229555328 ] } },
{ "type": "Feature", "properties": { "visible_points": 3, "total_points": 58, "visibility_pct": 5.1724137931034484 }, "geometry": { "type": "Point", "coordinates": [ -1.900057557694107, 53.60734805687725 ] } },
{ "type": "Feature", "properties": { "visible_points": 0, "total_points": 59, "visibility_pct": 0.0 }, "geometry": { "type": "Point", "coordinates": [ -1.899848144261104, 53.607347883832702 ] } },
{ "type": "Feature", "properties": { "visible_points": 3, "total_points": 50, "visibility_pct": 6.0 }, "geometry": { "type": "Point", "coordinates": [ -1.900371426085675, 53.60745617395073 ] } },
{ "type": "Feature", "properties": { "visible_points": 1, "total_points": 54, "visibility_pct": 1.8518518518518516 }, "geometry": { "type": "Point", "coordinates": [ -1.900162012115623, 53.60745600145539 ] } },
{ "type": "Feature", "properties": { "visible_points": 0, "total_points": 57, "visibility_pct": 0.0 }, "geometry": { "type": "Point", "coordinates": [ -1.899952598147788, 53.607455828593572 ] } },
{ "type": "Feature", "properties": { "visible_points": 0, "total_points": 45, "visibility_pct": 0.0 }, "geometry": { "type": "Point", "coordinates": [ -1.900475881574642, 53.607564118253066 ] } },
{ "type": "Feature", "properties": { "visible_points": 3, "total_points": 49, "visibility_pct": 6.1224489795918364 }, "geometry": { "type": "Point", "coordinates": [ -1.900266467069755, 53.607563945940456 ] } },
{ "type": "Feature", "properties": { "visible_points": 4, "total_points": 53, "visibility_pct": 7.5471698113207548 }, "geometry": { "type": "Point", "coordinates": [ -1.900057052567077, 53.607563773261383 ] } },
{ "type": "Feature", "properties": { "visible_points": 5, "total_points": 55, "visibility_pct": 9.0909090909090917 }, "geometry": { "type": "Point", "coordinates": [ -1.899847638066616, 53.607563600215848 ] } },
{ "type": "Feature", "properties": { "visible_points": 0, "total_points": 43, "visibility_pct": 0.0 }, "geometry": { "type": "Point", "coordinates": [ -1.900370922556502, 53.607671890332462 ] } },
{ "type": "Feature", "properties": { "visible_points": 0, "total_points": 46, "visibility_pct": 0.0 }, "geometry": { "type": "Point", "coordinates": [ -1.900161507518978, 53.607671717836126 ] } },
{ "type": "Feature", "properties": { "visible_points": 4, "total_points": 49, "visibility_pct": 8.1632653061224492 }, "geometry": { "type": "Point", "coordinates": [ -1.899952092483675, 53.607671544973314 ] } }
]
}
