{
"type": "FeatureCollection",
"name": "877f189d79b1_visibility",
"crs": { "type": "name", "properties": { "name": "urn:ogc:def:crs:OGC:1.3:CRS84" } },
"features": [
{ "type": "Feature", "properties": { "visible_points": 9, "total_points": 52, "visibility_pct": 17.307692307692307 }, "geometry": { "type": "Point", "coordinates": [ -1.631301287413357, 53.701441798839532 ] } },
{ "type": "Feature", "properties": { "visible_points": 15, "total_points": 54, "visibility_pct": 27.777777777777779 }, "geometry": { "type": "Point", "coordinates": [ -1.631091407511569, 53.701441156350342 ] } },
{ "type": "Feature", "properties": { "visible_points": 8, "total_points": 53, "visibility_pct": 15.09433962264151 }, "geometry": { "type": "Point", "coordinates": [ -1.630881527618094, 53.701440513493651 ] } },
{ "type": "Feature", "properties": { "visible_points": 11, "total_points": 53, "visibility_pct": 20.754716981132077 }, "geometry": { "type": "Point", "coordinates": [ -1.631405286060409, 53.701549975787927 ] } },
{ "type": "Feature", "properties": { "visible_points": 13, "total_points": 54, "visibility_pct": 24.074074074074073 }, "geometry": { "type": "Point", "coordinates": [ -1.631195405607303, 53.701549333461614 ] } },
{ "type": "Feature", "properties": { "visible_points": 14, "total_points": 54, "visibility_pct": 25.925925925925924 }, "geometry": { "type": "Point", "coordinates": [ -1.630985525162514, 53.701548690767801 ] } },
{ "type": "Feature", "properties": { "visible_points": 14, "total_points": 54, "visibility_pct": 25.925925925925924 }, "geometry": { "type": "Point", "coordinates": [ -1.630775644726036, 53.701548047706503 ] } },
{ "type": "Feature", "properties": { "visible_points": 11, "total_points": 54, "visibility_pct": 20.37037037037037 }, "geometry": { "type": "Point", "coordinates": [ -1.631299404246034, 53.701657510499757 ] } },
{ "type": "Feature", "properties": { "visible_points": 12, "total_points": 54, "visibility_pct": 22.222222222222221 }, "geometry": { "type": "Point", "coordinates": [ -1.63108952324992, 53.701656867968822 ] } },
{ "type": "Feature", "properties": { "visible_points": 12, "total_points": 54, "visibility_pct": 22.222222222222221 }, "geometry": { "type": "Point", "coordinates": [ -1.630879642262124, 53.701656225070401 ] } },
{ "type": "Feature", "properties": { "visible_points": 13, "total_points": 54, "visibility_pct": 24.074074074074073 }, "geometry": { "type": "Point", "coordinates": [ -1.630669761282644, 53.701655581804474 ] } },
{ "type": "Feature", "properties": { "visible_points": 9, "total_points": 54, "visibility_pct": 16.666666666666664 }, "geometry": { "type": "Point", "coordinates": [ -1.631193521880329, 53.701765045096728 ] } },
{ "type": "Feature", "properties": { "visible_points": 8, "total_points": 54, "visibility_pct": 14.814814814814813 }, "geometry": { "type": "Point", "coordinates": [ -1.630983640341201, 53.701764402361171 ] } },
{ "type": "Feature", "properties": { "visible_points": 0, "total_points": 54, "visibility_pct": 0.0 }, "geometry": { "type": "Point", "coordinates": [ -1.630773758810398, 53.701763759258128 ] } },
{ "type": "Feature", "properties": { "visible_points": 10, "total_points": 52, "visibility_pct": 19.230769230769234 }, "geometry": { "type": "Point", "coordinates": [ -1.630563877287913, 53.701763115787578 ] } },
{ "type": "Feature", "properties": { "visible_points": 0, "total_points": 54, "visibility_pct": 0.0 }, "geometry": { "type": "Point", "coordinates": [ -1.631087638963281, 53.701872579578811 ] } },
{ "type": "Feature", "properties": { "visible_points": 0, "total_points": 54, "visibility_pct": 0.0 }, "geometry": { "type": "Point", "coordinates": [ -1.630877756881145, 53.701871936638632 ] } },
{ "type": "Feature", "properties": { "visible_points": 5, "total_points": 51, "visibility_pct": 9.8039215686274517 }, "geometry": { "type": "Point", "coordinates": [ -1.63066787480733, 53.701871293330981 ] } },
{ "type": "Feature", "properties": { "visible_points": 4, "total_points": 49, "visibility_pct": 8.1632653061224492 }, "geometry": { "type": "Point", "coordinates": [ -1.631191638128362, 53.701980756723337 ] } },
{ "type": "Feature", "properties": { "visible_points": 1, "total_points": 49, "visibility_pct": 2.0408163265306123 }, "geometry": { "type": "Point", "coordinates": [ -1.630981755494894, 53.70198011394605 ] } },
{ "type": "Feature", "properties": { "visible_points": 2, "total_points": 47, "visibility_pct": 4.2553191489361701 }, "geometry": { "type": "Point", "coordinates": [ -1.630771872869741, 53.701979470801263 ] } }
]
}
