{
"type": "FeatureCollection",
"name": "a58e7bf81c7d_visibility",
"crs": { "type": "name", "properties": { "name": "urn:ogc:def:crs:OGC:1.3:CRS84" } },
"features": [
{ "type": "Feature", "properties": { "visible_points": 0, "total_points": 60, "visibility_pct": 0.0 }, "geometry": { "type": "Point", "coordinates": [ -1.90370697386821, 53.611083733321671 ] } },
{ "type": "Feature", "properties": { "visible_points": 0, "total_points": 63, "visibility_pct": 0.0 }, "geometry": { "type": "Point", "coordinates": [ -1.903497542204344, 53.611083566602062 ] } },
{ "type": "Feature", "properties": { "visible_points": 0, "total_points": 62, "visibility_pct": 0.0 }, "geometry": { "type": "Point", "coordinates": [ -1.903288110542606, 53.611083399515941 ] } },
{ "type": "Feature", "properties": { "visible_points": 0, "total_points": 59, "visibility_pct": 0.0 }, "geometry": { "type": "Point", "coordinates": [ -1.90381144681516, 53.611191674740738 ] } },
{ "type": "Feature", "properties": { "visible_points": 2, "total_points": 63, "visibility_pct": 3.1746031746031744 }, "geometry": { "type": "Point", "coordinates": [ -1.903602014618822, 53.611191508205422 ] } },
{ "type": "Feature", "properties": { "visible_points": 1, "total_points": 63, "visibility_pct": 1.5873015873015872 }, "geometry": { "type": "Point", "coordinates": [ -1.903392582424612, 53.611191341303552 ] } },
{ "type": "Feature", "properties": { "visible_points": 0, "total_points": 62, "visibility_pct": 0.0 }, "geometry": { "type": "Point", "coordinates": [ -1.903183150232538, 53.61119117403517 ] } },
{ "type": "Feature", "properties": { "visible_points": 0, "total_points": 57, "visibility_pct": 0.0 }, "geometry": { "type": "Point", "coordinates": [ -1.902973718042597, 53.611191006400261 ] } },
{ "type": "Feature", "properties": { "visible_points": 1, "total_points": 57, "visibility_pct": 1.7543859649122806 }, "geometry": { "type": "Point", "coordinates": [ -1.903915920292444, 53.611299616065224 ] } },
{ "type": "Feature", "properties": { "visible_points": 3, "total_points": 63, "visibility_pct": 4.7619047619047619 }, "geometry": { "type": "Point", "coordinates": [ -1.90370648756363, 53.611299449714167 ] } },
{ "type": "Feature", "properties": { "visible_points": 2, "total_points": 63, "visibility_pct": 3.1746031746031744 }, "geometry": { "type": "Point", "coordinates": [ -1.903497054836945, 53.611299282996583 ] } },
{ "type": "Feature", "properties": { "visible_points": 1, "total_points": 63, "visibility_pct": 1.5873015873015872 }, "geometry": { "type": "Point", "coordinates": [ -1.903287622112389, 53.61129911591248 ] } },
{ "type": "Feature", "properties": { "visible_points": 0, "total_points": 61, "visibility_pct": 0.0 }, "geometry": { "type": "Point", "coordinates": [ -1.903078189389972, 53.61129894846183 ] } },
{ "type": "Feature", "properties": { "visible_points": 1, "total_points": 53, "visibility_pct": 1.8867924528301887 }, "geometry": { "type": "Point", "coordinates": [ -1.902868756669692, 53.611298780644645 ] } },
{ "type": "Feature", "properties": { "visible_points": 0, "total_points": 53, "visibility_pct": 0.0 }, "geometry": { "type": "Point", "coordinates": [ -1.904020394300059, 53.611407557295131 ] } },
{ "type": "Feature", "properties": { "visible_points": 3, "total_points": 60, "visibility_pct": 5.0 }, "geometry": { "type": "Point", "coordinates": [ -1.903810961038773, 53.611407391128346 ] } },
{ "type": "Feature", "properties": { "visible_points": 0, "total_points": 63, "visibility_pct": 0.0 }, "geometry": { "type": "Point", "coordinates": [ -1.903601527779607, 53.611407224595034 ] } },
{ "type": "Feature", "properties": { "visible_points": 1, "total_points": 63, "visibility_pct": 1.5873015873015872 }, "geometry": { "type": "Point", "coordinates": [ -1.903392094522573, 53.611407057695189 ] } },
{ "type": "Feature", "properties": { "visible_points": 0, "total_points": 63, "visibility_pct": 0.0 }, "geometry": { "type": "Point", "coordinates": [ -1.903182661267672, 53.61140689042881 ] } },
{ "type": "Feature", "properties": { "visible_points": 0, "total_points": 56, "visibility_pct": 0.0 }, "geometry": { "type": "Point", "coordinates": [ -1.902973228014907, 53.611406722795905 ] } },
{ "type": "Feature", "properties": { "visible_points": 0, "total_points": 61, "visibility_pct": 0.0 }, "geometry": { "type": "Point", "coordinates": [ -1.903706001252608, 53.61151516609889 ] } },
{ "type": "Feature", "properties": { "visible_points": 0, "total_points": 63, "visibility_pct": 0.0 }, "geometry": { "type": "Point", "coordinates": [ -1.903496567463087, 53.611514999383324 ] } }
]
}
