{
"type": "FeatureCollection",
"name": "cb7dbfeddccf_visibility",
"crs": { "type": "name", "properties": { "name": "urn:ogc:def:crs:OGC:1.3:CRS84" } },
"features": [
{ "type": "Feature", "properties": { "visible_points": 26, "total_points": 53, "visibility_pct": 49.056603773584904 }, "geometry": { "type": "Point", "coordinates": [ -1.737092054860959, 53.64344071569451 ] } },
{ "type": "Feature", "properties": { "visible_points": 22, "total_points": 53, "visibility_pct": 41.509433962264154 }, "geometry": { "type": "Point", "coordinates": [ -1.736882464947785, 53.643440255526521 ] } },
{ "type": "Feature", "properties": { "visible_points": 23, "total_points": 51, "visibility_pct": 45.098039215686278 }, "geometry": { "type": "Point", "coordinates": [ -1.736672875040421, 53.643439794991629 ] } },
{ "type": "Feature", "properties": { "visible_points": 18, "total_points": 47, "visibility_pct": 38.297872340425535 }, "geometry": { "type": "Point", "coordinates": [ -1.736463285138864, 53.643439334089848 ] } },
{ "type": "Feature", "properties": { "visible_points": 24, "total_points": 53, "visibility_pct": 45.283018867924532 }, "geometry": { "type": "Point", "coordinates": [ -1.737196180729833, 53.643548801093779 ] } },
{ "type": "Feature", "properties": { "visible_points": 20, "total_points": 53, "visibility_pct": 37.735849056603776 }, "geometry": { "type": "Point", "coordinates": [ -1.736986590281116, 53.643548341103603 ] } },
{ "type": "Feature", "properties": { "visible_points": 21, "total_points": 53, "visibility_pct": 39.622641509433961 }, "geometry": { "type": "Point", "coordinates": [ -1.736776999838199, 53.643547880746524 ] } },
{ "type": "Feature", "properties": { "visible_points": 21, "total_points": 51, "visibility_pct": 41.17647058823529 }, "geometry": { "type": "Point", "coordinates": [ -1.736567409401092, 53.643547420022522 ] } },
{ "type": "Feature", "properties": { "visible_points": 26, "total_points": 53, "visibility_pct": 49.056603773584904 }, "geometry": { "type": "Point", "coordinates": [ -1.737300307128446, 53.643656886404997 ] } },
{ "type": "Feature", "properties": { "visible_points": 22, "total_points": 53, "visibility_pct": 41.509433962264154 }, "geometry": { "type": "Point", "coordinates": [ -1.737090716144177, 53.643656426592621 ] } },
{ "type": "Feature", "properties": { "visible_points": 22, "total_points": 53, "visibility_pct": 41.509433962264154 }, "geometry": { "type": "Point", "coordinates": [ -1.736881125165706, 53.643655966413334 ] } },
{ "type": "Feature", "properties": { "visible_points": 20, "total_points": 53, "visibility_pct": 37.735849056603776 }, "geometry": { "type": "Point", "coordinates": [ -1.736671534193046, 53.643655505867152 ] } },
{ "type": "Feature", "properties": { "visible_points": 15, "total_points": 50, "visibility_pct": 30.0 }, "geometry": { "type": "Point", "coordinates": [ -1.736461943226193, 53.643655044954052 ] } },
{ "type": "Feature", "properties": { "visible_points": 19, "total_points": 50, "visibility_pct": 38.0 }, "geometry": { "type": "Point", "coordinates": [ -1.737404434056791, 53.643764971628151 ] } },
{ "type": "Feature", "properties": { "visible_points": 22, "total_points": 53, "visibility_pct": 41.509433962264154 }, "geometry": { "type": "Point", "coordinates": [ -1.737194842536976, 53.643764511993581 ] } },
{ "type": "Feature", "properties": { "visible_points": 21, "total_points": 53, "visibility_pct": 39.622641509433961 }, "geometry": { "type": "Point", "coordinates": [ -1.736985251022952, 53.643764051992108 ] } },
{ "type": "Feature", "properties": { "visible_points": 25, "total_points": 53, "visibility_pct": 47.169811320754718 }, "geometry": { "type": "Point", "coordinates": [ -1.736775659514731, 53.643763591623731 ] } },
{ "type": "Feature", "properties": { "visible_points": 19, "total_points": 53, "visibility_pct": 35.849056603773583 }, "geometry": { "type": "Point", "coordinates": [ -1.736566068012321, 53.643763130888424 ] } },
{ "type": "Feature", "properties": { "visible_points": 18, "total_points": 52, "visibility_pct": 34.615384615384613 }, "geometry": { "type": "Point", "coordinates": [ -1.737089377409936, 53.64387213748283 ] } },
{ "type": "Feature", "properties": { "visible_points": 22, "total_points": 53, "visibility_pct": 41.509433962264154 }, "geometry": { "type": "Point", "coordinates": [ -1.736879785366157, 53.643871677292246 ] } },
{ "type": "Feature", "properties": { "visible_points": 23, "total_points": 53, "visibility_pct": 43.39622641509434 }, "geometry": { "type": "Point", "coordinates": [ -1.736670193328187, 53.643871216734752 ] } }
]
}
