{
"type": "FeatureCollection",
"name": "e982c7c22f00_visibility",
"crs": { "type": "name", "properties": { "name": "urn:ogc:def:crs:OGC:1.3:CRS84" } },
"features": [
{ "type": "Feature", "properties": { "visible_points": 5, "total_points": 49, "visibility_pct": 10.204081632653061 }, "geometry": { "type": "Point", "coordinates": [ -1.84178999150903, 53.641607995263271 ] } },
{ "type": "Feature", "properties": { "visible_points": 4, "total_points": 48, "visibility_pct": 8.3333333333333321 }, "geometry": { "type": "Point", "coordinates": [ -1.841580409071969, 53.641607720186812 ] } },
{ "type": "Feature", "properties": { "visible_points": 4, "total_points": 47, "visibility_pct": 8.5106382978723403 }, "geometry": { "type": "Point", "coordinates": [ -1.841370826638433, 53.641607444743414 ] } },
{ "type": "Feature", "properties": { "visible_points": 0, "total_points": 44, "visibility_pct": 0.0 }, "geometry": { "type": "Point", "coordinates": [ -1.841161244208425, 53.641607168933113 ] } },
{ "type": "Feature", "properties": { "visible_points": 3, "total_points": 53, "visibility_pct": 5.6603773584905666 }, "geometry": { "type": "Point", "coordinates": [ -1.841894381143248, 53.641715990043217 ] } },
{ "type": "Feature", "properties": { "visible_points": 7, "total_points": 53, "visibility_pct": 13.20754716981132 }, "geometry": { "type": "Point", "coordinates": [ -1.841684798166933, 53.641715715149495 ] } },
{ "type": "Feature", "properties": { "visible_points": 3, "total_points": 52, "visibility_pct": 5.7692307692307692 }, "geometry": { "type": "Point", "coordinates": [ -1.841475215194148, 53.641715439888863 ] } },
{ "type": "Feature", "properties": { "visible_points": 1, "total_points": 50, "visibility_pct": 2.0 }, "geometry": { "type": "Point", "coordinates": [ -1.841265632224884, 53.641715164261278 ] } },
{ "type": "Feature", "properties": { "visible_points": 8, "total_points": 57, "visibility_pct": 14.035087719298245 }, "geometry": { "type": "Point", "coordinates": [ -1.841789187797618, 53.641823710019224 ] } },
{ "type": "Feature", "properties": { "visible_points": 5, "total_points": 56, "visibility_pct": 8.9285714285714288 }, "geometry": { "type": "Point", "coordinates": [ -1.841579604285575, 53.641823434941315 ] } },
{ "type": "Feature", "properties": { "visible_points": 4, "total_points": 55, "visibility_pct": 7.2727272727272725 }, "geometry": { "type": "Point", "coordinates": [ -1.841370020777058, 53.641823159496489 ] } },
{ "type": "Feature", "properties": { "visible_points": 5, "total_points": 57, "visibility_pct": 8.7719298245614024 }, "geometry": { "type": "Point", "coordinates": [ -1.841683993809782, 53.641931429927084 ] } },
{ "type": "Feature", "properties": { "visible_points": 6, "total_points": 57, "visibility_pct": 10.526315789473683 }, "geometry": { "type": "Point", "coordinates": [ -1.841474409763752, 53.641931154664867 ] } },
{ "type": "Feature", "properties": { "visible_points": 3, "total_points": 56, "visibility_pct": 5.3571428571428568 }, "geometry": { "type": "Point", "coordinates": [ -1.841788383612235, 53.642039424858787 ] } },
{ "type": "Feature", "properties": { "visible_points": 7, "total_points": 57, "visibility_pct": 12.280701754385964 }, "geometry": { "type": "Point", "coordinates": [ -1.841578799031754, 53.642039149779173 ] } },
{ "type": "Feature", "properties": { "visible_points": 1, "total_points": 50, "visibility_pct": 2.0 }, "geometry": { "type": "Point", "coordinates": [ -1.841892773899046, 53.642147419712799 ] } },
{ "type": "Feature", "properties": { "visible_points": 4, "total_points": 51, "visibility_pct": 7.8431372549019605 }, "geometry": { "type": "Point", "coordinates": [ -1.841683188784146, 53.64214714481588 ] } },
{ "type": "Feature", "properties": { "visible_points": 0, "total_points": 51, "visibility_pct": 0.0 }, "geometry": { "type": "Point", "coordinates": [ -1.841473603672741, 53.64214686955205 ] } },
{ "type": "Feature", "properties": { "visible_points": 1, "total_points": 45, "visibility_pct": 2.2222222222222223 }, "geometry": { "type": "Point", "coordinates": [ -1.841787579067442, 53.642255139759683 ] } },
{ "type": "Feature", "properties": { "visible_points": 1, "total_points": 39, "visibility_pct": 2.5641025641025639 }, "geometry": { "type": "Point", "coordinates": [ -1.841891969881649, 53.642363134610562 ] } }
]
}
