{
"type": "FeatureCollection",
"name": "KIRKL_148_toilets",
"crs": { "type": "name", "properties": { "name": "urn:ogc:def:crs:OGC:1.3:CRS84" } },
"features": [
{ "type": "Feature", "properties": { "name": "Lidl Supermarket Mirfield", "payment_info": "Free", "accessible": "True", "radar": "Unknown", "women": "True", "men": "True", "baby_change": "True", "Mon": "09:00-17:00", "Tue": "09:00-17:00", "Wed": "09:00-17:00", "Thu": "09:00-17:00", "Fri": "09:00-17:00", "Sat": "09:00-17:00", "Sun": "09:00-17:00", "index_right": 50, "park_offical_id": "KIRKL_148" }, "geometry": { "type": "Point", "coordinates": [ -1.691514349, 53.67197831 ] } }
]
}
