{
"type": "FeatureCollection",
"name": "KIRKL_42_toilets",
"crs": { "type": "name", "properties": { "name": "urn:ogc:def:crs:OGC:1.3:CRS84" } },
"features": [
{ "type": "Feature", "properties": { "name": "Huddersfield Open Market", "payment_info": "Free", "accessible": "False", "radar": "False", "women": "True", "men": "True", "baby_change": "False", "Mon": "Unknown", "Tue": "Unknown", "Wed": "Unknown", "Thu": "Unknown", "Fri": "Unknown", "Sat": "Unknown", "Sun": "Unknown", "index_right": 175, "park_offical_id": "KIRKL_42" }, "geometry": { "type": "Point", "coordinates": [ -1.781346202, 53.64917705 ] } },
{ "type": "Feature", "properties": { "name": "Huddersfield Train Station", "payment_info": "Free", "accessible": "False", "radar": "False", "women": "True", "men": "True", "baby_change": "True", "Mon": "Unknown", "Tue": "Unknown", "Wed": "Unknown", "Thu": "Unknown", "Fri": "Unknown", "Sat": "Unknown", "Sun": "Unknown", "index_right": 175, "park_offical_id": "KIRKL_42" }, "geometry": { "type": "Point", "coordinates": [ -1.784784794, 53.648215153 ] } },
{ "type": "Feature", "properties": { "name": "Huddersfield Train Station  platforms", "payment_info": "Free", "accessible": "False", "radar": "Unknown", "women": "True", "men": "True", "baby_change": "True", "Mon": "Unknown", "Tue": "Unknown", "Wed": "Unknown", "Thu": "Unknown", "Fri": "Unknown", "Sat": "Unknown", "Sun": "Unknown", "index_right": 175, "park_offical_id": "KIRKL_42" }, "geometry": { "type": "Point", "coordinates": [ -1.784704328, 53.648590357 ] } },
{ "type": "Feature", "properties": { "name": "Tesco", "payment_info": "Free", "accessible": "True", "radar": "Unknown", "women": "True", "men": "True", "baby_change": "Unknown", "Mon": "06:00-23:58", "Tue": "06:00-23:58", "Wed": "06:00-23:58", "Thu": "06:00-23:58", "Fri": "06:00-23:58", "Sat": "06:00-23:58", "Sun": "10:00-16:00", "index_right": 175, "park_offical_id": "KIRKL_42" }, "geometry": { "type": "Point", "coordinates": [ -1.781864007, 53.65030051 ] } }
]
}
