{
"type": "FeatureCollection",
"name": "KIRKL_43_toilets",
"crs": { "type": "name", "properties": { "name": "urn:ogc:def:crs:OGC:1.3:CRS84" } },
"features": [
{ "type": "Feature", "properties": { "name": "Library and Art Gallery", "payment_info": "Cost unknown", "accessible": "True", "radar": "True", "women": "Unknown", "men": "Unknown", "baby_change": "Unknown", "Mon": "Unknown", "Tue": "Unknown", "Wed": "Unknown", "Thu": "Unknown", "Fri": "Unknown", "Sat": "Unknown", "Sun": "Unknown", "index_right": 179, "park_offical_id": "KIRKL_43" }, "geometry": { "type": "Point", "coordinates": [ -1.781303732, 53.644589312 ] } }
]
}
