{
"type": "FeatureCollection",
"name": "KIRKL_430_toilets",
"crs": { "type": "name", "properties": { "name": "urn:ogc:def:crs:OGC:1.3:CRS84" } },
"features": [
{ "type": "Feature", "properties": { "name": "Unknown", "payment_info": "Free", "accessible": "False", "radar": "False", "women": "Unknown", "men": "Unknown", "baby_change": "False", "Mon": "09:00-17:00", "Tue": "09:00-17:00", "Wed": "09:00-17:00", "Thu": "09:00-17:00", "Fri": "09:00-17:00", "Sat": "Closed", "Sun": "Closed", "index_right": 180, "park_offical_id": "KIRKL_430" }, "geometry": { "type": "Point", "coordinates": [ -1.8099819, 53.6266799 ] } }
]
}
