{
"type": "FeatureCollection",
"name": "271c8c4fe2d3_visibility",
"crs": { "type": "name", "properties": { "name": "urn:ogc:def:crs:OGC:1.3:CRS84" } },
"features": [
{ "type": "Feature", "properties": { "visible_points": 3, "total_points": 36, "visibility_pct": 8.3333333333333321 }, "geometry": { "type": "Point", "coordinates": [ -0.65283065282581, 53.552577999730346 ] } },
{ "type": "Feature", "properties": { "visible_points": 3, "total_points": 37, "visibility_pct": 8.1081081081081088 }, "geometry": { "type": "Point", "coordinates": [ -0.652621564808103, 53.552575644865485 ] } },
{ "type": "Feature", "properties": { "visible_points": 1, "total_points": 40, "visibility_pct": 2.5 }, "geometry": { "type": "Point", "coordinates": [ -0.652722686251886, 53.552684652689138 ] } },
{ "type": "Feature", "properties": { "visible_points": 0, "total_points": 41, "visibility_pct": 0.0 }, "geometry": { "type": "Point", "coordinates": [ -0.652513597724986, 53.552682297632167 ] } },
{ "type": "Feature", "properties": { "visible_points": 0, "total_points": 45, "visibility_pct": 0.0 }, "geometry": { "type": "Point", "coordinates": [ -0.652614719139491, 53.552791305545078 ] } },
{ "type": "Feature", "properties": { "visible_points": 0, "total_points": 45, "visibility_pct": 0.0 }, "geometry": { "type": "Point", "coordinates": [ -0.652405630103402, 53.552788950296041 ] } },
{ "type": "Feature", "properties": { "visible_points": 0, "total_points": 49, "visibility_pct": 0.0 }, "geometry": { "type": "Point", "coordinates": [ -0.652506751488623, 53.552897958298217 ] } },
{ "type": "Feature", "properties": { "visible_points": 0, "total_points": 53, "visibility_pct": 0.0 }, "geometry": { "type": "Point", "coordinates": [ -0.652607873383023, 53.553006966216266 ] } },
{ "type": "Feature", "properties": { "visible_points": 0, "total_points": 53, "visibility_pct": 0.0 }, "geometry": { "type": "Point", "coordinates": [ -0.652398783299277, 53.553004610948499 ] } },
{ "type": "Feature", "properties": { "visible_points": 0, "total_points": 54, "visibility_pct": 0.0 }, "geometry": { "type": "Point", "coordinates": [ -0.652499905164393, 53.553113618955798 ] } },
{ "type": "Feature", "properties": { "visible_points": 0, "total_points": 53, "visibility_pct": 0.0 }, "geometry": { "type": "Point", "coordinates": [ -0.65229081457145, 53.55311126349595 ] } },
{ "type": "Feature", "properties": { "visible_points": 0, "total_points": 52, "visibility_pct": 0.0 }, "geometry": { "type": "Point", "coordinates": [ -0.652391936407282, 53.553220271592529 ] } },
{ "type": "Feature", "properties": { "visible_points": 0, "total_points": 48, "visibility_pct": 0.0 }, "geometry": { "type": "Point", "coordinates": [ -0.652493058752295, 53.553329279604988 ] } },
{ "type": "Feature", "properties": { "visible_points": 0, "total_points": 47, "visibility_pct": 0.0 }, "geometry": { "type": "Point", "coordinates": [ -0.652283967111679, 53.553326924126409 ] } },
{ "type": "Feature", "properties": { "visible_points": 0, "total_points": 43, "visibility_pct": 0.0 }, "geometry": { "type": "Point", "coordinates": [ -0.652385089427408, 53.553435932228133 ] } },
{ "type": "Feature", "properties": { "visible_points": 0, "total_points": 39, "visibility_pct": 0.0 }, "geometry": { "type": "Point", "coordinates": [ -0.652486212252329, 53.553544940245764 ] } },
{ "type": "Feature", "properties": { "visible_points": 2, "total_points": 38, "visibility_pct": 5.2631578947368416 }, "geometry": { "type": "Point", "coordinates": [ -0.652277119564022, 53.553542584748442 ] } },
{ "type": "Feature", "properties": { "visible_points": 0, "total_points": 34, "visibility_pct": 0.0 }, "geometry": { "type": "Point", "coordinates": [ -0.652378242359658, 53.553651592855331 ] } },
{ "type": "Feature", "properties": { "visible_points": 0, "total_points": 30, "visibility_pct": 0.0 }, "geometry": { "type": "Point", "coordinates": [ -0.652479365664487, 53.5537606008781 ] } },
{ "type": "Feature", "properties": { "visible_points": 2, "total_points": 30, "visibility_pct": 6.666666666666667 }, "geometry": { "type": "Point", "coordinates": [ -0.652270271928483, 53.553758245362076 ] } }
]
}
