{
"type": "FeatureCollection",
"name": "5edb8740b883_visibility",
"crs": { "type": "name", "properties": { "name": "urn:ogc:def:crs:OGC:1.3:CRS84" } },
"features": [
{ "type": "Feature", "properties": { "visible_points": 0, "total_points": 37, "visibility_pct": 0.0 }, "geometry": { "type": "Point", "coordinates": [ -0.832727419737278, 53.557952522507577 ] } },
{ "type": "Feature", "properties": { "visible_points": 0, "total_points": 38, "visibility_pct": 0.0 }, "geometry": { "type": "Point", "coordinates": [ -0.832518290062796, 53.557950481839875 ] } },
{ "type": "Feature", "properties": { "visible_points": 1, "total_points": 37, "visibility_pct": 2.7027027027027026 }, "geometry": { "type": "Point", "coordinates": [ -0.832309160413962, 53.557948440806548 ] } },
{ "type": "Feature", "properties": { "visible_points": 0, "total_points": 42, "visibility_pct": 0.0 }, "geometry": { "type": "Point", "coordinates": [ -0.832619887513213, 53.558059339878419 ] } },
{ "type": "Feature", "properties": { "visible_points": 0, "total_points": 42, "visibility_pct": 0.0 }, "geometry": { "type": "Point", "coordinates": [ -0.832410757319988, 53.558057299020831 ] } },
{ "type": "Feature", "properties": { "visible_points": 0, "total_points": 47, "visibility_pct": 0.0 }, "geometry": { "type": "Point", "coordinates": [ -0.832512354744742, 53.55816615714874 ] } },
{ "type": "Feature", "properties": { "visible_points": 0, "total_points": 46, "visibility_pct": 0.0 }, "geometry": { "type": "Point", "coordinates": [ -0.832303224032771, 53.558164116101217 ] } },
{ "type": "Feature", "properties": { "visible_points": 0, "total_points": 51, "visibility_pct": 0.0 }, "geometry": { "type": "Point", "coordinates": [ -0.83261395268822, 53.558275015190318 ] } },
{ "type": "Feature", "properties": { "visible_points": 0, "total_points": 51, "visibility_pct": 0.0 }, "geometry": { "type": "Point", "coordinates": [ -0.832404821431853, 53.558272974318527 ] } },
{ "type": "Feature", "properties": { "visible_points": 0, "total_points": 55, "visibility_pct": 0.0 }, "geometry": { "type": "Point", "coordinates": [ -0.832506419349665, 53.558381832449463 ] } },
{ "type": "Feature", "properties": { "visible_points": 0, "total_points": 55, "visibility_pct": 0.0 }, "geometry": { "type": "Point", "coordinates": [ -0.832297287574551, 53.558379791387779 ] } },
{ "type": "Feature", "properties": { "visible_points": 0, "total_points": 52, "visibility_pct": 0.0 }, "geometry": { "type": "Point", "coordinates": [ -0.832608017786217, 53.558490690494033 ] } },
{ "type": "Feature", "properties": { "visible_points": 0, "total_points": 52, "visibility_pct": 0.0 }, "geometry": { "type": "Point", "coordinates": [ -0.832398885466696, 53.558488649608087 ] } },
{ "type": "Feature", "properties": { "visible_points": 0, "total_points": 48, "visibility_pct": 0.0 }, "geometry": { "type": "Point", "coordinates": [ -0.832500483923626, 53.558597507734518 ] } },
{ "type": "Feature", "properties": { "visible_points": 0, "total_points": 47, "visibility_pct": 0.0 }, "geometry": { "type": "Point", "coordinates": [ -0.832291351081029, 53.558595466658772 ] } },
{ "type": "Feature", "properties": { "visible_points": 0, "total_points": 43, "visibility_pct": 0.0 }, "geometry": { "type": "Point", "coordinates": [ -0.832602083175602, 53.558706365754084 ] } },
{ "type": "Feature", "properties": { "visible_points": 0, "total_points": 43, "visibility_pct": 0.0 }, "geometry": { "type": "Point", "coordinates": [ -0.832392949782726, 53.558704324853494 ] } },
{ "type": "Feature", "properties": { "visible_points": 2, "total_points": 39, "visibility_pct": 5.1282051282051277 }, "geometry": { "type": "Point", "coordinates": [ -0.832494549122126, 53.558813182948121 ] } },
{ "type": "Feature", "properties": { "visible_points": 0, "total_points": 38, "visibility_pct": 0.0 }, "geometry": { "type": "Point", "coordinates": [ -0.832285415208135, 53.558811141856147 ] } },
{ "type": "Feature", "properties": { "visible_points": 1, "total_points": 34, "visibility_pct": 2.9411764705882351 }, "geometry": { "type": "Point", "coordinates": [ -0.832596148982641, 53.558922040957867 ] } },
{ "type": "Feature", "properties": { "visible_points": 4, "total_points": 34, "visibility_pct": 11.76470588235294 }, "geometry": { "type": "Point", "coordinates": [ -0.832387014521781, 53.558920000040118 ] } }
]
}
