{
"type": "FeatureCollection",
"name": "801878c4b40e_visibility",
"crs": { "type": "name", "properties": { "name": "urn:ogc:def:crs:OGC:1.3:CRS84" } },
"features": [
{ "type": "Feature", "properties": { "visible_points": 1, "total_points": 41, "visibility_pct": 2.4390243902439024 }, "geometry": { "type": "Point", "coordinates": [ -0.669043336475182, 53.550418221774812 ] } },
{ "type": "Feature", "properties": { "visible_points": 3, "total_points": 40, "visibility_pct": 7.5 }, "geometry": { "type": "Point", "coordinates": [ -0.668834256869846, 53.550415895240278 ] } },
{ "type": "Feature", "properties": { "visible_points": 3, "total_points": 46, "visibility_pct": 6.5217391304347823 }, "geometry": { "type": "Point", "coordinates": [ -0.669144495124275, 53.550527216022004 ] } },
{ "type": "Feature", "properties": { "visible_points": 1, "total_points": 45, "visibility_pct": 2.2222222222222223 }, "geometry": { "type": "Point", "coordinates": [ -0.668935414985701, 53.550524889661013 ] } },
{ "type": "Feature", "properties": { "visible_points": 3, "total_points": 51, "visibility_pct": 5.8823529411764701 }, "geometry": { "type": "Point", "coordinates": [ -0.669245654277902, 53.550636210184955 ] } },
{ "type": "Feature", "properties": { "visible_points": 2, "total_points": 50, "visibility_pct": 4.0 }, "geometry": { "type": "Point", "coordinates": [ -0.669036573606081, 53.550633883997492 ] } },
{ "type": "Feature", "properties": { "visible_points": 0, "total_points": 48, "visibility_pct": 0.0 }, "geometry": { "type": "Point", "coordinates": [ -0.668827492962956, 53.550631557444561 ] } },
{ "type": "Feature", "properties": { "visible_points": 0, "total_points": 55, "visibility_pct": 0.0 }, "geometry": { "type": "Point", "coordinates": [ -0.669137732731003, 53.550742878249679 ] } },
{ "type": "Feature", "properties": { "visible_points": 0, "total_points": 53, "visibility_pct": 0.0 }, "geometry": { "type": "Point", "coordinates": [ -0.668928651554624, 53.550740551870291 ] } },
{ "type": "Feature", "properties": { "visible_points": 0, "total_points": 60, "visibility_pct": 0.0 }, "geometry": { "type": "Point", "coordinates": [ -0.669238892360456, 53.550851872417617 ] } },
{ "type": "Feature", "properties": { "visible_points": 2, "total_points": 59, "visibility_pct": 3.3898305084745761 }, "geometry": { "type": "Point", "coordinates": [ -0.669029810650835, 53.550849546211744 ] } },
{ "type": "Feature", "properties": { "visible_points": 0, "total_points": 56, "visibility_pct": 0.0 }, "geometry": { "type": "Point", "coordinates": [ -0.669340052494469, 53.550960866501278 ] } },
{ "type": "Feature", "properties": { "visible_points": 1, "total_points": 57, "visibility_pct": 1.7543859649122806 }, "geometry": { "type": "Point", "coordinates": [ -0.669130970251585, 53.550958540468947 ] } },
{ "type": "Feature", "properties": { "visible_points": 0, "total_points": 50, "visibility_pct": 0.0 }, "geometry": { "type": "Point", "coordinates": [ -0.669441213133022, 53.551069860500668 ] } },
{ "type": "Feature", "properties": { "visible_points": 1, "total_points": 52, "visibility_pct": 1.9230769230769231 }, "geometry": { "type": "Point", "coordinates": [ -0.669232130356883, 53.551067534641874 ] } },
{ "type": "Feature", "properties": { "visible_points": 0, "total_points": 45, "visibility_pct": 0.0 }, "geometry": { "type": "Point", "coordinates": [ -0.66954237427613, 53.551178854415788 ] } },
{ "type": "Feature", "properties": { "visible_points": 1, "total_points": 47, "visibility_pct": 2.1276595744680851 }, "geometry": { "type": "Point", "coordinates": [ -0.669333290966737, 53.551176528730537 ] } },
{ "type": "Feature", "properties": { "visible_points": 0, "total_points": 48, "visibility_pct": 0.0 }, "geometry": { "type": "Point", "coordinates": [ -0.669124207686027, 53.551174202679817 ] } },
{ "type": "Feature", "properties": { "visible_points": 0, "total_points": 42, "visibility_pct": 0.0 }, "geometry": { "type": "Point", "coordinates": [ -0.66943445208114, 53.551285522734915 ] } },
{ "type": "Feature", "properties": { "visible_points": 0, "total_points": 43, "visibility_pct": 0.0 }, "geometry": { "type": "Point", "coordinates": [ -0.669225368267174, 53.551283196857753 ] } },
{ "type": "Feature", "properties": { "visible_points": 3, "total_points": 36, "visibility_pct": 8.3333333333333321 }, "geometry": { "type": "Point", "coordinates": [ -0.66953561370011, 53.551394516655037 ] } },
{ "type": "Feature", "properties": { "visible_points": 0, "total_points": 38, "visibility_pct": 0.0 }, "geometry": { "type": "Point", "coordinates": [ -0.669326529352872, 53.551392190951411 ] } }
]
}
