{
"type": "FeatureCollection",
"name": "ac7f223e1538_visibility",
"crs": { "type": "name", "properties": { "name": "urn:ogc:def:crs:OGC:1.3:CRS84" } },
"features": [
{ "type": "Feature", "properties": { "visible_points": 1, "total_points": 49, "visibility_pct": 2.0408163265306123 }, "geometry": { "type": "Point", "coordinates": [ -0.862007302652253, 53.505899305185871 ] } },
{ "type": "Feature", "properties": { "visible_points": 4, "total_points": 45, "visibility_pct": 8.8888888888888893 }, "geometry": { "type": "Point", "coordinates": [ -0.861798427030262, 53.505897316965431 ] } },
{ "type": "Feature", "properties": { "visible_points": 0, "total_points": 53, "visibility_pct": 0.0 }, "geometry": { "type": "Point", "coordinates": [ -0.862317729989096, 53.506010126682881 ] } },
{ "type": "Feature", "properties": { "visible_points": 5, "total_points": 53, "visibility_pct": 9.433962264150944 }, "geometry": { "type": "Point", "coordinates": [ -0.862108853797737, 53.506008139001338 ] } },
{ "type": "Feature", "properties": { "visible_points": 8, "total_points": 50, "visibility_pct": 16.0 }, "geometry": { "type": "Point", "coordinates": [ -0.861899977631372, 53.506006150954889 ] } },
{ "type": "Feature", "properties": { "visible_points": 7, "total_points": 46, "visibility_pct": 15.217391304347828 }, "geometry": { "type": "Point", "coordinates": [ -0.861691101490011, 53.506004162543526 ] } },
{ "type": "Feature", "properties": { "visible_points": 5, "total_points": 53, "visibility_pct": 9.433962264150944 }, "geometry": { "type": "Point", "coordinates": [ -0.862419282198317, 53.506118960239498 ] } },
{ "type": "Feature", "properties": { "visible_points": 5, "total_points": 53, "visibility_pct": 9.433962264150944 }, "geometry": { "type": "Point", "coordinates": [ -0.862210405462581, 53.506116972731959 ] } },
{ "type": "Feature", "properties": { "visible_points": 7, "total_points": 53, "visibility_pct": 13.20754716981132 }, "geometry": { "type": "Point", "coordinates": [ -0.862001528751835, 53.506114984859494 ] } },
{ "type": "Feature", "properties": { "visible_points": 0, "total_points": 50, "visibility_pct": 0.0 }, "geometry": { "type": "Point", "coordinates": [ -0.861792652066096, 53.506112996622136 ] } },
{ "type": "Feature", "properties": { "visible_points": 0, "total_points": 45, "visibility_pct": 0.0 }, "geometry": { "type": "Point", "coordinates": [ -0.861583775405371, 53.50611100801985 ] } },
{ "type": "Feature", "properties": { "visible_points": 0, "total_points": 44, "visibility_pct": 0.0 }, "geometry": { "type": "Point", "coordinates": [ -0.862729712232009, 53.506229780679902 ] } },
{ "type": "Feature", "properties": { "visible_points": 5, "total_points": 50, "visibility_pct": 10.0 }, "geometry": { "type": "Point", "coordinates": [ -0.862520834926903, 53.506227793711282 ] } },
{ "type": "Feature", "properties": { "visible_points": 6, "total_points": 53, "visibility_pct": 11.320754716981133 }, "geometry": { "type": "Point", "coordinates": [ -0.862311957646788, 53.506225806377728 ] } },
{ "type": "Feature", "properties": { "visible_points": 0, "total_points": 53, "visibility_pct": 0.0 }, "geometry": { "type": "Point", "coordinates": [ -0.862103080391663, 53.506223818679267 ] } },
{ "type": "Feature", "properties": { "visible_points": 0, "total_points": 53, "visibility_pct": 0.0 }, "geometry": { "type": "Point", "coordinates": [ -0.861894203161545, 53.5062218306159 ] } },
{ "type": "Feature", "properties": { "visible_points": 0, "total_points": 38, "visibility_pct": 0.0 }, "geometry": { "type": "Point", "coordinates": [ -0.862831266024342, 53.506338613892829 ] } },
{ "type": "Feature", "properties": { "visible_points": 0, "total_points": 44, "visibility_pct": 0.0 }, "geometry": { "type": "Point", "coordinates": [ -0.862622388174857, 53.5063366270982 ] } },
{ "type": "Feature", "properties": { "visible_points": 0, "total_points": 49, "visibility_pct": 0.0 }, "geometry": { "type": "Point", "coordinates": [ -0.862413510350361, 53.50633463993865 ] } },
{ "type": "Feature", "properties": { "visible_points": 0, "total_points": 52, "visibility_pct": 0.0 }, "geometry": { "type": "Point", "coordinates": [ -0.862204632550861, 53.506332652414201 ] } }
]
}
