{
"type": "FeatureCollection",
"name": "f24bd243dae4_visibility",
"crs": { "type": "name", "properties": { "name": "urn:ogc:def:crs:OGC:1.3:CRS84" } },
"features": [
{ "type": "Feature", "properties": { "visible_points": 0, "total_points": 33, "visibility_pct": 0.0 }, "geometry": { "type": "Point", "coordinates": [ -0.659407677479809, 53.551107759597834 ] } },
{ "type": "Feature", "properties": { "visible_points": 4, "total_points": 38, "visibility_pct": 10.526315789473683 }, "geometry": { "type": "Point", "coordinates": [ -0.659198596048906, 53.551105416277181 ] } },
{ "type": "Feature", "properties": { "visible_points": 4, "total_points": 43, "visibility_pct": 9.3023255813953494 }, "geometry": { "type": "Point", "coordinates": [ -0.658989514647115, 53.55110307259109 ] } },
{ "type": "Feature", "properties": { "visible_points": 6, "total_points": 48, "visibility_pct": 12.5 }, "geometry": { "type": "Point", "coordinates": [ -0.658780433274454, 53.551100728539552 ] } },
{ "type": "Feature", "properties": { "visible_points": 0, "total_points": 37, "visibility_pct": 0.0 }, "geometry": { "type": "Point", "coordinates": [ -0.659299730867233, 53.551214418650325 ] } },
{ "type": "Feature", "properties": { "visible_points": 0, "total_points": 42, "visibility_pct": 0.0 }, "geometry": { "type": "Point", "coordinates": [ -0.659090648927112, 53.551212075137649 ] } },
{ "type": "Feature", "properties": { "visible_points": 4, "total_points": 47, "visibility_pct": 8.5106382978723403 }, "geometry": { "type": "Point", "coordinates": [ -0.658881567016103, 53.551209731259533 ] } },
{ "type": "Feature", "properties": { "visible_points": 2, "total_points": 52, "visibility_pct": 3.8461538461538463 }, "geometry": { "type": "Point", "coordinates": [ -0.658672485134226, 53.551207387015928 ] } },
{ "type": "Feature", "properties": { "visible_points": 4, "total_points": 57, "visibility_pct": 7.0175438596491224 }, "geometry": { "type": "Point", "coordinates": [ -0.658463403281472, 53.551205042406863 ] } },
{ "type": "Feature", "properties": { "visible_points": 0, "total_points": 56, "visibility_pct": 0.0 }, "geometry": { "type": "Point", "coordinates": [ -0.65825432145785, 53.551202697432387 ] } },
{ "type": "Feature", "properties": { "visible_points": 0, "total_points": 56, "visibility_pct": 0.0 }, "geometry": { "type": "Point", "coordinates": [ -0.658564536455632, 53.551314045389518 ] } },
{ "type": "Feature", "properties": { "visible_points": 2, "total_points": 57, "visibility_pct": 3.5087719298245612 }, "geometry": { "type": "Point", "coordinates": [ -0.658355454093669, 53.551311700588442 ] } },
{ "type": "Feature", "properties": { "visible_points": 2, "total_points": 53, "visibility_pct": 3.7735849056603774 }, "geometry": { "type": "Point", "coordinates": [ -0.658146371760834, 53.5513093554219 ] } },
{ "type": "Feature", "properties": { "visible_points": 1, "total_points": 48, "visibility_pct": 2.083333333333333 }, "geometry": { "type": "Point", "coordinates": [ -0.657937289457138, 53.551307009889896 ] } },
{ "type": "Feature", "properties": { "visible_points": 1, "total_points": 43, "visibility_pct": 2.3255813953488373 }, "geometry": { "type": "Point", "coordinates": [ -0.657728207182592, 53.551304663992468 ] } },
{ "type": "Feature", "properties": { "visible_points": 3, "total_points": 38, "visibility_pct": 7.8947368421052628 }, "geometry": { "type": "Point", "coordinates": [ -0.657519124937191, 53.551302317729565 ] } },
{ "type": "Feature", "properties": { "visible_points": 0, "total_points": 49, "visibility_pct": 0.0 }, "geometry": { "type": "Point", "coordinates": [ -0.658038421525446, 53.551416013308618 ] } },
{ "type": "Feature", "properties": { "visible_points": 1, "total_points": 44, "visibility_pct": 2.2727272727272729 }, "geometry": { "type": "Point", "coordinates": [ -0.657829338712545, 53.551413667584569 ] } },
{ "type": "Feature", "properties": { "visible_points": 0, "total_points": 39, "visibility_pct": 0.0 }, "geometry": { "type": "Point", "coordinates": [ -0.657620255928785, 53.551411321495074 ] } },
{ "type": "Feature", "properties": { "visible_points": 3, "total_points": 34, "visibility_pct": 8.8235294117647065 }, "geometry": { "type": "Point", "coordinates": [ -0.657411173174178, 53.551408975040133 ] } },
{ "type": "Feature", "properties": { "visible_points": 2, "total_points": 35, "visibility_pct": 5.7142857142857144 }, "geometry": { "type": "Point", "coordinates": [ -0.657512304136601, 53.551517978894893 ] } }
]
}
