{
"type": "FeatureCollection",
"name": "LEEDS_5_toilets",
"crs": { "type": "name", "properties": { "name": "urn:ogc:def:crs:OGC:1.3:CRS84" } },
"features": [
{ "type": "Feature", "properties": { "name": "Waitrose Meanwood", "payment_info": "Free", "accessible": "True", "radar": "False", "women": "True", "men": "True", "baby_change": "True", "Mon": "Unknown", "Tue": "Unknown", "Wed": "Unknown", "Thu": "Unknown", "Fri": "Unknown", "Sat": "Unknown", "Sun": "Unknown", "index_right": 309, "park_offical_id": "LEEDS_5" }, "geometry": { "type": "Point", "coordinates": [ -1.567563415, 53.828782979 ] } },
{ "type": "Feature", "properties": { "name": "Aldi Meanwood Leeds ", "payment_info": "Free", "accessible": "True", "radar": "False", "women": "True", "men": "True", "baby_change": "True", "Mon": "Unknown", "Tue": "Unknown", "Wed": "Unknown", "Thu": "Unknown", "Fri": "Unknown", "Sat": "Unknown", "Sun": "Unknown", "index_right": 309, "park_offical_id": "LEEDS_5" }, "geometry": { "type": "Point", "coordinates": [ -1.564732476, 53.828452122 ] } },
{ "type": "Feature", "properties": { "name": "KFC Meanwood", "payment_info": "Cost unknown", "accessible": "True", "radar": "False", "women": "True", "men": "True", "baby_change": "False", "Mon": "Unknown", "Tue": "Unknown", "Wed": "Unknown", "Thu": "Unknown", "Fri": "Unknown", "Sat": "Unknown", "Sun": "Unknown", "index_right": 309, "park_offical_id": "LEEDS_5" }, "geometry": { "type": "Point", "coordinates": [ -1.564575434, 53.829299047 ] } },
{ "type": "Feature", "properties": { "name": "Starbucks Meanwood", "payment_info": "Free", "accessible": "True", "radar": "False", "women": "True", "men": "True", "baby_change": "True", "Mon": "Unknown", "Tue": "Unknown", "Wed": "Unknown", "Thu": "Unknown", "Fri": "Unknown", "Sat": "Unknown", "Sun": "Unknown", "index_right": 309, "park_offical_id": "LEEDS_5" }, "geometry": { "type": "Point", "coordinates": [ -1.563888566, 53.828496447 ] } }
]
}
