{
"type": "FeatureCollection",
"name": "LEEDS_116_toilets",
"crs": { "type": "name", "properties": { "name": "urn:ogc:def:crs:OGC:1.3:CRS84" } },
"features": [
{ "type": "Feature", "properties": { "name": "Middleton Golf Course", "payment_info": "Free", "accessible": "False", "radar": "Unknown", "women": "Unknown", "men": "Unknown", "baby_change": "Unknown", "Mon": "Unknown", "Tue": "Unknown", "Wed": "Unknown", "Thu": "Unknown", "Fri": "Unknown", "Sat": "Unknown", "Sun": "Unknown", "index_right": 48, "park_offical_id": "LEEDS_116" }, "geometry": { "type": "Point", "coordinates": [ -1.5480595, 53.7511294 ] } },
{ "type": "Feature", "properties": { "name": "Middleton Park", "payment_info": "Cost unknown", "accessible": "True", "radar": "Unknown", "women": "True", "men": "True", "baby_change": "True", "Mon": "09:00-17:00", "Tue": "09:00-17:00", "Wed": "09:00-17:00", "Thu": "09:00-17:00", "Fri": "09:00-17:00", "Sat": "09:00-17:00", "Sun": "09:00-17:00", "index_right": 48, "park_offical_id": "LEEDS_116" }, "geometry": { "type": "Point", "coordinates": [ -1.544901238, 53.75427192 ] } }
]
}
