{
"type": "FeatureCollection",
"name": "LEEDS_96_toilets",
"crs": { "type": "name", "properties": { "name": "urn:ogc:def:crs:OGC:1.3:CRS84" } },
"features": [
{ "type": "Feature", "properties": { "name": "Esso Service Station", "payment_info": "Free", "accessible": "Unknown", "radar": "Unknown", "women": "Unknown", "men": "Unknown", "baby_change": "Unknown", "Mon": "Unknown", "Tue": "Unknown", "Wed": "Unknown", "Thu": "Unknown", "Fri": "Unknown", "Sat": "Unknown", "Sun": "Unknown", "index_right": 514, "park_offical_id": "LEEDS_96" }, "geometry": { "type": "Point", "coordinates": [ -1.580719471, 53.77236557 ] } }
]
}
