{
"type": "FeatureCollection",
"name": "LEEDS_55_toilets",
"crs": { "type": "name", "properties": { "name": "urn:ogc:def:crs:OGC:1.3:CRS84" } },
"features": [
{ "type": "Feature", "properties": { "name": "Aldi", "payment_info": "Free", "accessible": "True", "radar": "Unknown", "women": "True", "men": "True", "baby_change": "True", "Mon": "Unknown", "Tue": "Unknown", "Wed": "Unknown", "Thu": "Unknown", "Fri": "Unknown", "Sat": "Unknown", "Sun": "Unknown", "index_right": 319, "park_offical_id": "LEEDS_55" }, "geometry": { "type": "Point", "coordinates": [ -1.601935923, 53.793550274 ] } }
]
}
