{
"type": "FeatureCollection",
"name": "LEEDS_666_toilets",
"crs": { "type": "name", "properties": { "name": "urn:ogc:def:crs:OGC:1.3:CRS84" } },
"features": [
{ "type": "Feature", "properties": { "name": "Crossgates Shopping Centre", "payment_info": "Free", "accessible": "False", "radar": "Unknown", "women": "True", "men": "True", "baby_change": "Unknown", "Mon": "09:00-17:00", "Tue": "09:00-17:00", "Wed": "09:00-17:00", "Thu": "09:00-17:00", "Fri": "09:00-17:00", "Sat": "09:00-17:00", "Sun": "09:00-17:00", "index_right": 361, "park_offical_id": "LEEDS_666" }, "geometry": { "type": "Point", "coordinates": [ -1.450206041, 53.806069693 ] } },
{ "type": "Feature", "properties": { "name": "Next The Springs", "payment_info": "Free", "accessible": "True", "radar": "Unknown", "women": "True", "men": "True", "baby_change": "True", "Mon": "Unknown", "Tue": "Unknown", "Wed": "Unknown", "Thu": "Unknown", "Fri": "Unknown", "Sat": "Unknown", "Sun": "Unknown", "index_right": 361, "park_offical_id": "LEEDS_666" }, "geometry": { "type": "Point", "coordinates": [ -1.423630714, 53.799174416 ] } }
]
}
