{
"type": "FeatureCollection",
"name": "LEEDS_538_lighting",
"crs": { "type": "name", "properties": { "name": "urn:ogc:def:crs:OGC:1.3:CRS84" } },
"features": [
{"type":"Feature","properties":{"Park Feature":"Street Light"},"geometry":{"type":"Point","coordinates":[-1.349490420481458,53.898505494828605]}},
{"type":"Feature","properties":{"Park Feature":"Street Light"},"geometry":{"type":"Point","coordinates":[-1.349616806784954,53.898942371763496]}},
{"type":"Feature","properties":{"Park Feature":"Street Light"},"geometry":{"type":"Point","coordinates":[-1.349743936103365,53.899331503539614]}},
{"type":"Feature","properties":{"Park Feature":"Street Light"},"geometry":{"type":"Point","coordinates":[-1.349478706896583,53.899383154539329]}},
{"type":"Feature","properties":{"Park Feature":"Street Light"},"geometry":{"type":"Point","coordinates":[-1.348725007809715,53.899467831355679]}},
{"type":"Feature","properties":{"Park Feature":"Street Light"},"geometry":{"type":"Point","coordinates":[-1.349455852548937,53.899476841922407]}},
{"type":"Feature","properties":{"Park Feature":"Street Light"},"geometry":{"type":"Point","coordinates":[-1.348216363699876,53.89960551187248]}},
{"type":"Feature","properties":{"Park Feature":"Street Light"},"geometry":{"type":"Point","coordinates":[-1.34707930106338,53.899661417223712]}},
{"type":"Feature","properties":{"Park Feature":"Street Light"},"geometry":{"type":"Point","coordinates":[-1.347713223196945,53.899664294819807]}},
{"type":"Feature","properties":{"Park Feature":"Street Light"},"geometry":{"type":"Point","coordinates":[-1.349707002278952,53.899719749197089]}},
{"type":"Feature","properties":{"Park Feature":"Street Light"},"geometry":{"type":"Point","coordinates":[-1.347267721555764,53.89990033822906]}},
{"type":"Feature","properties":{"Park Feature":"Street Light"},"geometry":{"type":"Point","coordinates":[-1.349836479506761,53.900049630142185]}},
{"type":"Feature","properties":{"Park Feature":"Street Light"},"geometry":{"type":"Point","coordinates":[-1.347301826870811,53.900184203228939]}},
{"type":"Feature","properties":{"Park Feature":"Street Light"},"geometry":{"type":"Point","coordinates":[-1.34851767826208,53.900384314503491]}},
{"type":"Feature","properties":{"Park Feature":"Street Light"},"geometry":{"type":"Point","coordinates":[-1.349933295976989,53.900431014872638]}},
{"type":"Feature","properties":{"Park Feature":"Street Light"},"geometry":{"type":"Point","coordinates":[-1.348866477082757,53.900678871120881]}},
{"type":"Feature","properties":{"Park Feature":"Street Light"},"geometry":{"type":"Point","coordinates":[-1.348267085200948,53.900717755711121]}},
{"type":"Feature","properties":{"Park Feature":"Street Light"},"geometry":{"type":"Point","coordinates":[-1.347591154596661,53.900723922442104]}},
{"type":"Feature","properties":{"Park Feature":"Street Light"},"geometry":{"type":"Point","coordinates":[-1.350004117849424,53.90086337776124]}},
{"type":"Feature","properties":{"Park Feature":"Street Light"},"geometry":{"type":"Point","coordinates":[-1.349056665496007,53.900896733199531]}}
]
}
