{
"type": "FeatureCollection",
"name": "LEEDS_994_lighting",
"crs": { "type": "name", "properties": { "name": "urn:ogc:def:crs:OGC:1.3:CRS84" } },
"features": [
{"type":"Feature","properties":{"Park Feature":"Street Light"},"geometry":{"type":"Point","coordinates":[-1.349320859771951,53.778902437455116]}},
{"type":"Feature","properties":{"Park Feature":"Street Light"},"geometry":{"type":"Point","coordinates":[-1.349280730430799,53.77895221626796]}},
{"type":"Feature","properties":{"Park Feature":"Street Light"},"geometry":{"type":"Point","coordinates":[-1.349095781705363,53.778952338015294]}},
{"type":"Feature","properties":{"Park Feature":"Street Light"},"geometry":{"type":"Point","coordinates":[-1.349479787442828,53.778959753851737]}},
{"type":"Feature","properties":{"Park Feature":"Street Light"},"geometry":{"type":"Point","coordinates":[-1.349487801467728,53.779116246254006]}},
{"type":"Feature","properties":{"Park Feature":"Street Light"},"geometry":{"type":"Point","coordinates":[-1.348743779952593,53.779144516313643]}},
{"type":"Feature","properties":{"Park Feature":"Street Light"},"geometry":{"type":"Point","coordinates":[-1.348945183227139,53.779184368818157]}},
{"type":"Feature","properties":{"Park Feature":"Street Light"},"geometry":{"type":"Point","coordinates":[-1.349771954645749,53.779202327856055]}},
{"type":"Feature","properties":{"Park Feature":"Street Light"},"geometry":{"type":"Point","coordinates":[-1.348317701150209,53.779220290025997]}},
{"type":"Feature","properties":{"Park Feature":"Street Light"},"geometry":{"type":"Point","coordinates":[-1.348602339470833,53.779274919698864]}},
{"type":"Feature","properties":{"Park Feature":"Street Light"},"geometry":{"type":"Point","coordinates":[-1.34974596477359,53.779288416932118]}},
{"type":"Feature","properties":{"Park Feature":"Street Light"},"geometry":{"type":"Point","coordinates":[-1.348757941912443,53.779301884285147]}},
{"type":"Feature","properties":{"Park Feature":"Street Light"},"geometry":{"type":"Point","coordinates":[-1.349860807296311,53.779344652038453]}},
{"type":"Feature","properties":{"Park Feature":"Street Light"},"geometry":{"type":"Point","coordinates":[-1.350104943683421,53.779350466782596]}},
{"type":"Feature","properties":{"Park Feature":"Street Light"},"geometry":{"type":"Point","coordinates":[-1.348744836320579,53.779382705875264]}},
{"type":"Feature","properties":{"Park Feature":"Street Light"},"geometry":{"type":"Point","coordinates":[-1.34905367225446,53.779406007371804]}},
{"type":"Feature","properties":{"Park Feature":"Street Light"},"geometry":{"type":"Point","coordinates":[-1.349451337303627,53.779419676561332]}},
{"type":"Feature","properties":{"Park Feature":"Street Light"},"geometry":{"type":"Point","coordinates":[-1.349689171497517,53.779434446095458]}},
{"type":"Feature","properties":{"Park Feature":"Street Light"},"geometry":{"type":"Point","coordinates":[-1.350571445588851,53.779513088971697]}},
{"type":"Feature","properties":{"Park Feature":"Street Light"},"geometry":{"type":"Point","coordinates":[-1.349279128613329,53.779546543616974]}},
{"type":"Feature","properties":{"Park Feature":"Street Light"},"geometry":{"type":"Point","coordinates":[-1.349063668421248,53.779556892099194]}},
{"type":"Feature","properties":{"Park Feature":"Street Light"},"geometry":{"type":"Point","coordinates":[-1.34940353581254,53.77956687868506]}},
{"type":"Feature","properties":{"Park Feature":"Street Light"},"geometry":{"type":"Point","coordinates":[-1.349250012795949,53.779589359685701]}},
{"type":"Feature","properties":{"Park Feature":"Street Light"},"geometry":{"type":"Point","coordinates":[-1.349197077602365,53.779761812867669]}},
{"type":"Feature","properties":{"Park Feature":"Street Light"},"geometry":{"type":"Point","coordinates":[-1.349147669218743,53.780104777083864]}}
]
}
