{
"type": "FeatureCollection",
"name": "LEEDS_454_lighting",
"crs": { "type": "name", "properties": { "name": "urn:ogc:def:crs:OGC:1.3:CRS84" } },
"features": [
{"type":"Feature","properties":{"Park Feature":"Street Light"},"geometry":{"type":"Point","coordinates":[-1.348216363699876,53.89960551187248]}},
{"type":"Feature","properties":{"Park Feature":"Street Light"},"geometry":{"type":"Point","coordinates":[-1.34707930106338,53.899661417223712]}},
{"type":"Feature","properties":{"Park Feature":"Street Light"},"geometry":{"type":"Point","coordinates":[-1.347713223196945,53.899664294819807]}},
{"type":"Feature","properties":{"Park Feature":"Street Light"},"geometry":{"type":"Point","coordinates":[-1.346414985717955,53.899716792357033]}},
{"type":"Feature","properties":{"Park Feature":"Street Light"},"geometry":{"type":"Point","coordinates":[-1.347267721555764,53.89990033822906]}},
{"type":"Feature","properties":{"Park Feature":"Street Light"},"geometry":{"type":"Point","coordinates":[-1.347301826870811,53.900184203228939]}},
{"type":"Feature","properties":{"Park Feature":"Street Light"},"geometry":{"type":"Point","coordinates":[-1.34851767826208,53.900384314503491]}},
{"type":"Feature","properties":{"Park Feature":"Street Light"},"geometry":{"type":"Point","coordinates":[-1.347254622193617,53.900497399551263]}},
{"type":"Feature","properties":{"Park Feature":"Street Light"},"geometry":{"type":"Point","coordinates":[-1.348866477082757,53.900678871120881]}},
{"type":"Feature","properties":{"Park Feature":"Street Light"},"geometry":{"type":"Point","coordinates":[-1.348267085200948,53.900717755711121]}},
{"type":"Feature","properties":{"Park Feature":"Street Light"},"geometry":{"type":"Point","coordinates":[-1.347591154596661,53.900723922442104]}},
{"type":"Feature","properties":{"Park Feature":"Street Light"},"geometry":{"type":"Point","coordinates":[-1.345559194969158,53.900643508584295]}},
{"type":"Feature","properties":{"Park Feature":"Street Light"},"geometry":{"type":"Point","coordinates":[-1.347825984247884,53.900884449516077]}},
{"type":"Feature","properties":{"Park Feature":"Street Light"},"geometry":{"type":"Point","coordinates":[-1.349056665496007,53.900896733199531]}},
{"type":"Feature","properties":{"Park Feature":"Street Light"},"geometry":{"type":"Point","coordinates":[-1.34752128107198,53.901240908545198]}},
{"type":"Feature","properties":{"Park Feature":"Street Light"},"geometry":{"type":"Point","coordinates":[-1.34752128107198,53.901240908545198]}},
{"type":"Feature","properties":{"Park Feature":"Street Light"},"geometry":{"type":"Point","coordinates":[-1.347034617775634,53.901248097768836]}},
{"type":"Feature","properties":{"Park Feature":"Street Light"},"geometry":{"type":"Point","coordinates":[-1.347034617775634,53.901248097768836]}},
{"type":"Feature","properties":{"Park Feature":"Street Light"},"geometry":{"type":"Point","coordinates":[-1.348966167023013,53.901272892374173]}}
]
}
