{
"type": "FeatureCollection",
"name": "LEEDS_606_lighting",
"crs": { "type": "name", "properties": { "name": "urn:ogc:def:crs:OGC:1.3:CRS84" } },
"features": [
{"type":"Feature","properties":{"Park Feature":"Street Light"},"geometry":{"type":"Point","coordinates":[-1.392876101917425,53.797881530762119]}},
{"type":"Feature","properties":{"Park Feature":"Street Light"},"geometry":{"type":"Point","coordinates":[-1.393502386350911,53.797979071677702]}},
{"type":"Feature","properties":{"Park Feature":"Street Light"},"geometry":{"type":"Point","coordinates":[-1.394090226707672,53.798011812514808]}},
{"type":"Feature","properties":{"Park Feature":"Street Light"},"geometry":{"type":"Point","coordinates":[-1.394754709663158,53.798092686675695]}},
{"type":"Feature","properties":{"Park Feature":"Street Light"},"geometry":{"type":"Point","coordinates":[-1.395355734336271,53.798165653394932]}},
{"type":"Feature","properties":{"Park Feature":"Street Light"},"geometry":{"type":"Point","coordinates":[-1.396015522351099,53.798243407654915]}}
]
}
