{
"type": "FeatureCollection",
"name": "fb7d6b1c9c52_visibility",
"crs": { "type": "name", "properties": { "name": "urn:ogc:def:crs:OGC:1.3:CRS84" } },
"features": [
{ "type": "Feature", "properties": { "visible_points": 1, "total_points": 48, "visibility_pct": 2.083333333333333 }, "geometry": { "type": "Point", "coordinates": [ -0.223473687949341, 53.978372144361487 ] } },
{ "type": "Feature", "properties": { "visible_points": 0, "total_points": 51, "visibility_pct": 0.0 }, "geometry": { "type": "Point", "coordinates": [ -0.223262514662562, 53.978369022312307 ] } },
{ "type": "Feature", "properties": { "visible_points": 0, "total_points": 52, "visibility_pct": 0.0 }, "geometry": { "type": "Point", "coordinates": [ -0.223051341415645, 53.978365899892189 ] } },
{ "type": "Feature", "properties": { "visible_points": 3, "total_points": 52, "visibility_pct": 5.7692307692307692 }, "geometry": { "type": "Point", "coordinates": [ -0.222840168208574, 53.978362777101118 ] } },
{ "type": "Feature", "properties": { "visible_points": 0, "total_points": 47, "visibility_pct": 0.0 }, "geometry": { "type": "Point", "coordinates": [ -0.223574691091123, 53.97848150505579 ] } },
{ "type": "Feature", "properties": { "visible_points": 1, "total_points": 51, "visibility_pct": 1.9607843137254901 }, "geometry": { "type": "Point", "coordinates": [ -0.223363517241778, 53.978478383179265 ] } },
{ "type": "Feature", "properties": { "visible_points": 0, "total_points": 52, "visibility_pct": 0.0 }, "geometry": { "type": "Point", "coordinates": [ -0.223152343432286, 53.978475260931795 ] } },
{ "type": "Feature", "properties": { "visible_points": 4, "total_points": 52, "visibility_pct": 7.6923076923076925 }, "geometry": { "type": "Point", "coordinates": [ -0.222941169662645, 53.978472138313371 ] } },
{ "type": "Feature", "properties": { "visible_points": 3, "total_points": 52, "visibility_pct": 5.7692307692307692 }, "geometry": { "type": "Point", "coordinates": [ -0.22272999593286, 53.978469015324009 ] } },
{ "type": "Feature", "properties": { "visible_points": 0, "total_points": 47, "visibility_pct": 0.0 }, "geometry": { "type": "Point", "coordinates": [ -0.222518822242941, 53.978465891963687 ] } },
{ "type": "Feature", "properties": { "visible_points": 0, "total_points": 51, "visibility_pct": 0.0 }, "geometry": { "type": "Point", "coordinates": [ -0.223464520343693, 53.978587743964098 ] } },
{ "type": "Feature", "properties": { "visible_points": 1, "total_points": 52, "visibility_pct": 1.9230769230769231 }, "geometry": { "type": "Point", "coordinates": [ -0.223253345971623, 53.978584621889262 ] } },
{ "type": "Feature", "properties": { "visible_points": 0, "total_points": 52, "visibility_pct": 0.0 }, "geometry": { "type": "Point", "coordinates": [ -0.223042171639404, 53.978581499443486 ] } },
{ "type": "Feature", "properties": { "visible_points": 3, "total_points": 52, "visibility_pct": 5.7692307692307692 }, "geometry": { "type": "Point", "coordinates": [ -0.222830997347048, 53.978578376626771 ] } },
{ "type": "Feature", "properties": { "visible_points": 4, "total_points": 50, "visibility_pct": 8.0 }, "geometry": { "type": "Point", "coordinates": [ -0.222619823094543, 53.978575253439097 ] } },
{ "type": "Feature", "properties": { "visible_points": 3, "total_points": 52, "visibility_pct": 5.7692307692307692 }, "geometry": { "type": "Point", "coordinates": [ -0.223143174138871, 53.978690860491461 ] } },
{ "type": "Feature", "properties": { "visible_points": 0, "total_points": 52, "visibility_pct": 0.0 }, "geometry": { "type": "Point", "coordinates": [ -0.222931999283929, 53.978687737847395 ] } },
{ "type": "Feature", "properties": { "visible_points": 0, "total_points": 51, "visibility_pct": 0.0 }, "geometry": { "type": "Point", "coordinates": [ -0.222720824468845, 53.978684614832339 ] } },
{ "type": "Feature", "properties": { "visible_points": 4, "total_points": 45, "visibility_pct": 8.8888888888888893 }, "geometry": { "type": "Point", "coordinates": [ -0.222509649693625, 53.97868149144638 ] } },
{ "type": "Feature", "properties": { "visible_points": 5, "total_points": 45, "visibility_pct": 11.111111111111111 }, "geometry": { "type": "Point", "coordinates": [ -0.222610651028039, 53.978790852930146 ] } }
]
}
