{
"type": "FeatureCollection",
"name": "fc3bdd4bb307_visibility",
"crs": { "type": "name", "properties": { "name": "urn:ogc:def:crs:OGC:1.3:CRS84" } },
"features": [
{ "type": "Feature", "properties": { "visible_points": 0, "total_points": 53, "visibility_pct": 0.0 }, "geometry": { "type": "Point", "coordinates": [ -0.917379764721367, 53.991390131835892 ] } },
{ "type": "Feature", "properties": { "visible_points": 1, "total_points": 53, "visibility_pct": 1.8867924528301887 }, "geometry": { "type": "Point", "coordinates": [ -0.91716846357825, 53.991388230256028 ] } },
{ "type": "Feature", "properties": { "visible_points": 0, "total_points": 52, "visibility_pct": 0.0 }, "geometry": { "type": "Point", "coordinates": [ -0.916957162459543, 53.991386328304728 ] } },
{ "type": "Feature", "properties": { "visible_points": 0, "total_points": 54, "visibility_pct": 0.0 }, "geometry": { "type": "Point", "coordinates": [ -0.917271319813181, 53.991497010967372 ] } },
{ "type": "Feature", "properties": { "visible_points": 1, "total_points": 54, "visibility_pct": 1.8518518518518516 }, "geometry": { "type": "Point", "coordinates": [ -0.917060018136107, 53.991495109193714 ] } },
{ "type": "Feature", "properties": { "visible_points": 2, "total_points": 53, "visibility_pct": 3.7735849056603774 }, "geometry": { "type": "Point", "coordinates": [ -0.91684871648345, 53.991493207048634 ] } },
{ "type": "Feature", "properties": { "visible_points": 1, "total_points": 54, "visibility_pct": 1.8518518518518516 }, "geometry": { "type": "Point", "coordinates": [ -0.917374176582045, 53.991605791591887 ] } },
{ "type": "Feature", "properties": { "visible_points": 0, "total_points": 54, "visibility_pct": 0.0 }, "geometry": { "type": "Point", "coordinates": [ -0.917162874346615, 53.991603889995858 ] } },
{ "type": "Feature", "properties": { "visible_points": 0, "total_points": 54, "visibility_pct": 0.0 }, "geometry": { "type": "Point", "coordinates": [ -0.916951572135586, 53.991601988028414 ] } },
{ "type": "Feature", "properties": { "visible_points": 4, "total_points": 53, "visibility_pct": 7.5471698113207548 }, "geometry": { "type": "Point", "coordinates": [ -0.916740269948972, 53.991600085689534 ] } },
{ "type": "Feature", "properties": { "visible_points": 1, "total_points": 54, "visibility_pct": 1.8518518518518516 }, "geometry": { "type": "Point", "coordinates": [ -0.917477033884855, 53.991714572129574 ] } },
{ "type": "Feature", "properties": { "visible_points": 1, "total_points": 54, "visibility_pct": 1.8518518518518516 }, "geometry": { "type": "Point", "coordinates": [ -0.917265731091056, 53.991712670711181 ] } },
{ "type": "Feature", "properties": { "visible_points": 0, "total_points": 54, "visibility_pct": 0.0 }, "geometry": { "type": "Point", "coordinates": [ -0.91705442832166, 53.991710768921372 ] } },
{ "type": "Feature", "properties": { "visible_points": 5, "total_points": 54, "visibility_pct": 9.2592592592592595 }, "geometry": { "type": "Point", "coordinates": [ -0.916843125576681, 53.991708866760128 ] } },
{ "type": "Feature", "properties": { "visible_points": 5, "total_points": 54, "visibility_pct": 9.2592592592592595 }, "geometry": { "type": "Point", "coordinates": [ -0.917368588369463, 53.991821451339639 ] } },
{ "type": "Feature", "properties": { "visible_points": 4, "total_points": 54, "visibility_pct": 7.4074074074074066 }, "geometry": { "type": "Point", "coordinates": [ -0.917157285041677, 53.991819549727502 ] } },
{ "type": "Feature", "properties": { "visible_points": 10, "total_points": 53, "visibility_pct": 18.867924528301888 }, "geometry": { "type": "Point", "coordinates": [ -0.916945981738325, 53.991817647743886 ] } },
{ "type": "Feature", "properties": { "visible_points": 0, "total_points": 46, "visibility_pct": 0.0 }, "geometry": { "type": "Point", "coordinates": [ -0.917471446214512, 53.991930231870299 ] } },
{ "type": "Feature", "properties": { "visible_points": 2, "total_points": 49, "visibility_pct": 4.0816326530612246 }, "geometry": { "type": "Point", "coordinates": [ -0.917260142326187, 53.991928330436082 ] } },
{ "type": "Feature", "properties": { "visible_points": 9, "total_points": 49, "visibility_pct": 18.367346938775512 }, "geometry": { "type": "Point", "coordinates": [ -0.917048838462718, 53.991926428630343 ] } }
]
}
