{
"type": "FeatureCollection",
"name": "c96d3f6cfc20_visibility",
"crs": { "type": "name", "properties": { "name": "urn:ogc:def:crs:OGC:1.3:CRS84" } },
"features": [
{ "type": "Feature", "properties": { "visible_points": 0, "total_points": 57, "visibility_pct": 0.0 }, "geometry": { "type": "Point", "coordinates": [ -0.162696589298679, 53.5782716783947 ] } },
{ "type": "Feature", "properties": { "visible_points": 0, "total_points": 52, "visibility_pct": 0.0 }, "geometry": { "type": "Point", "coordinates": [ -0.162487424564399, 53.578268467369291 ] } },
{ "type": "Feature", "properties": { "visible_points": 0, "total_points": 61, "visibility_pct": 0.0 }, "geometry": { "type": "Point", "coordinates": [ -0.163005662105695, 53.578384296109974 ] } },
{ "type": "Feature", "properties": { "visible_points": 0, "total_points": 61, "visibility_pct": 0.0 }, "geometry": { "type": "Point", "coordinates": [ -0.16279649678651, 53.578381085630866 ] } },
{ "type": "Feature", "properties": { "visible_points": 0, "total_points": 58, "visibility_pct": 0.0 }, "geometry": { "type": "Point", "coordinates": [ -0.162587331507315, 53.578377874785637 ] } },
{ "type": "Feature", "properties": { "visible_points": 0, "total_points": 53, "visibility_pct": 0.0 }, "geometry": { "type": "Point", "coordinates": [ -0.162378166268126, 53.57837466357423 ] } },
{ "type": "Feature", "properties": { "visible_points": 0, "total_points": 54, "visibility_pct": 0.0 }, "geometry": { "type": "Point", "coordinates": [ -0.163314736547432, 53.578496913008387 ] } },
{ "type": "Feature", "properties": { "visible_points": 0, "total_points": 61, "visibility_pct": 0.0 }, "geometry": { "type": "Point", "coordinates": [ -0.163105570643336, 53.578493703075601 ] } },
{ "type": "Feature", "properties": { "visible_points": 0, "total_points": 61, "visibility_pct": 0.0 }, "geometry": { "type": "Point", "coordinates": [ -0.16289640477924, 53.578490492776638 ] } },
{ "type": "Feature", "properties": { "visible_points": 0, "total_points": 61, "visibility_pct": 0.0 }, "geometry": { "type": "Point", "coordinates": [ -0.162687238955137, 53.578487282111546 ] } },
{ "type": "Feature", "properties": { "visible_points": 0, "total_points": 57, "visibility_pct": 0.0 }, "geometry": { "type": "Point", "coordinates": [ -0.162478073171024, 53.578484071080297 ] } },
{ "type": "Feature", "properties": { "visible_points": 0, "total_points": 52, "visibility_pct": 0.0 }, "geometry": { "type": "Point", "coordinates": [ -0.162268907426926, 53.578480859682898 ] } },
{ "type": "Feature", "properties": { "visible_points": 0, "total_points": 49, "visibility_pct": 0.0 }, "geometry": { "type": "Point", "coordinates": [ -0.163414646134902, 53.578606319703447 ] } },
{ "type": "Feature", "properties": { "visible_points": 0, "total_points": 56, "visibility_pct": 0.0 }, "geometry": { "type": "Point", "coordinates": [ -0.163205479685891, 53.578603109950812 ] } },
{ "type": "Feature", "properties": { "visible_points": 0, "total_points": 61, "visibility_pct": 0.0 }, "geometry": { "type": "Point", "coordinates": [ -0.16299631327688, 53.578599899832014 ] } },
{ "type": "Feature", "properties": { "visible_points": 0, "total_points": 61, "visibility_pct": 0.0 }, "geometry": { "type": "Point", "coordinates": [ -0.162787146907857, 53.57859668934708 ] } },
{ "type": "Feature", "properties": { "visible_points": 0, "total_points": 61, "visibility_pct": 0.0 }, "geometry": { "type": "Point", "coordinates": [ -0.162577980578831, 53.578593478495947 ] } },
{ "type": "Feature", "properties": { "visible_points": 0, "total_points": 56, "visibility_pct": 0.0 }, "geometry": { "type": "Point", "coordinates": [ -0.162368814289807, 53.578590267278699 ] } },
{ "type": "Feature", "properties": { "visible_points": 0, "total_points": 49, "visibility_pct": 0.0 }, "geometry": { "type": "Point", "coordinates": [ -0.163305389233362, 53.578712516735607 ] } },
{ "type": "Feature", "properties": { "visible_points": 0, "total_points": 56, "visibility_pct": 0.0 }, "geometry": { "type": "Point", "coordinates": [ -0.163096222279426, 53.578709306796959 ] } },
{ "type": "Feature", "properties": { "visible_points": 0, "total_points": 60, "visibility_pct": 0.0 }, "geometry": { "type": "Point", "coordinates": [ -0.162887055365487, 53.578706096492162 ] } },
{ "type": "Feature", "properties": { "visible_points": 0, "total_points": 61, "visibility_pct": 0.0 }, "geometry": { "type": "Point", "coordinates": [ -0.162677888491539, 53.578702885821208 ] } },
{ "type": "Feature", "properties": { "visible_points": 0, "total_points": 49, "visibility_pct": 0.0 }, "geometry": { "type": "Point", "coordinates": [ -0.163196131786895, 53.578818713671509 ] } },
{ "type": "Feature", "properties": { "visible_points": 0, "total_points": 54, "visibility_pct": 0.0 }, "geometry": { "type": "Point", "coordinates": [ -0.162986964328028, 53.578815503546856 ] } }
]
}
