{
"type": "FeatureCollection",
"name": "EASRI_515",
"crs": { "type": "name", "properties": { "name": "urn:ogc:def:crs:OGC:1.3:CRS84" } },
"features": [
{ "type": "Feature", "properties": { "osm_id": 9537392930, "name": null, "amenity": "bench", "man_made": null, "leisure": null, "playground": null, "memorial": null }, "geometry": { "type": "Point", "coordinates": [ -0.4250679, 53.8395163 ] } },
{ "type": "Feature", "properties": { "osm_id": 9537392931, "name": null, "amenity": "bench", "man_made": null, "leisure": null, "playground": null, "memorial": null }, "geometry": { "type": "Point", "coordinates": [ -0.4249676, 53.8395436 ] } }
]
}
