{
"type": "FeatureCollection",
"name": "2e1ba8ef7cd7_visibility",
"crs": { "type": "name", "properties": { "name": "urn:ogc:def:crs:OGC:1.3:CRS84" } },
"features": [
{ "type": "Feature", "properties": { "visible_points": 0, "total_points": 42, "visibility_pct": 0.0 }, "geometry": { "type": "Point", "coordinates": [ -1.345025095023461, 53.904221257517094 ] } },
{ "type": "Feature", "properties": { "visible_points": 2, "total_points": 45, "visibility_pct": 4.4444444444444446 }, "geometry": { "type": "Point", "coordinates": [ -1.344814209271455, 53.904220109061228 ] } },
{ "type": "Feature", "properties": { "visible_points": 0, "total_points": 44, "visibility_pct": 0.0 }, "geometry": { "type": "Point", "coordinates": [ -1.345128853296122, 53.904329677005293 ] } },
{ "type": "Feature", "properties": { "visible_points": 0, "total_points": 48, "visibility_pct": 0.0 }, "geometry": { "type": "Point", "coordinates": [ -1.34491796698884, 53.904328528729941 ] } },
{ "type": "Feature", "properties": { "visible_points": 3, "total_points": 51, "visibility_pct": 5.8823529411764701 }, "geometry": { "type": "Point", "coordinates": [ -1.344707080696338, 53.904327380084219 ] } },
{ "type": "Feature", "properties": { "visible_points": 0, "total_points": 50, "visibility_pct": 0.0 }, "geometry": { "type": "Point", "coordinates": [ -1.345021725246692, 53.904436948308749 ] } },
{ "type": "Feature", "properties": { "visible_points": 0, "total_points": 54, "visibility_pct": 0.0 }, "geometry": { "type": "Point", "coordinates": [ -1.344810838398912, 53.904435799843533 ] } },
{ "type": "Feature", "properties": { "visible_points": 4, "total_points": 56, "visibility_pct": 7.1428571428571423 }, "geometry": { "type": "Point", "coordinates": [ -1.34459995156593, 53.904434651007968 ] } },
{ "type": "Feature", "properties": { "visible_points": 1, "total_points": 55, "visibility_pct": 1.8181818181818181 }, "geometry": { "type": "Point", "coordinates": [ -1.344914596641962, 53.904544219512957 ] } },
{ "type": "Feature", "properties": { "visible_points": 0, "total_points": 57, "visibility_pct": 0.0 }, "geometry": { "type": "Point", "coordinates": [ -1.344703709253685, 53.904543070857919 ] } },
{ "type": "Feature", "properties": { "visible_points": 5, "total_points": 57, "visibility_pct": 8.7719298245614024 }, "geometry": { "type": "Point", "coordinates": [ -1.344492821880213, 53.904541921832461 ] } },
{ "type": "Feature", "properties": { "visible_points": 2, "total_points": 57, "visibility_pct": 3.5087719298245612 }, "geometry": { "type": "Point", "coordinates": [ -1.344807467481921, 53.904651490617937 ] } },
{ "type": "Feature", "properties": { "visible_points": 0, "total_points": 57, "visibility_pct": 0.0 }, "geometry": { "type": "Point", "coordinates": [ -1.34459657955315, 53.904650341773035 ] } },
{ "type": "Feature", "properties": { "visible_points": 3, "total_points": 54, "visibility_pct": 5.5555555555555554 }, "geometry": { "type": "Point", "coordinates": [ -1.344385691639185, 53.904649192557748 ] } },
{ "type": "Feature", "properties": { "visible_points": 1, "total_points": 54, "visibility_pct": 1.8518518518518516 }, "geometry": { "type": "Point", "coordinates": [ -1.344700337766572, 53.90475876162369 ] } },
{ "type": "Feature", "properties": { "visible_points": 0, "total_points": 52, "visibility_pct": 0.0 }, "geometry": { "type": "Point", "coordinates": [ -1.344489449297303, 53.904757612588938 ] } },
{ "type": "Feature", "properties": { "visible_points": 1, "total_points": 48, "visibility_pct": 2.083333333333333 }, "geometry": { "type": "Point", "coordinates": [ -1.344278560842841, 53.90475646318378 ] } },
{ "type": "Feature", "properties": { "visible_points": 0, "total_points": 49, "visibility_pct": 0.0 }, "geometry": { "type": "Point", "coordinates": [ -1.344593207495908, 53.904866032530208 ] } },
{ "type": "Feature", "properties": { "visible_points": 0, "total_points": 46, "visibility_pct": 0.0 }, "geometry": { "type": "Point", "coordinates": [ -1.344382318486135, 53.904864883305592 ] } },
{ "type": "Feature", "properties": { "visible_points": 1, "total_points": 42, "visibility_pct": 2.3809523809523809 }, "geometry": { "type": "Point", "coordinates": [ -1.34417142949118, 53.904863733710592 ] } },
{ "type": "Feature", "properties": { "visible_points": 0, "total_points": 42, "visibility_pct": 0.0 }, "geometry": { "type": "Point", "coordinates": [ -1.344486076669924, 53.904973303337478 ] } },
{ "type": "Feature", "properties": { "visible_points": 0, "total_points": 39, "visibility_pct": 0.0 }, "geometry": { "type": "Point", "coordinates": [ -1.344275187119648, 53.904972153923005 ] } },
{ "type": "Feature", "properties": { "visible_points": 1, "total_points": 36, "visibility_pct": 2.7777777777777777 }, "geometry": { "type": "Point", "coordinates": [ -1.344064297584192, 53.90497100413814 ] } }
]
}
