{
"type": "FeatureCollection",
"name": "7d5e7a2194a2_visibility",
"crs": { "type": "name", "properties": { "name": "urn:ogc:def:crs:OGC:1.3:CRS84" } },
"features": [
{ "type": "Feature", "properties": { "visible_points": 0, "total_points": 48, "visibility_pct": 0.0 }, "geometry": { "type": "Point", "coordinates": [ -1.652138090633746, 53.801326274635741 ] } },
{ "type": "Feature", "properties": { "visible_points": 0, "total_points": 48, "visibility_pct": 0.0 }, "geometry": { "type": "Point", "coordinates": [ -1.651927714772637, 53.801325666124455 ] } },
{ "type": "Feature", "properties": { "visible_points": 1, "total_points": 53, "visibility_pct": 1.8867924528301887 }, "geometry": { "type": "Point", "coordinates": [ -1.652242389710886, 53.801434432061008 ] } },
{ "type": "Feature", "properties": { "visible_points": 0, "total_points": 54, "visibility_pct": 0.0 }, "geometry": { "type": "Point", "coordinates": [ -1.652032013312027, 53.801433823731173 ] } },
{ "type": "Feature", "properties": { "visible_points": 1, "total_points": 53, "visibility_pct": 1.8867924528301887 }, "geometry": { "type": "Point", "coordinates": [ -1.651821636920853, 53.801433215032276 ] } },
{ "type": "Feature", "properties": { "visible_points": 0, "total_points": 58, "visibility_pct": 0.0 }, "geometry": { "type": "Point", "coordinates": [ -1.652136312381456, 53.801541981246729 ] } },
{ "type": "Feature", "properties": { "visible_points": 1, "total_points": 58, "visibility_pct": 1.7241379310344827 }, "geometry": { "type": "Point", "coordinates": [ -1.651925935452531, 53.801541372729304 ] } },
{ "type": "Feature", "properties": { "visible_points": 1, "total_points": 58, "visibility_pct": 1.7241379310344827 }, "geometry": { "type": "Point", "coordinates": [ -1.652240611980935, 53.801650138671135 ] } },
{ "type": "Feature", "properties": { "visible_points": 3, "total_points": 58, "visibility_pct": 5.1724137931034484 }, "geometry": { "type": "Point", "coordinates": [ -1.652030234514252, 53.801649530335162 ] } },
{ "type": "Feature", "properties": { "visible_points": 5, "total_points": 58, "visibility_pct": 8.6206896551724146 }, "geometry": { "type": "Point", "coordinates": [ -1.651819857055262, 53.801648921630139 ] } },
{ "type": "Feature", "properties": { "visible_points": 2, "total_points": 58, "visibility_pct": 3.4482758620689653 }, "geometry": { "type": "Point", "coordinates": [ -1.651609479401781, 53.801648312569874 ] } },
{ "type": "Feature", "properties": { "visible_points": 2, "total_points": 58, "visibility_pct": 3.4482758620689653 }, "geometry": { "type": "Point", "coordinates": [ -1.652134534106023, 53.801757687849879 ] } },
{ "type": "Feature", "properties": { "visible_points": 5, "total_points": 58, "visibility_pct": 8.6206896551724146 }, "geometry": { "type": "Point", "coordinates": [ -1.651924156109269, 53.8017570793263 ] } },
{ "type": "Feature", "properties": { "visible_points": 1, "total_points": 57, "visibility_pct": 1.7543859649122806 }, "geometry": { "type": "Point", "coordinates": [ -1.651713778120206, 53.801756470433673 ] } },
{ "type": "Feature", "properties": { "visible_points": 2, "total_points": 53, "visibility_pct": 3.7735849056603774 }, "geometry": { "type": "Point", "coordinates": [ -1.652238834227847, 53.801865845273433 ] } },
{ "type": "Feature", "properties": { "visible_points": 4, "total_points": 54, "visibility_pct": 7.4074074074074066 }, "geometry": { "type": "Point", "coordinates": [ -1.652028455693324, 53.801865236931306 ] } },
{ "type": "Feature", "properties": { "visible_points": 1, "total_points": 53, "visibility_pct": 1.8867924528301887 }, "geometry": { "type": "Point", "coordinates": [ -1.651818077166501, 53.801864628220144 ] } },
{ "type": "Feature", "properties": { "visible_points": 1, "total_points": 48, "visibility_pct": 2.083333333333333 }, "geometry": { "type": "Point", "coordinates": [ -1.652132755807443, 53.80197339444517 ] } },
{ "type": "Feature", "properties": { "visible_points": 0, "total_points": 48, "visibility_pct": 0.0 }, "geometry": { "type": "Point", "coordinates": [ -1.651922376742844, 53.801972785915453 ] } },
{ "type": "Feature", "properties": { "visible_points": 0, "total_points": 47, "visibility_pct": 0.0 }, "geometry": { "type": "Point", "coordinates": [ -1.651711997685947, 53.801972177016687 ] } },
{ "type": "Feature", "properties": { "visible_points": 0, "total_points": 43, "visibility_pct": 0.0 }, "geometry": { "type": "Point", "coordinates": [ -1.652026676849248, 53.80208094351962 ] } },
{ "type": "Feature", "properties": { "visible_points": 1, "total_points": 42, "visibility_pct": 2.3809523809523809 }, "geometry": { "type": "Point", "coordinates": [ -1.651816297254576, 53.802080334802298 ] } }
]
}
