{
"type": "FeatureCollection",
"name": "d5e32cb64a8a_visibility",
"crs": { "type": "name", "properties": { "name": "urn:ogc:def:crs:OGC:1.3:CRS84" } },
"features": [
{ "type": "Feature", "properties": { "visible_points": 1, "total_points": 45, "visibility_pct": 2.2222222222222223 }, "geometry": { "type": "Point", "coordinates": [ -1.396402276348792, 53.940257067743048 ] } },
{ "type": "Feature", "properties": { "visible_points": 5, "total_points": 44, "visibility_pct": 11.363636363636363 }, "geometry": { "type": "Point", "coordinates": [ -1.396191206893433, 53.940256008990772 ] } },
{ "type": "Feature", "properties": { "visible_points": 0, "total_points": 41, "visibility_pct": 0.0 }, "geometry": { "type": "Point", "coordinates": [ -1.395980137451644, 53.940254949867644 ] } },
{ "type": "Feature", "properties": { "visible_points": 0, "total_points": 51, "visibility_pct": 0.0 }, "geometry": { "type": "Point", "coordinates": [ -1.396506256775248, 53.940365442810474 ] } },
{ "type": "Feature", "properties": { "visible_points": 5, "total_points": 50, "visibility_pct": 10.0 }, "geometry": { "type": "Point", "coordinates": [ -1.396295186768798, 53.940364384239288 ] } },
{ "type": "Feature", "properties": { "visible_points": 0, "total_points": 48, "visibility_pct": 0.0 }, "geometry": { "type": "Point", "coordinates": [ -1.396084116775909, 53.940363325297227 ] } },
{ "type": "Feature", "properties": { "visible_points": 0, "total_points": 51, "visibility_pct": 0.0 }, "geometry": { "type": "Point", "coordinates": [ -1.396610237739221, 53.940473817787549 ] } },
{ "type": "Feature", "properties": { "visible_points": 5, "total_points": 51, "visibility_pct": 9.8039215686274517 }, "geometry": { "type": "Point", "coordinates": [ -1.39639916718167, 53.940472759397466 ] } },
{ "type": "Feature", "properties": { "visible_points": 5, "total_points": 51, "visibility_pct": 9.8039215686274517 }, "geometry": { "type": "Point", "coordinates": [ -1.396188096637685, 53.940471700636493 ] } },
{ "type": "Feature", "properties": { "visible_points": 0, "total_points": 49, "visibility_pct": 0.0 }, "geometry": { "type": "Point", "coordinates": [ -1.395977026107272, 53.940470641504625 ] } },
{ "type": "Feature", "properties": { "visible_points": 5, "total_points": 51, "visibility_pct": 9.8039215686274517 }, "geometry": { "type": "Point", "coordinates": [ -1.396503148132062, 53.940581134465297 ] } },
{ "type": "Feature", "properties": { "visible_points": 5, "total_points": 51, "visibility_pct": 9.8039215686274517 }, "geometry": { "type": "Point", "coordinates": [ -1.396292077036978, 53.940580075885407 ] } },
{ "type": "Feature", "properties": { "visible_points": 0, "total_points": 51, "visibility_pct": 0.0 }, "geometry": { "type": "Point", "coordinates": [ -1.396081005955457, 53.940579016934635 ] } },
{ "type": "Feature", "properties": { "visible_points": 7, "total_points": 50, "visibility_pct": 14.000000000000002 }, "geometry": { "type": "Point", "coordinates": [ -1.396607129619977, 53.940689509442784 ] } },
{ "type": "Feature", "properties": { "visible_points": 6, "total_points": 51, "visibility_pct": 11.76470588235294 }, "geometry": { "type": "Point", "coordinates": [ -1.396396057973787, 53.940688451043982 ] } },
{ "type": "Feature", "properties": { "visible_points": 0, "total_points": 51, "visibility_pct": 0.0 }, "geometry": { "type": "Point", "coordinates": [ -1.396184986341162, 53.940687392274285 ] } },
{ "type": "Feature", "properties": { "visible_points": 4, "total_points": 45, "visibility_pct": 8.8888888888888893 }, "geometry": { "type": "Point", "coordinates": [ -1.396711111645422, 53.940797884329918 ] } },
{ "type": "Feature", "properties": { "visible_points": 2, "total_points": 47, "visibility_pct": 4.2553191489361701 }, "geometry": { "type": "Point", "coordinates": [ -1.396500039448124, 53.940796826112205 ] } },
{ "type": "Feature", "properties": { "visible_points": 5, "total_points": 48, "visibility_pct": 10.416666666666668 }, "geometry": { "type": "Point", "coordinates": [ -1.396288967264385, 53.940795767523618 ] } },
{ "type": "Feature", "properties": { "visible_points": 3, "total_points": 42, "visibility_pct": 7.1428571428571423 }, "geometry": { "type": "Point", "coordinates": [ -1.396604021459989, 53.940905201090082 ] } },
{ "type": "Feature", "properties": { "visible_points": 4, "total_points": 43, "visibility_pct": 9.3023255813953494 }, "geometry": { "type": "Point", "coordinates": [ -1.39639294872514, 53.940904142682598 ] } }
]
}
