{
"type": "FeatureCollection",
"name": "e169aacc04d0_visibility",
"crs": { "type": "name", "properties": { "name": "urn:ogc:def:crs:OGC:1.3:CRS84" } },
"features": [
{ "type": "Feature", "properties": { "visible_points": 3, "total_points": 39, "visibility_pct": 7.6923076923076925 }, "geometry": { "type": "Point", "coordinates": [ -1.572385233479368, 53.7559250966072 ] } },
{ "type": "Feature", "properties": { "visible_points": 2, "total_points": 43, "visibility_pct": 4.6511627906976747 }, "geometry": { "type": "Point", "coordinates": [ -1.5721750855734, 53.755924349186905 ] } },
{ "type": "Feature", "properties": { "visible_points": 5, "total_points": 45, "visibility_pct": 11.111111111111111 }, "geometry": { "type": "Point", "coordinates": [ -1.57196493767703, 53.755923601398173 ] } },
{ "type": "Feature", "properties": { "visible_points": 3, "total_points": 46, "visibility_pct": 6.5217391304347823 }, "geometry": { "type": "Point", "coordinates": [ -1.571754789790268, 53.755922853241017 ] } },
{ "type": "Feature", "properties": { "visible_points": 1, "total_points": 49, "visibility_pct": 2.0408163265306123 }, "geometry": { "type": "Point", "coordinates": [ -1.572068918098934, 53.756031829328464 ] } },
{ "type": "Feature", "properties": { "visible_points": 0, "total_points": 50, "visibility_pct": 0.0 }, "geometry": { "type": "Point", "coordinates": [ -1.571858769662891, 53.756031081351992 ] } },
{ "type": "Feature", "properties": { "visible_points": 2, "total_points": 51, "visibility_pct": 3.9215686274509802 }, "geometry": { "type": "Point", "coordinates": [ -1.571648621236458, 53.756030333007104 ] } },
{ "type": "Feature", "properties": { "visible_points": 6, "total_points": 50, "visibility_pct": 12.0 }, "geometry": { "type": "Point", "coordinates": [ -1.571438472819635, 53.756029584293756 ] } },
{ "type": "Feature", "properties": { "visible_points": 2, "total_points": 55, "visibility_pct": 3.6363636363636362 }, "geometry": { "type": "Point", "coordinates": [ -1.571542452133342, 53.756137812675561 ] } },
{ "type": "Feature", "properties": { "visible_points": 0, "total_points": 60, "visibility_pct": 0.0 }, "geometry": { "type": "Point", "coordinates": [ -1.571646431986703, 53.756246040966822 ] } },
{ "type": "Feature", "properties": { "visible_points": 4, "total_points": 56, "visibility_pct": 7.1428571428571423 }, "geometry": { "type": "Point", "coordinates": [ -1.571436282480919, 53.756245292246419 ] } },
{ "type": "Feature", "properties": { "visible_points": 0, "total_points": 59, "visibility_pct": 0.0 }, "geometry": { "type": "Point", "coordinates": [ -1.571750412379732, 53.756354269167531 ] } },
{ "type": "Feature", "properties": { "visible_points": 0, "total_points": 56, "visibility_pct": 0.0 }, "geometry": { "type": "Point", "coordinates": [ -1.571540262324645, 53.756353520627805 ] } },
{ "type": "Feature", "properties": { "visible_points": 1, "total_points": 54, "visibility_pct": 1.8518518518518516 }, "geometry": { "type": "Point", "coordinates": [ -1.571644242708045, 53.756461748918674 ] } },
{ "type": "Feature", "properties": { "visible_points": 6, "total_points": 51, "visibility_pct": 11.76470588235294 }, "geometry": { "type": "Point", "coordinates": [ -1.571434092113273, 53.756461000191187 ] } },
{ "type": "Feature", "properties": { "visible_points": 1, "total_points": 49, "visibility_pct": 2.0408163265306123 }, "geometry": { "type": "Point", "coordinates": [ -1.571748223631108, 53.756569977118993 ] } },
{ "type": "Feature", "properties": { "visible_points": 0, "total_points": 47, "visibility_pct": 0.0 }, "geometry": { "type": "Point", "coordinates": [ -1.571538072487037, 53.756569228572189 ] } },
{ "type": "Feature", "properties": { "visible_points": 0, "total_points": 42, "visibility_pct": 0.0 }, "geometry": { "type": "Point", "coordinates": [ -1.571642053400472, 53.756677456862654 ] } },
{ "type": "Feature", "properties": { "visible_points": 7, "total_points": 40, "visibility_pct": 17.5 }, "geometry": { "type": "Point", "coordinates": [ -1.571431901716712, 53.756676708128111 ] } },
{ "type": "Feature", "properties": { "visible_points": 2, "total_points": 36, "visibility_pct": 5.5555555555555554 }, "geometry": { "type": "Point", "coordinates": [ -1.571746034853588, 53.75678568506256 ] } },
{ "type": "Feature", "properties": { "visible_points": 3, "total_points": 35, "visibility_pct": 8.5714285714285712 }, "geometry": { "type": "Point", "coordinates": [ -1.57153588262051, 53.756784936508708 ] } }
]
}
