{
"type": "FeatureCollection",
"name": "3815293841cd_visibility",
"crs": { "type": "name", "properties": { "name": "urn:ogc:def:crs:OGC:1.3:CRS84" } },
"features": [
{ "type": "Feature", "properties": { "visible_points": 0, "total_points": 44, "visibility_pct": 0.0 }, "geometry": { "type": "Point", "coordinates": [ -0.362668296361031, 53.780963679086462 ] } },
{ "type": "Feature", "properties": { "visible_points": 4, "total_points": 49, "visibility_pct": 8.1632653061224492 }, "geometry": { "type": "Point", "coordinates": [ -0.362458104990236, 53.780960808769692 ] } },
{ "type": "Feature", "properties": { "visible_points": 0, "total_points": 52, "visibility_pct": 0.0 }, "geometry": { "type": "Point", "coordinates": [ -0.362247913656081, 53.780957938084526 ] } },
{ "type": "Feature", "properties": { "visible_points": 5, "total_points": 52, "visibility_pct": 9.6153846153846168 }, "geometry": { "type": "Point", "coordinates": [ -0.362037722358568, 53.780955067030959 ] } },
{ "type": "Feature", "properties": { "visible_points": 4, "total_points": 49, "visibility_pct": 8.1632653061224492 }, "geometry": { "type": "Point", "coordinates": [ -0.361827531097697, 53.780952195608997 ] } },
{ "type": "Feature", "properties": { "visible_points": 5, "total_points": 43, "visibility_pct": 11.627906976744185 }, "geometry": { "type": "Point", "coordinates": [ -0.36161733987348, 53.780949323818618 ] } },
{ "type": "Feature", "properties": { "visible_points": 6, "total_points": 42, "visibility_pct": 14.285714285714285 }, "geometry": { "type": "Point", "coordinates": [ -0.362769198417025, 53.781072923442302 ] } },
{ "type": "Feature", "properties": { "visible_points": 6, "total_points": 47, "visibility_pct": 12.76595744680851 }, "geometry": { "type": "Point", "coordinates": [ -0.362559006485563, 53.78107005329889 ] } },
{ "type": "Feature", "properties": { "visible_points": 4, "total_points": 52, "visibility_pct": 7.6923076923076925 }, "geometry": { "type": "Point", "coordinates": [ -0.362348814590736, 53.781067182787076 ] } },
{ "type": "Feature", "properties": { "visible_points": 5, "total_points": 52, "visibility_pct": 9.6153846153846168 }, "geometry": { "type": "Point", "coordinates": [ -0.362138622732545, 53.781064311906839 ] } },
{ "type": "Feature", "properties": { "visible_points": 3, "total_points": 52, "visibility_pct": 5.7692307692307692 }, "geometry": { "type": "Point", "coordinates": [ -0.361928430911, 53.781061440658213 ] } },
{ "type": "Feature", "properties": { "visible_points": 0, "total_points": 46, "visibility_pct": 0.0 }, "geometry": { "type": "Point", "coordinates": [ -0.361718239126102, 53.781058569041171 ] } },
{ "type": "Feature", "properties": { "visible_points": 0, "total_points": 40, "visibility_pct": 0.0 }, "geometry": { "type": "Point", "coordinates": [ -0.361508047377861, 53.781055697055741 ] } },
{ "type": "Feature", "properties": { "visible_points": 4, "total_points": 44, "visibility_pct": 9.0909090909090917 }, "geometry": { "type": "Point", "coordinates": [ -0.362659908504906, 53.7811792977447 ] } },
{ "type": "Feature", "properties": { "visible_points": 0, "total_points": 49, "visibility_pct": 0.0 }, "geometry": { "type": "Point", "coordinates": [ -0.362449716049402, 53.781176427406209 ] } },
{ "type": "Feature", "properties": { "visible_points": 4, "total_points": 52, "visibility_pct": 7.6923076923076925 }, "geometry": { "type": "Point", "coordinates": [ -0.362239523630533, 53.781173556699336 ] } },
{ "type": "Feature", "properties": { "visible_points": 2, "total_points": 52, "visibility_pct": 3.8461538461538463 }, "geometry": { "type": "Point", "coordinates": [ -0.362029331248313, 53.781170685624033 ] } },
{ "type": "Feature", "properties": { "visible_points": 0, "total_points": 48, "visibility_pct": 0.0 }, "geometry": { "type": "Point", "coordinates": [ -0.361819138902732, 53.781167814180343 ] } },
{ "type": "Feature", "properties": { "visible_points": 2, "total_points": 42, "visibility_pct": 4.7619047619047619 }, "geometry": { "type": "Point", "coordinates": [ -0.361608946593806, 53.78116494236825 ] } },
{ "type": "Feature", "properties": { "visible_points": 3, "total_points": 36, "visibility_pct": 8.3333333333333321 }, "geometry": { "type": "Point", "coordinates": [ -0.361398754321533, 53.78116207018774 ] } }
]
}
