{
"type": "FeatureCollection",
"name": "23c8a98b8acb_visibility",
"crs": { "type": "name", "properties": { "name": "urn:ogc:def:crs:OGC:1.3:CRS84" } },
"features": [
{ "type": "Feature", "properties": { "visible_points": 0, "total_points": 50, "visibility_pct": 0.0 }, "geometry": { "type": "Point", "coordinates": [ -1.611015488588709, 53.54293774088385 ] } },
{ "type": "Feature", "properties": { "visible_points": 2, "total_points": 50, "visibility_pct": 4.0 }, "geometry": { "type": "Point", "coordinates": [ -1.610806395103493, 53.542937062494353 ] } },
{ "type": "Feature", "properties": { "visible_points": 2, "total_points": 50, "visibility_pct": 4.0 }, "geometry": { "type": "Point", "coordinates": [ -1.610597301627128, 53.542936383738962 ] } },
{ "type": "Feature", "properties": { "visible_points": 2, "total_points": 50, "visibility_pct": 4.0 }, "geometry": { "type": "Point", "coordinates": [ -1.610388208159615, 53.542935704617655 ] } },
{ "type": "Feature", "properties": { "visible_points": 2, "total_points": 45, "visibility_pct": 4.4444444444444446 }, "geometry": { "type": "Point", "coordinates": [ -1.610179114700969, 53.54293502513049 ] } },
{ "type": "Feature", "properties": { "visible_points": 3, "total_points": 50, "visibility_pct": 6.0 }, "geometry": { "type": "Point", "coordinates": [ -1.61111905236254, 53.54304593440731 ] } },
{ "type": "Feature", "properties": { "visible_points": 0, "total_points": 50, "visibility_pct": 0.0 }, "geometry": { "type": "Point", "coordinates": [ -1.61090995831693, 53.543045256222193 ] } },
{ "type": "Feature", "properties": { "visible_points": 0, "total_points": 50, "visibility_pct": 0.0 }, "geometry": { "type": "Point", "coordinates": [ -1.610700864280162, 53.543044577671154 ] } },
{ "type": "Feature", "properties": { "visible_points": 0, "total_points": 50, "visibility_pct": 0.0 }, "geometry": { "type": "Point", "coordinates": [ -1.610491770252255, 53.543043898754235 ] } },
{ "type": "Feature", "properties": { "visible_points": 4, "total_points": 50, "visibility_pct": 8.0 }, "geometry": { "type": "Point", "coordinates": [ -1.610282676233211, 53.543043219471421 ] } },
{ "type": "Feature", "properties": { "visible_points": 2, "total_points": 50, "visibility_pct": 4.0 }, "geometry": { "type": "Point", "coordinates": [ -1.611013522081885, 53.543153449835373 ] } },
{ "type": "Feature", "properties": { "visible_points": 3, "total_points": 50, "visibility_pct": 6.0 }, "geometry": { "type": "Point", "coordinates": [ -1.610804427484721, 53.543152771488728 ] } },
{ "type": "Feature", "properties": { "visible_points": 6, "total_points": 50, "visibility_pct": 12.0 }, "geometry": { "type": "Point", "coordinates": [ -1.610595332896413, 53.543152092776182 ] } },
{ "type": "Feature", "properties": { "visible_points": 5, "total_points": 50, "visibility_pct": 10.0 }, "geometry": { "type": "Point", "coordinates": [ -1.610386238316962, 53.54315141369775 ] } },
{ "type": "Feature", "properties": { "visible_points": 4, "total_points": 47, "visibility_pct": 8.5106382978723403 }, "geometry": { "type": "Point", "coordinates": [ -1.610177143746372, 53.543150734253409 ] } },
{ "type": "Feature", "properties": { "visible_points": 7, "total_points": 47, "visibility_pct": 14.893617021276595 }, "geometry": { "type": "Point", "coordinates": [ -1.611117086398367, 53.543261643333928 ] } },
{ "type": "Feature", "properties": { "visible_points": 9, "total_points": 50, "visibility_pct": 18.0 }, "geometry": { "type": "Point", "coordinates": [ -1.610907991240806, 53.543260965191656 ] } },
{ "type": "Feature", "properties": { "visible_points": 9, "total_points": 50, "visibility_pct": 18.0 }, "geometry": { "type": "Point", "coordinates": [ -1.610698896092091, 53.543260286683491 ] } },
{ "type": "Feature", "properties": { "visible_points": 4, "total_points": 50, "visibility_pct": 8.0 }, "geometry": { "type": "Point", "coordinates": [ -1.610489800952234, 53.543259607809439 ] } },
{ "type": "Feature", "properties": { "visible_points": 7, "total_points": 46, "visibility_pct": 15.217391304347828 }, "geometry": { "type": "Point", "coordinates": [ -1.611011555548417, 53.543369158779974 ] } },
{ "type": "Feature", "properties": { "visible_points": 5, "total_points": 49, "visibility_pct": 10.204081632653061 }, "geometry": { "type": "Point", "coordinates": [ -1.610802459839296, 53.543368480476168 ] } }
]
}
