{
"type": "FeatureCollection",
"name": "BARNS_53_toilets",
"crs": { "type": "name", "properties": { "name": "urn:ogc:def:crs:OGC:1.3:CRS84" } },
"features": [
{ "type": "Feature", "properties": { "name": "Barnsley Road", "payment_info": "Free", "accessible": "False", "radar": "False", "women": "True", "men": "Unknown", "baby_change": "False", "Mon": "Unknown", "Tue": "Unknown", "Wed": "Unknown", "Thu": "Unknown", "Fri": "Unknown", "Sat": "Unknown", "Sun": "Unknown", "index_right": 172, "park_offical_id": "BARNS_53" }, "geometry": { "type": "Point", "coordinates": [ -1.3116123, 53.5331186 ] } }
]
}
