{
"type": "FeatureCollection",
"name": "BARNS_79_toilets",
"crs": { "type": "name", "properties": { "name": "urn:ogc:def:crs:OGC:1.3:CRS84" } },
"features": [
{ "type": "Feature", "properties": { "name": "The ship inn ", "payment_info": "Cost unknown", "accessible": "Unknown", "radar": "Unknown", "women": "True", "men": "True", "baby_change": "Unknown", "Mon": "Unknown", "Tue": "Unknown", "Wed": "Unknown", "Thu": "Unknown", "Fri": "Unknown", "Sat": "Unknown", "Sun": "Unknown", "index_right": 200, "park_offical_id": "BARNS_79" }, "geometry": { "type": "Point", "coordinates": [ -1.470623016, 53.528628343 ] } },
{ "type": "Feature", "properties": { "name": "Miners welfare ", "payment_info": "Cost unknown", "accessible": "True", "radar": "Unknown", "women": "True", "men": "True", "baby_change": "Unknown", "Mon": "Unknown", "Tue": "Unknown", "Wed": "Unknown", "Thu": "Unknown", "Fri": "Unknown", "Sat": "Unknown", "Sun": "Unknown", "index_right": 200, "park_offical_id": "BARNS_79" }, "geometry": { "type": "Point", "coordinates": [ -1.470859051, 53.526316558 ] } },
{ "type": "Feature", "properties": { "name": "Worsbrough Mill", "payment_info": "Free", "accessible": "Unknown", "radar": "Unknown", "women": "True", "men": "True", "baby_change": "Unknown", "Mon": "Unknown", "Tue": "Unknown", "Wed": "Unknown", "Thu": "Unknown", "Fri": "Unknown", "Sat": "Unknown", "Sun": "Unknown", "index_right": 200, "park_offical_id": "BARNS_79" }, "geometry": { "type": "Point", "coordinates": [ -1.4736197, 53.5254564 ] } }
]
}
