{
"type": "FeatureCollection",
"name": "51c00f67c264_visibility",
"crs": { "type": "name", "properties": { "name": "urn:ogc:def:crs:OGC:1.3:CRS84" } },
"features": [
{ "type": "Feature", "properties": { "visible_points": 13, "total_points": 51, "visibility_pct": 25.490196078431371 }, "geometry": { "type": "Point", "coordinates": [ -2.095965922633112, 53.714297518316876 ] } },
{ "type": "Feature", "properties": { "visible_points": 13, "total_points": 52, "visibility_pct": 25.0 }, "geometry": { "type": "Point", "coordinates": [ -2.095755973783902, 53.714297688664701 ] } },
{ "type": "Feature", "properties": { "visible_points": 10, "total_points": 52, "visibility_pct": 19.230769230769234 }, "geometry": { "type": "Point", "coordinates": [ -2.095546024932587, 53.714297858644642 ] } },
{ "type": "Feature", "properties": { "visible_points": 11, "total_points": 51, "visibility_pct": 21.568627450980394 }, "geometry": { "type": "Point", "coordinates": [ -2.095336076079174, 53.714298028256692 ] } },
{ "type": "Feature", "properties": { "visible_points": 12, "total_points": 51, "visibility_pct": 23.52941176470588 }, "geometry": { "type": "Point", "coordinates": [ -2.096071146662477, 53.714405288150594 ] } },
{ "type": "Feature", "properties": { "visible_points": 10, "total_points": 52, "visibility_pct": 19.230769230769234 }, "geometry": { "type": "Point", "coordinates": [ -2.095861197281382, 53.714405458684304 ] } },
{ "type": "Feature", "properties": { "visible_points": 17, "total_points": 52, "visibility_pct": 32.692307692307693 }, "geometry": { "type": "Point", "coordinates": [ -2.095651247898179, 53.714405628850095 ] } },
{ "type": "Feature", "properties": { "visible_points": 13, "total_points": 52, "visibility_pct": 25.0 }, "geometry": { "type": "Point", "coordinates": [ -2.095441298512875, 53.714405798648038 ] } },
{ "type": "Feature", "properties": { "visible_points": 11, "total_points": 51, "visibility_pct": 21.568627450980394 }, "geometry": { "type": "Point", "coordinates": [ -2.09523134912547, 53.714405968078061 ] } },
{ "type": "Feature", "properties": { "visible_points": 11, "total_points": 50, "visibility_pct": 22.0 }, "geometry": { "type": "Point", "coordinates": [ -2.096176371225823, 53.714513057888418 ] } },
{ "type": "Feature", "properties": { "visible_points": 13, "total_points": 52, "visibility_pct": 25.0 }, "geometry": { "type": "Point", "coordinates": [ -2.095966421312835, 53.714513228608013 ] } },
{ "type": "Feature", "properties": { "visible_points": 14, "total_points": 52, "visibility_pct": 26.923076923076923 }, "geometry": { "type": "Point", "coordinates": [ -2.09575647139774, 53.714513398959724 ] } },
{ "type": "Feature", "properties": { "visible_points": 19, "total_points": 52, "visibility_pct": 36.538461538461533 }, "geometry": { "type": "Point", "coordinates": [ -2.095546521480545, 53.714513568943538 ] } },
{ "type": "Feature", "properties": { "visible_points": 17, "total_points": 52, "visibility_pct": 32.692307692307693 }, "geometry": { "type": "Point", "coordinates": [ -2.095336571561247, 53.71451373855944 ] } },
{ "type": "Feature", "properties": { "visible_points": 0, "total_points": 51, "visibility_pct": 0.0 }, "geometry": { "type": "Point", "coordinates": [ -2.09607164587827, 53.714620998435905 ] } },
{ "type": "Feature", "properties": { "visible_points": 12, "total_points": 52, "visibility_pct": 23.076923076923077 }, "geometry": { "type": "Point", "coordinates": [ -2.095861695431279, 53.71462116897348 ] } },
{ "type": "Feature", "properties": { "visible_points": 13, "total_points": 52, "visibility_pct": 25.0 }, "geometry": { "type": "Point", "coordinates": [ -2.095651744982189, 53.714621339143171 ] } },
{ "type": "Feature", "properties": { "visible_points": 14, "total_points": 52, "visibility_pct": 26.923076923076923 }, "geometry": { "type": "Point", "coordinates": [ -2.095441794530991, 53.714621508944951 ] } },
{ "type": "Feature", "properties": { "visible_points": 13, "total_points": 49, "visibility_pct": 26.530612244897959 }, "geometry": { "type": "Point", "coordinates": [ -2.095231844077707, 53.714621678378855 ] } },
{ "type": "Feature", "properties": { "visible_points": 0, "total_points": 51, "visibility_pct": 0.0 }, "geometry": { "type": "Point", "coordinates": [ -2.095547018034719, 53.714729279234618 ] } },
{ "type": "Feature", "properties": { "visible_points": 0, "total_points": 48, "visibility_pct": 0.0 }, "geometry": { "type": "Point", "coordinates": [ -2.095337067049524, 53.714729448854406 ] } }
]
}
