{
"type": "FeatureCollection",
"name": "9b9a14f7c34a_visibility",
"crs": { "type": "name", "properties": { "name": "urn:ogc:def:crs:OGC:1.3:CRS84" } },
"features": [
{ "type": "Feature", "properties": { "visible_points": 2, "total_points": 52, "visibility_pct": 3.8461538461538463 }, "geometry": { "type": "Point", "coordinates": [ -2.111319686140889, 53.729384328393984 ] } },
{ "type": "Feature", "properties": { "visible_points": 3, "total_points": 55, "visibility_pct": 5.4545454545454541 }, "geometry": { "type": "Point", "coordinates": [ -2.111109666483256, 53.729384524193918 ] } },
{ "type": "Feature", "properties": { "visible_points": 0, "total_points": 51, "visibility_pct": 0.0 }, "geometry": { "type": "Point", "coordinates": [ -2.111424983593167, 53.729492085179174 ] } },
{ "type": "Feature", "properties": { "visible_points": 1, "total_points": 55, "visibility_pct": 1.8181818181818181 }, "geometry": { "type": "Point", "coordinates": [ -2.111214963415539, 53.729492281166642 ] } },
{ "type": "Feature", "properties": { "visible_points": 1, "total_points": 56, "visibility_pct": 1.7857142857142856 }, "geometry": { "type": "Point", "coordinates": [ -2.111004943235514, 53.729492476786028 ] } },
{ "type": "Feature", "properties": { "visible_points": 2, "total_points": 56, "visibility_pct": 3.5714285714285712 }, "geometry": { "type": "Point", "coordinates": [ -2.110794923053092, 53.72949267203731 ] } },
{ "type": "Feature", "properties": { "visible_points": 4, "total_points": 54, "visibility_pct": 7.4074074074074066 }, "geometry": { "type": "Point", "coordinates": [ -2.110584902868287, 53.729492866920516 ] } },
{ "type": "Feature", "properties": { "visible_points": 2, "total_points": 55, "visibility_pct": 3.6363636363636362 }, "geometry": { "type": "Point", "coordinates": [ -2.111320260870195, 53.729600038041902 ] } },
{ "type": "Feature", "properties": { "visible_points": 2, "total_points": 56, "visibility_pct": 3.5714285714285712 }, "geometry": { "type": "Point", "coordinates": [ -2.111110240170178, 53.729600233848799 ] } },
{ "type": "Feature", "properties": { "visible_points": 3, "total_points": 56, "visibility_pct": 5.3571428571428568 }, "geometry": { "type": "Point", "coordinates": [ -2.110900219467758, 53.729600429287622 ] } },
{ "type": "Feature", "properties": { "visible_points": 1, "total_points": 56, "visibility_pct": 1.7857142857142856 }, "geometry": { "type": "Point", "coordinates": [ -2.11069019876295, 53.729600624358348 ] } },
{ "type": "Feature", "properties": { "visible_points": 1, "total_points": 50, "visibility_pct": 2.0 }, "geometry": { "type": "Point", "coordinates": [ -2.11048017805576, 53.729600819060977 ] } },
{ "type": "Feature", "properties": { "visible_points": 1, "total_points": 52, "visibility_pct": 1.9230769230769231 }, "geometry": { "type": "Point", "coordinates": [ -2.111425558847237, 53.729707794819674 ] } },
{ "type": "Feature", "properties": { "visible_points": 1, "total_points": 56, "visibility_pct": 1.7857142857142856 }, "geometry": { "type": "Point", "coordinates": [ -2.111215537627214, 53.729707990814113 ] } },
{ "type": "Feature", "properties": { "visible_points": 2, "total_points": 56, "visibility_pct": 3.5714285714285712 }, "geometry": { "type": "Point", "coordinates": [ -2.111005516404801, 53.729708186440455 ] } },
{ "type": "Feature", "properties": { "visible_points": 0, "total_points": 56, "visibility_pct": 0.0 }, "geometry": { "type": "Point", "coordinates": [ -2.110795495179988, 53.729708381698714 ] } },
{ "type": "Feature", "properties": { "visible_points": 0, "total_points": 53, "visibility_pct": 0.0 }, "geometry": { "type": "Point", "coordinates": [ -2.110585473952792, 53.729708576588884 ] } },
{ "type": "Feature", "properties": { "visible_points": 0, "total_points": 45, "visibility_pct": 0.0 }, "geometry": { "type": "Point", "coordinates": [ -2.110375452723206, 53.72970877111095 ] } },
{ "type": "Feature", "properties": { "visible_points": 0, "total_points": 54, "visibility_pct": 0.0 }, "geometry": { "type": "Point", "coordinates": [ -2.111320835606641, 53.729815747681982 ] } },
{ "type": "Feature", "properties": { "visible_points": 1, "total_points": 56, "visibility_pct": 1.7857142857142856 }, "geometry": { "type": "Point", "coordinates": [ -2.111110813864219, 53.729815943495836 ] } },
{ "type": "Feature", "properties": { "visible_points": 2, "total_points": 55, "visibility_pct": 3.6363636363636362 }, "geometry": { "type": "Point", "coordinates": [ -2.110900792119404, 53.729816138941629 ] } },
{ "type": "Feature", "properties": { "visible_points": 0, "total_points": 52, "visibility_pct": 0.0 }, "geometry": { "type": "Point", "coordinates": [ -2.110690770372199, 53.729816334019326 ] } },
{ "type": "Feature", "properties": { "visible_points": 1, "total_points": 46, "visibility_pct": 2.1739130434782608 }, "geometry": { "type": "Point", "coordinates": [ -2.110480748622606, 53.729816528728925 ] } }
]
}
