{
"type": "FeatureCollection",
"name": "db95dc08dc22_visibility",
"crs": { "type": "name", "properties": { "name": "urn:ogc:def:crs:OGC:1.3:CRS84" } },
"features": [
{ "type": "Feature", "properties": { "visible_points": 0, "total_points": 54, "visibility_pct": 0.0 }, "geometry": { "type": "Point", "coordinates": [ -1.577956807506476, 53.462956019001439 ] } },
{ "type": "Feature", "properties": { "visible_points": 0, "total_points": 59, "visibility_pct": 0.0 }, "geometry": { "type": "Point", "coordinates": [ -1.577748110069755, 53.462955283653741 ] } },
{ "type": "Feature", "properties": { "visible_points": 1, "total_points": 61, "visibility_pct": 1.639344262295082 }, "geometry": { "type": "Point", "coordinates": [ -1.577539412642599, 53.462954547941401 ] } },
{ "type": "Feature", "properties": { "visible_points": 0, "total_points": 61, "visibility_pct": 0.0 }, "geometry": { "type": "Point", "coordinates": [ -1.57733071522502, 53.462953811864402 ] } },
{ "type": "Feature", "properties": { "visible_points": 0, "total_points": 56, "visibility_pct": 0.0 }, "geometry": { "type": "Point", "coordinates": [ -1.577122017817015, 53.462953075422718 ] } },
{ "type": "Feature", "properties": { "visible_points": 1, "total_points": 49, "visibility_pct": 2.0408163265306123 }, "geometry": { "type": "Point", "coordinates": [ -1.576913320418594, 53.46295233861639 ] } },
{ "type": "Feature", "properties": { "visible_points": 0, "total_points": 51, "visibility_pct": 0.0 }, "geometry": { "type": "Point", "coordinates": [ -1.578060087128123, 53.463064244404713 ] } },
{ "type": "Feature", "properties": { "visible_points": 0, "total_points": 58, "visibility_pct": 0.0 }, "geometry": { "type": "Point", "coordinates": [ -1.577851389134027, 53.463063509245977 ] } },
{ "type": "Feature", "properties": { "visible_points": 1, "total_points": 61, "visibility_pct": 1.639344262295082 }, "geometry": { "type": "Point", "coordinates": [ -1.577642691149501, 53.463062773722584 ] } },
{ "type": "Feature", "properties": { "visible_points": 1, "total_points": 61, "visibility_pct": 1.639344262295082 }, "geometry": { "type": "Point", "coordinates": [ -1.577433993174546, 53.463062037834504 ] } },
{ "type": "Feature", "properties": { "visible_points": 1, "total_points": 61, "visibility_pct": 1.639344262295082 }, "geometry": { "type": "Point", "coordinates": [ -1.577225295209162, 53.463061301581789 ] } },
{ "type": "Feature", "properties": { "visible_points": 1, "total_points": 54, "visibility_pct": 1.8518518518518516 }, "geometry": { "type": "Point", "coordinates": [ -1.57701659725336, 53.463060564964401 ] } },
{ "type": "Feature", "properties": { "visible_points": 0, "total_points": 54, "visibility_pct": 0.0 }, "geometry": { "type": "Point", "coordinates": [ -1.577954668746099, 53.463171734738545 ] } },
{ "type": "Feature", "properties": { "visible_points": 0, "total_points": 61, "visibility_pct": 0.0 }, "geometry": { "type": "Point", "coordinates": [ -1.5777459702042, 53.463170999404092 ] } },
{ "type": "Feature", "properties": { "visible_points": 0, "total_points": 61, "visibility_pct": 0.0 }, "geometry": { "type": "Point", "coordinates": [ -1.577537271671861, 53.463170263704981 ] } },
{ "type": "Feature", "properties": { "visible_points": 0, "total_points": 61, "visibility_pct": 0.0 }, "geometry": { "type": "Point", "coordinates": [ -1.577328573149099, 53.463169527641213 ] } },
{ "type": "Feature", "properties": { "visible_points": 0, "total_points": 58, "visibility_pct": 0.0 }, "geometry": { "type": "Point", "coordinates": [ -1.577119874635914, 53.463168791212766 ] } },
{ "type": "Feature", "properties": { "visible_points": 0, "total_points": 51, "visibility_pct": 0.0 }, "geometry": { "type": "Point", "coordinates": [ -1.576911176132312, 53.463168054419668 ] } },
{ "type": "Feature", "properties": { "visible_points": 0, "total_points": 56, "visibility_pct": 0.0 }, "geometry": { "type": "Point", "coordinates": [ -1.577849249806693, 53.463279224985968 ] } },
{ "type": "Feature", "properties": { "visible_points": 0, "total_points": 61, "visibility_pct": 0.0 }, "geometry": { "type": "Point", "coordinates": [ -1.577640550716978, 53.463278489475805 ] } },
{ "type": "Feature", "properties": { "visible_points": 0, "total_points": 61, "visibility_pct": 0.0 }, "geometry": { "type": "Point", "coordinates": [ -1.577431851636831, 53.463277753600977 ] } },
{ "type": "Feature", "properties": { "visible_points": 0, "total_points": 59, "visibility_pct": 0.0 }, "geometry": { "type": "Point", "coordinates": [ -1.577223152566261, 53.463277017361484 ] } },
{ "type": "Feature", "properties": { "visible_points": 0, "total_points": 56, "visibility_pct": 0.0 }, "geometry": { "type": "Point", "coordinates": [ -1.577743830309895, 53.463386715146953 ] } }
]
}
