{
"type": "FeatureCollection",
"name": "DONCA_113_toilets",
"crs": { "type": "name", "properties": { "name": "urn:ogc:def:crs:OGC:1.3:CRS84" } },
"features": [
{ "type": "Feature", "properties": { "name": "Mexborough Station", "payment_info": "Free", "accessible": "False", "radar": "False", "women": "Unknown", "men": "Unknown", "baby_change": "False", "Mon": "Unknown", "Tue": "Unknown", "Wed": "Unknown", "Thu": "Unknown", "Fri": "Unknown", "Sat": "Unknown", "Sun": "Unknown", "index_right": 8, "park_offical_id": "DONCA_113" }, "geometry": { "type": "Point", "coordinates": [ -1.28854394, 53.490851016 ] } }
]
}
