{
"type": "FeatureCollection",
"name": "ece0b488dafb_visibility",
"crs": { "type": "name", "properties": { "name": "urn:ogc:def:crs:OGC:1.3:CRS84" } },
"features": [
{ "type": "Feature", "properties": { "visible_points": 0, "total_points": 49, "visibility_pct": 0.0 }, "geometry": { "type": "Point", "coordinates": [ -0.419711684551852, 54.268816871861063 ] } },
{ "type": "Feature", "properties": { "visible_points": 0, "total_points": 54, "visibility_pct": 0.0 }, "geometry": { "type": "Point", "coordinates": [ -0.419499012915949, 54.268814085561424 ] } },
{ "type": "Feature", "properties": { "visible_points": 0, "total_points": 55, "visibility_pct": 0.0 }, "geometry": { "type": "Point", "coordinates": [ -0.419286341315828, 54.268811298886639 ] } },
{ "type": "Feature", "properties": { "visible_points": 1, "total_points": 55, "visibility_pct": 1.8181818181818181 }, "geometry": { "type": "Point", "coordinates": [ -0.419073669751484, 54.268808511836696 ] } },
{ "type": "Feature", "properties": { "visible_points": 0, "total_points": 53, "visibility_pct": 0.0 }, "geometry": { "type": "Point", "coordinates": [ -0.41886099822293, 54.268805724411635 ] } },
{ "type": "Feature", "properties": { "visible_points": 0, "total_points": 47, "visibility_pct": 0.0 }, "geometry": { "type": "Point", "coordinates": [ -0.419813898771135, 54.268926069205975 ] } },
{ "type": "Feature", "properties": { "visible_points": 0, "total_points": 54, "visibility_pct": 0.0 }, "geometry": { "type": "Point", "coordinates": [ -0.419601226570308, 54.268923283084987 ] } },
{ "type": "Feature", "properties": { "visible_points": 0, "total_points": 55, "visibility_pct": 0.0 }, "geometry": { "type": "Point", "coordinates": [ -0.419388554405258, 54.268920496588891 ] } },
{ "type": "Feature", "properties": { "visible_points": 1, "total_points": 55, "visibility_pct": 1.8181818181818181 }, "geometry": { "type": "Point", "coordinates": [ -0.419175882275987, 54.268917709717634 ] } },
{ "type": "Feature", "properties": { "visible_points": 2, "total_points": 55, "visibility_pct": 3.6363636363636362 }, "geometry": { "type": "Point", "coordinates": [ -0.4189632101825, 54.268914922471232 ] } },
{ "type": "Feature", "properties": { "visible_points": 3, "total_points": 50, "visibility_pct": 6.0 }, "geometry": { "type": "Point", "coordinates": [ -0.418750538124808, 54.268912134849693 ] } },
{ "type": "Feature", "properties": { "visible_points": 0, "total_points": 51, "visibility_pct": 0.0 }, "geometry": { "type": "Point", "coordinates": [ -0.4197034407538, 54.269032480521624 ] } },
{ "type": "Feature", "properties": { "visible_points": 0, "total_points": 55, "visibility_pct": 0.0 }, "geometry": { "type": "Point", "coordinates": [ -0.419490768023821, 54.269029694204193 ] } },
{ "type": "Feature", "properties": { "visible_points": 1, "total_points": 55, "visibility_pct": 1.8181818181818181 }, "geometry": { "type": "Point", "coordinates": [ -0.419278095329617, 54.269026907511616 ] } },
{ "type": "Feature", "properties": { "visible_points": 2, "total_points": 55, "visibility_pct": 3.6363636363636362 }, "geometry": { "type": "Point", "coordinates": [ -0.419065422671197, 54.269024120443888 ] } },
{ "type": "Feature", "properties": { "visible_points": 0, "total_points": 51, "visibility_pct": 0.0 }, "geometry": { "type": "Point", "coordinates": [ -0.418852750048564, 54.269021333001028 ] } },
{ "type": "Feature", "properties": { "visible_points": 1, "total_points": 55, "visibility_pct": 1.8181818181818181 }, "geometry": { "type": "Point", "coordinates": [ -0.419380308912378, 54.269136105218635 ] } },
{ "type": "Feature", "properties": { "visible_points": 0, "total_points": 55, "visibility_pct": 0.0 }, "geometry": { "type": "Point", "coordinates": [ -0.419167635689024, 54.269133318329573 ] } },
{ "type": "Feature", "properties": { "visible_points": 0, "total_points": 52, "visibility_pct": 0.0 }, "geometry": { "type": "Point", "coordinates": [ -0.418954962501449, 54.269130531065393 ] } },
{ "type": "Feature", "properties": { "visible_points": 1, "total_points": 47, "visibility_pct": 2.1276595744680851 }, "geometry": { "type": "Point", "coordinates": [ -0.418742289349672, 54.269127743426047 ] } },
{ "type": "Feature", "properties": { "visible_points": 0, "total_points": 46, "visibility_pct": 0.0 }, "geometry": { "type": "Point", "coordinates": [ -0.418844501766744, 54.269236941582143 ] } }
]
}
