{
"type": "FeatureCollection",
"name": "ROTH5_37",
"crs": { "type": "name", "properties": { "name": "urn:ogc:def:crs:OGC:1.3:CRS84" } },
"features": [
{ "type": "Feature", "properties": { "osm_id": 11486629069, "name": null, "amenity": "bench", "man_made": null, "leisure": null, "playground": null, "memorial": null }, "geometry": { "type": "Point", "coordinates": [ -1.3468756, 53.4304773 ] } },
{ "type": "Feature", "properties": { "osm_id": 11486628769, "name": null, "amenity": "bench", "man_made": null, "leisure": null, "playground": null, "memorial": null }, "geometry": { "type": "Point", "coordinates": [ -1.3462331, 53.4308629 ] } },
{ "type": "Feature", "properties": { "osm_id": 11486628669, "name": null, "amenity": "bench", "man_made": null, "leisure": null, "playground": null, "memorial": null }, "geometry": { "type": "Point", "coordinates": [ -1.3460199, 53.4311212 ] } }
]
}
