{
"type": "FeatureCollection",
"name": "39bfdb08ae85_visibility",
"crs": { "type": "name", "properties": { "name": "urn:ogc:def:crs:OGC:1.3:CRS84" } },
"features": [
{ "type": "Feature", "properties": { "visible_points": 1, "total_points": 37, "visibility_pct": 2.7027027027027026 }, "geometry": { "type": "Point", "coordinates": [ -1.771431278526054, 53.763499600479363 ] } },
{ "type": "Feature", "properties": { "visible_points": 10, "total_points": 43, "visibility_pct": 23.255813953488371 }, "geometry": { "type": "Point", "coordinates": [ -1.771221090063736, 53.76349920060759 ] } },
{ "type": "Feature", "properties": { "visible_points": 14, "total_points": 47, "visibility_pct": 29.787234042553191 }, "geometry": { "type": "Point", "coordinates": [ -1.771010901606668, 53.763498800367223 ] } },
{ "type": "Feature", "properties": { "visible_points": 14, "total_points": 49, "visibility_pct": 28.571428571428569 }, "geometry": { "type": "Point", "coordinates": [ -1.770800713154863, 53.763498399758248 ] } },
{ "type": "Feature", "properties": { "visible_points": 5, "total_points": 42, "visibility_pct": 11.904761904761903 }, "geometry": { "type": "Point", "coordinates": [ -1.771325595440089, 53.763607255677464 ] } },
{ "type": "Feature", "properties": { "visible_points": 11, "total_points": 47, "visibility_pct": 23.404255319148938 }, "geometry": { "type": "Point", "coordinates": [ -1.77111540642319, 53.763606855624673 ] } },
{ "type": "Feature", "properties": { "visible_points": 18, "total_points": 49, "visibility_pct": 36.734693877551024 }, "geometry": { "type": "Point", "coordinates": [ -1.770905217411554, 53.763606455203281 ] } },
{ "type": "Feature", "properties": { "visible_points": 20, "total_points": 49, "visibility_pct": 40.816326530612244 }, "geometry": { "type": "Point", "coordinates": [ -1.770695028405174, 53.763606054413287 ] } },
{ "type": "Feature", "properties": { "visible_points": 16, "total_points": 49, "visibility_pct": 32.653061224489797 }, "geometry": { "type": "Point", "coordinates": [ -1.770484839404062, 53.763605653254722 ] } },
{ "type": "Feature", "properties": { "visible_points": 15, "total_points": 45, "visibility_pct": 33.333333333333329 }, "geometry": { "type": "Point", "coordinates": [ -1.770274650408221, 53.763605251727562 ] } },
{ "type": "Feature", "properties": { "visible_points": 13, "total_points": 49, "visibility_pct": 26.530612244897959 }, "geometry": { "type": "Point", "coordinates": [ -1.771009722222816, 53.763714510550948 ] } },
{ "type": "Feature", "properties": { "visible_points": 17, "total_points": 49, "visibility_pct": 34.693877551020407 }, "geometry": { "type": "Point", "coordinates": [ -1.770799532656595, 53.763714109948545 ] } },
{ "type": "Feature", "properties": { "visible_points": 18, "total_points": 49, "visibility_pct": 36.734693877551024 }, "geometry": { "type": "Point", "coordinates": [ -1.770589343095647, 53.763713708977562 ] } },
{ "type": "Feature", "properties": { "visible_points": 15, "total_points": 46, "visibility_pct": 32.608695652173914 }, "geometry": { "type": "Point", "coordinates": [ -1.770379153539963, 53.763713307637957 ] } },
{ "type": "Feature", "properties": { "visible_points": 10, "total_points": 41, "visibility_pct": 24.390243902439025 }, "geometry": { "type": "Point", "coordinates": [ -1.770168963989553, 53.763712905929779 ] } },
{ "type": "Feature", "properties": { "visible_points": 16, "total_points": 49, "visibility_pct": 32.653061224489797 }, "geometry": { "type": "Point", "coordinates": [ -1.770693847341799, 53.763821764603016 ] } },
{ "type": "Feature", "properties": { "visible_points": 15, "total_points": 46, "visibility_pct": 32.608695652173914 }, "geometry": { "type": "Point", "coordinates": [ -1.770483657226271, 53.763821363451001 ] } },
{ "type": "Feature", "properties": { "visible_points": 14, "total_points": 42, "visibility_pct": 33.333333333333329 }, "geometry": { "type": "Point", "coordinates": [ -1.770273467116018, 53.763820961930371 ] } },
{ "type": "Feature", "properties": { "visible_points": 14, "total_points": 45, "visibility_pct": 31.111111111111111 }, "geometry": { "type": "Point", "coordinates": [ -1.770588161467159, 53.763929419166701 ] } },
{ "type": "Feature", "properties": { "visible_points": 12, "total_points": 41, "visibility_pct": 29.268292682926827 }, "geometry": { "type": "Point", "coordinates": [ -1.77037797079705, 53.763929017833647 ] } }
]
}
