{
"type": "FeatureCollection",
"name": "f608920f68cb_visibility",
"crs": { "type": "name", "properties": { "name": "urn:ogc:def:crs:OGC:1.3:CRS84" } },
"features": [
{ "type": "Feature", "properties": { "visible_points": 2, "total_points": 54, "visibility_pct": 3.7037037037037033 }, "geometry": { "type": "Point", "coordinates": [ -1.8550533595965, 53.792495809327512 ] } },
{ "type": "Feature", "properties": { "visible_points": 5, "total_points": 54, "visibility_pct": 9.2592592592592595 }, "geometry": { "type": "Point", "coordinates": [ -1.85484302397187, 53.792495555144583 ] } },
{ "type": "Feature", "properties": { "visible_points": 3, "total_points": 54, "visibility_pct": 5.5555555555555554 }, "geometry": { "type": "Point", "coordinates": [ -1.854632688350513, 53.792495300592684 ] } },
{ "type": "Feature", "properties": { "visible_points": 3, "total_points": 51, "visibility_pct": 5.8823529411764701 }, "geometry": { "type": "Point", "coordinates": [ -1.854422352732435, 53.792495045671835 ] } },
{ "type": "Feature", "properties": { "visible_points": 0, "total_points": 48, "visibility_pct": 0.0 }, "geometry": { "type": "Point", "coordinates": [ -1.855368493646762, 53.7926040440436 ] } },
{ "type": "Feature", "properties": { "visible_points": 0, "total_points": 54, "visibility_pct": 0.0 }, "geometry": { "type": "Point", "coordinates": [ -1.855158157471206, 53.792603790414887 ] } },
{ "type": "Feature", "properties": { "visible_points": 3, "total_points": 54, "visibility_pct": 5.5555555555555554 }, "geometry": { "type": "Point", "coordinates": [ -1.854947821298919, 53.792603536417239 ] } },
{ "type": "Feature", "properties": { "visible_points": 2, "total_points": 54, "visibility_pct": 3.7037037037037033 }, "geometry": { "type": "Point", "coordinates": [ -1.854737485129909, 53.792603282050621 ] } },
{ "type": "Feature", "properties": { "visible_points": 0, "total_points": 54, "visibility_pct": 0.0 }, "geometry": { "type": "Point", "coordinates": [ -1.854527148964177, 53.79260302731506 ] } },
{ "type": "Feature", "properties": { "visible_points": 0, "total_points": 50, "visibility_pct": 0.0 }, "geometry": { "type": "Point", "coordinates": [ -1.854316812801731, 53.79260277221055 ] } },
{ "type": "Feature", "properties": { "visible_points": 0, "total_points": 44, "visibility_pct": 0.0 }, "geometry": { "type": "Point", "coordinates": [ -1.855473292613485, 53.792712024850694 ] } },
{ "type": "Feature", "properties": { "visible_points": 1, "total_points": 52, "visibility_pct": 1.9230769230769231 }, "geometry": { "type": "Point", "coordinates": [ -1.855262955890276, 53.792711771407269 ] } },
{ "type": "Feature", "properties": { "visible_points": 4, "total_points": 54, "visibility_pct": 7.4074074074074066 }, "geometry": { "type": "Point", "coordinates": [ -1.855052619170334, 53.79271151759491 ] } },
{ "type": "Feature", "properties": { "visible_points": 1, "total_points": 54, "visibility_pct": 1.8518518518518516 }, "geometry": { "type": "Point", "coordinates": [ -1.854842282453669, 53.792711263413594 ] } },
{ "type": "Feature", "properties": { "visible_points": 1, "total_points": 54, "visibility_pct": 1.8518518518518516 }, "geometry": { "type": "Point", "coordinates": [ -1.854631945740281, 53.792711008863321 ] } },
{ "type": "Feature", "properties": { "visible_points": 0, "total_points": 53, "visibility_pct": 0.0 }, "geometry": { "type": "Point", "coordinates": [ -1.85442160903017, 53.792710753944093 ] } },
{ "type": "Feature", "properties": { "visible_points": 0, "total_points": 52, "visibility_pct": 0.0 }, "geometry": { "type": "Point", "coordinates": [ -1.855157417586126, 53.792819498677588 ] } },
{ "type": "Feature", "properties": { "visible_points": 0, "total_points": 54, "visibility_pct": 0.0 }, "geometry": { "type": "Point", "coordinates": [ -1.854947080321796, 53.79281924468156 ] } },
{ "type": "Feature", "properties": { "visible_points": 1, "total_points": 54, "visibility_pct": 1.8518518518518516 }, "geometry": { "type": "Point", "coordinates": [ -1.854736743060746, 53.792818990316569 ] } },
{ "type": "Feature", "properties": { "visible_points": 1, "total_points": 54, "visibility_pct": 1.8518518518518516 }, "geometry": { "type": "Point", "coordinates": [ -1.854526405802971, 53.792818735582621 ] } },
{ "type": "Feature", "properties": { "visible_points": 1, "total_points": 48, "visibility_pct": 2.083333333333333 }, "geometry": { "type": "Point", "coordinates": [ -1.854316068548487, 53.792818480479724 ] } },
{ "type": "Feature", "properties": { "visible_points": 1, "total_points": 53, "visibility_pct": 1.8867924528301887 }, "geometry": { "type": "Point", "coordinates": [ -1.854631203120142, 53.792926717126178 ] } }
]
}
