{
"type": "FeatureCollection",
"name": "KIRKL_104",
"crs": { "type": "name", "properties": { "name": "urn:ogc:def:crs:OGC:1.3:CRS84" } },
"features": [
{ "type": "Feature", "properties": { "osm_id": 982564520, "name": null, "amenity": "bench", "man_made": null, "leisure": null, "playground": null, "memorial": null }, "geometry": { "type": "Point", "coordinates": [ -1.6471661, 53.6892776 ] } },
{ "type": "Feature", "properties": { "osm_id": 982564540, "name": null, "amenity": "bench", "man_made": null, "leisure": null, "playground": null, "memorial": null }, "geometry": { "type": "Point", "coordinates": [ -1.6478064, 53.68999 ] } }
]
}
