{
"type": "FeatureCollection",
"name": "BRADF_144",
"crs": { "type": "name", "properties": { "name": "urn:ogc:def:crs:OGC:1.3:CRS84" } },
"features": [
{ "type": "Feature", "properties": { "osm_id": 12907614307, "name": null, "amenity": "bench", "man_made": null, "leisure": null, "playground": null, "memorial": null }, "geometry": { "type": "Point", "coordinates": [ -1.8302899, 53.9286644 ] } },
{ "type": "Feature", "properties": { "osm_id": 11905108570, "name": null, "amenity": "bench", "man_made": null, "leisure": null, "playground": null, "memorial": null }, "geometry": { "type": "Point", "coordinates": [ -1.8281403, 53.9286701 ] } },
{ "type": "Feature", "properties": { "osm_id": 11905068687, "name": null, "amenity": "bench", "man_made": null, "leisure": null, "playground": null, "memorial": null }, "geometry": { "type": "Point", "coordinates": [ -1.8283736, 53.928673 ] } },
{ "type": "Feature", "properties": { "osm_id": 11905074050, "name": null, "amenity": "bench", "man_made": null, "leisure": null, "playground": null, "memorial": null }, "geometry": { "type": "Point", "coordinates": [ -1.8284215, 53.9286762 ] } },
{ "type": "Feature", "properties": { "osm_id": 11905077386, "name": null, "amenity": "bench", "man_made": null, "leisure": null, "playground": null, "memorial": null }, "geometry": { "type": "Point", "coordinates": [ -1.8281556, 53.9286795 ] } },
{ "type": "Feature", "properties": { "osm_id": 11905085509, "name": null, "amenity": "bench", "man_made": null, "leisure": null, "playground": null, "memorial": null }, "geometry": { "type": "Point", "coordinates": [ -1.8285056, 53.928682 ] } },
{ "type": "Feature", "properties": { "osm_id": 11905046145, "name": null, "amenity": "bench", "man_made": null, "leisure": null, "playground": null, "memorial": null }, "geometry": { "type": "Point", "coordinates": [ -1.8282019, 53.928685 ] } },
{ "type": "Feature", "properties": { "osm_id": 11905068426, "name": null, "amenity": "bench", "man_made": null, "leisure": null, "playground": null, "memorial": null }, "geometry": { "type": "Point", "coordinates": [ -1.8282415, 53.9286899 ] } },
{ "type": "Feature", "properties": { "osm_id": 12907603020, "name": null, "amenity": "bench", "man_made": null, "leisure": null, "playground": null, "memorial": null }, "geometry": { "type": "Point", "coordinates": [ -1.8303714, 53.9286955 ] } },
{ "type": "Feature", "properties": { "osm_id": 11905077385, "name": null, "amenity": "bench", "man_made": null, "leisure": null, "playground": null, "memorial": null }, "geometry": { "type": "Point", "coordinates": [ -1.8282798, 53.9287005 ] } },
{ "type": "Feature", "properties": { "osm_id": 11905114770, "name": null, "amenity": "bench", "man_made": null, "leisure": null, "playground": null, "memorial": null }, "geometry": { "type": "Point", "coordinates": [ -1.8283189, 53.9287024 ] } },
{ "type": "Feature", "properties": { "osm_id": 11905109192, "name": null, "amenity": "bench", "man_made": null, "leisure": null, "playground": null, "memorial": null }, "geometry": { "type": "Point", "coordinates": [ -1.8283581, 53.9287087 ] } },
{ "type": "Feature", "properties": { "osm_id": 11905046144, "name": null, "amenity": "bench", "man_made": null, "leisure": null, "playground": null, "memorial": null }, "geometry": { "type": "Point", "coordinates": [ -1.8295205, 53.928772 ] } },
{ "type": "Feature", "properties": { "osm_id": 8940012986, "name": null, "amenity": "bench", "man_made": null, "leisure": null, "playground": null, "memorial": null }, "geometry": { "type": "Point", "coordinates": [ -1.830098, 53.9287767 ] } },
{ "type": "Feature", "properties": { "osm_id": 11905076162, "name": null, "amenity": "bench", "man_made": null, "leisure": null, "playground": null, "memorial": null }, "geometry": { "type": "Point", "coordinates": [ -1.8296219, 53.9287791 ] } },
{ "type": "Feature", "properties": { "osm_id": 11905072506, "name": null, "amenity": "bench", "man_made": null, "leisure": null, "playground": null, "memorial": null }, "geometry": { "type": "Point", "coordinates": [ -1.8299018, 53.9287807 ] } },
{ "type": "Feature", "properties": { "osm_id": 11905112825, "name": null, "amenity": "bench", "man_made": null, "leisure": null, "playground": null, "memorial": null }, "geometry": { "type": "Point", "coordinates": [ -1.8297272, 53.9287842 ] } },
{ "type": "Feature", "properties": { "osm_id": 11905079401, "name": null, "amenity": "bench", "man_made": null, "leisure": null, "playground": null, "memorial": null }, "geometry": { "type": "Point", "coordinates": [ -1.8299978, 53.9287878 ] } },
{ "type": "Feature", "properties": { "osm_id": 8789461738, "name": null, "amenity": "bench", "man_made": null, "leisure": null, "playground": null, "memorial": null }, "geometry": { "type": "Point", "coordinates": [ -1.8302361, 53.9287963 ] } }
]
}
