{
"type": "FeatureCollection",
"name": "ROTH5_1_toilets",
"crs": { "type": "name", "properties": { "name": "urn:ogc:def:crs:OGC:1.3:CRS84" } },
"features": [
{ "type": "Feature", "properties": { "name": "Swinton South Yorks Station", "payment_info": "Free", "accessible": "False", "radar": "False", "women": "Unknown", "men": "Unknown", "baby_change": "False", "Mon": "Unknown", "Tue": "Unknown", "Wed": "Unknown", "Thu": "Unknown", "Fri": "Unknown", "Sat": "Unknown", "Sun": "Unknown", "index_right": 1, "park_offical_id": "ROTH5_1" }, "geometry": { "type": "Point", "coordinates": [ -1.305629611, 53.485576624 ] } }
]
}
