{
"type": "FeatureCollection",
"name": "BARNS_66",
"crs": { "type": "name", "properties": { "name": "urn:ogc:def:crs:OGC:1.3:CRS84" } },
"features": [
{ "type": "Feature", "properties": { "osm_id": 12729546738, "name": null, "amenity": "bench", "man_made": null, "leisure": null, "playground": null, "memorial": null }, "geometry": { "type": "Point", "coordinates": [ -1.4608545, 53.5320046 ] } },
{ "type": "Feature", "properties": { "osm_id": 12729546740, "name": null, "amenity": "bench", "man_made": null, "leisure": null, "playground": null, "memorial": null }, "geometry": { "type": "Point", "coordinates": [ -1.4593724, 53.5322828 ] } },
{ "type": "Feature", "properties": { "osm_id": 12729546739, "name": null, "amenity": "bench", "man_made": null, "leisure": null, "playground": null, "memorial": null }, "geometry": { "type": "Point", "coordinates": [ -1.4605575, 53.5323541 ] } },
{ "type": "Feature", "properties": { "osm_id": 12729546741, "name": null, "amenity": null, "man_made": null, "leisure": "picnic_table", "playground": null, "memorial": null }, "geometry": { "type": "Point", "coordinates": [ -1.4601934, 53.5327373 ] } },
{ "type": "Feature", "properties": { "osm_id": 12729546743, "name": null, "amenity": "bench", "man_made": null, "leisure": null, "playground": null, "memorial": null }, "geometry": { "type": "Point", "coordinates": [ -1.461006, 53.5327548 ] } },
{ "type": "Feature", "properties": { "osm_id": 12729546742, "name": null, "amenity": null, "man_made": null, "leisure": "picnic_table", "playground": null, "memorial": null }, "geometry": { "type": "Point", "coordinates": [ -1.4604011, 53.5328031 ] } }
]
}
