{
"type": "FeatureCollection",
"name": "BARNS_74",
"crs": { "type": "name", "properties": { "name": "urn:ogc:def:crs:OGC:1.3:CRS84" } },
"features": [
{ "type": "Feature", "properties": { "osm_id": 13138428507, "name": null, "amenity": "bench", "man_made": null, "leisure": null, "playground": null, "memorial": null }, "geometry": { "type": "Point", "coordinates": [ -1.4936447, 53.5653551 ] } },
{ "type": "Feature", "properties": { "osm_id": 13138428506, "name": null, "amenity": "bench", "man_made": null, "leisure": null, "playground": null, "memorial": null }, "geometry": { "type": "Point", "coordinates": [ -1.4936338, 53.5655903 ] } },
{ "type": "Feature", "properties": { "osm_id": 12089551154, "name": null, "amenity": "bench", "man_made": null, "leisure": null, "playground": null, "memorial": null }, "geometry": { "type": "Point", "coordinates": [ -1.4933306, 53.5659928 ] } },
{ "type": "Feature", "properties": { "osm_id": 12089551156, "name": null, "amenity": "bench", "man_made": null, "leisure": null, "playground": null, "memorial": null }, "geometry": { "type": "Point", "coordinates": [ -1.4937712, 53.5660115 ] } },
{ "type": "Feature", "properties": { "osm_id": 12089551155, "name": null, "amenity": "bench", "man_made": null, "leisure": null, "playground": null, "memorial": null }, "geometry": { "type": "Point", "coordinates": [ -1.4933192, 53.5660149 ] } },
{ "type": "Feature", "properties": { "osm_id": 12089551153, "name": null, "amenity": null, "man_made": null, "leisure": "picnic_table", "playground": null, "memorial": null }, "geometry": { "type": "Point", "coordinates": [ -1.4933755, 53.5660171 ] } },
{ "type": "Feature", "properties": { "osm_id": 12089551157, "name": null, "amenity": "bench", "man_made": null, "leisure": null, "playground": null, "memorial": null }, "geometry": { "type": "Point", "coordinates": [ -1.4937363, 53.5660737 ] } }
]
}
