{
"type": "FeatureCollection",
"name": "BARNS_67",
"crs": { "type": "name", "properties": { "name": "urn:ogc:def:crs:OGC:1.3:CRS84" } },
"features": [
{ "type": "Feature", "properties": { "osm_id": 4375775179, "name": "Earls Seat", "amenity": "bench", "man_made": null, "leisure": null, "playground": null, "memorial": null }, "geometry": { "type": "Point", "coordinates": [ -1.5213542, 53.5222953 ] } },
{ "type": "Feature", "properties": { "osm_id": 13752091155, "name": null, "amenity": "bench", "man_made": null, "leisure": null, "playground": null, "memorial": null }, "geometry": { "type": "Point", "coordinates": [ -1.514998, 53.5174558 ] } },
{ "type": "Feature", "properties": { "osm_id": 13752091154, "name": null, "amenity": "bench", "man_made": null, "leisure": null, "playground": null, "memorial": null }, "geometry": { "type": "Point", "coordinates": [ -1.5153304, 53.5175038 ] } },
{ "type": "Feature", "properties": { "osm_id": 12980097409, "name": null, "amenity": "bench", "man_made": null, "leisure": null, "playground": null, "memorial": null }, "geometry": { "type": "Point", "coordinates": [ -1.5150976, 53.5175788 ] } },
{ "type": "Feature", "properties": { "osm_id": 6943140496, "name": null, "amenity": "bench", "man_made": null, "leisure": null, "playground": null, "memorial": null }, "geometry": { "type": "Point", "coordinates": [ -1.5135919, 53.5179332 ] } },
{ "type": "Feature", "properties": { "osm_id": 6942961884, "name": null, "amenity": "bench", "man_made": null, "leisure": null, "playground": null, "memorial": null }, "geometry": { "type": "Point", "coordinates": [ -1.5115441, 53.519615 ] } },
{ "type": "Feature", "properties": { "osm_id": 6943140493, "name": null, "amenity": "bench", "man_made": null, "leisure": null, "playground": null, "memorial": null }, "geometry": { "type": "Point", "coordinates": [ -1.5100223, 53.519879 ] } },
{ "type": "Feature", "properties": { "osm_id": 6943127396, "name": null, "amenity": "bench", "man_made": null, "leisure": null, "playground": null, "memorial": null }, "geometry": { "type": "Point", "coordinates": [ -1.5097189, 53.5216757 ] } },
{ "type": "Feature", "properties": { "osm_id": 6943069974, "name": null, "amenity": "bench", "man_made": null, "leisure": null, "playground": null, "memorial": null }, "geometry": { "type": "Point", "coordinates": [ -1.5087502, 53.5224698 ] } },
{ "type": "Feature", "properties": { "osm_id": 6943235428, "name": null, "amenity": "bench", "man_made": null, "leisure": null, "playground": null, "memorial": null }, "geometry": { "type": "Point", "coordinates": [ -1.517003, 53.5225846 ] } },
{ "type": "Feature", "properties": { "osm_id": 12980093968, "name": null, "amenity": "bench", "man_made": null, "leisure": null, "playground": null, "memorial": null }, "geometry": { "type": "Point", "coordinates": [ -1.5110328, 53.5248788 ] } },
{ "type": "Feature", "properties": { "osm_id": 12980098803, "name": null, "amenity": "bench", "man_made": null, "leisure": null, "playground": null, "memorial": null }, "geometry": { "type": "Point", "coordinates": [ -1.5171285, 53.525649 ] } },
{ "type": "Feature", "properties": { "osm_id": 6943235435, "name": null, "amenity": "bench", "man_made": null, "leisure": null, "playground": null, "memorial": null }, "geometry": { "type": "Point", "coordinates": [ -1.5155443, 53.5261884 ] } },
{ "type": "Feature", "properties": { "osm_id": 12980077722, "name": null, "amenity": "bench", "man_made": null, "leisure": null, "playground": null, "memorial": null }, "geometry": { "type": "Point", "coordinates": [ -1.5135105, 53.5271348 ] } },
{ "type": "Feature", "properties": { "osm_id": 6948520836, "name": null, "amenity": "bench", "man_made": null, "leisure": null, "playground": null, "memorial": null }, "geometry": { "type": "Point", "coordinates": [ -1.5201324, 53.5225315 ] } }
]
}
